Workbook
Name Emissions: #REF!
Name Emissions: #REF!
Name Emissions: #REF!
Name Emissions: #REF!
Name Emissions: #REF!
Name Emissions: #REF!
Name Emissions: #REF!
Name Emissions: #REF!
Name Emissions: #REF!
Name Emissions: #REF!
Name Emissions: #REF!
Name Fuels: [1]Data!$C$2:$C$24
Name Fuels: [1]Data!$C$2:$C$24
Name Fuels: [1]Data!$C$2:$C$24
Name Fuels: #REF!
Name Fuels: #REF!
Name Fuels: [2]Data!$C$2:$C$24
Name Fuels: [1]Data!$C$2:$C$24
Name Fuels: #REF!
Name Fuels: #REF!
Name Fuels: [1]Data!$C$2:$C$24
Name Fuels: #REF!
Name Fuels: [3]Data!$C$2:$C$24
Name Fuels: [3]Data!$C$2:$C$24
Name Fuels: [2]Data!$C$2:$C$24
Name Fuels: [2]Data!$C$2:$C$24
Name Fuels: #REF!
Name Regions: [1]Data!$G$2:$G$11
Name Regions: [1]Data!$G$2:$G$11
Name Regions: [1]Data!$G$2:$G$11
Name Regions: #REF!
Name Regions: #REF!
Name Regions: [2]Data!$G$2:$G$11
Name Regions: [1]Data!$G$2:$G$11
Name Regions: #REF!
Name Regions: #REF!
Name Regions: [1]Data!$G$2:$G$11
Name Regions: #REF!
Name Regions: [3]Data!$G$2:$G$11
Name Regions: [3]Data!$G$2:$G$11
Name Regions: [2]Data!$G$2:$G$11
Name Regions: [2]Data!$G$2:$G$11
Name Regions: #REF!
Name Storages: #REF!
Name Storages: #REF!
Name Storages: #REF!
Name Storages: #REF!
Name Storages: #REF!
Name Storages: #REF!
Name Storages: #REF!
Name Storages: #REF!
Name Storages: #REF!
Name Storages: #REF!
Name Storages: #REF!
Name Technologies: #REF!:B
Name Technologies: #REF!:B
Name Technologies: #REF!:B
Name Technologies: #REF!:B
Name Technologies: [2]Data!#REF!:B
Name Technologies: [4]Data!$B$2:$B$83

Sheet Sets
A1: Emission | B1: Technology | C1: Fuel | D1: Year | E1: Timeslice | F1: Mode_of_operation | G1: Region | H1: Season | I1: Daytype | J1: Daylitimebracket | K1: Storage | L1: ModalType | M1: obsolete | N1: Sectors
A2: CO2 | B2: A_Air | C2: Area_Rooftop_Commercial | D2: 2018 | E2: Q1M | F2: 1 | G2: AT | H2: 1 | I2: 1 | J2: 1 | K2: S_PHS | L2: MT_PSNG_ROAD | M2: HHT_Biomass | N2: Power
B3: A_Rooftop_Commercial | C3: Area_Rooftop_Residential | D3: 2025 | E3: Q1P | F3: 2 | G3: BE | H3: 2 | J3: 2 | K3: S_Gas_H2 | L3: MT_PSNG_RAIL | M3: HHT_Coal_Hardcoal | N3: Industry
B4: A_Rooftop_Residential | C4: Biomass | D4: 2030 | E4: Q1A | F4: 3 | G4: BG | H4: 3 | J4: 3 | K4: S_Battery_Li-Ion | L4: MT_PSNG_AIR | M4: HHT_Coal_Lignite | N4: Buildings
B5: CHP_Biomass_Solid | C5: Hardcoal | D5: 2035 | E5: Q1N | F5: 4 | G5: CH | H5: 4 | J5: 4 | K5: S_Battery_Redox | L5: MT_PSNG_ROAD_RE | M5: HHT_Electric_Furnace | N5: Transportation
B6: CHP_Biomass_Solid_CCS | C6: H2 | D6: 2040 | E6: Q2M | G6: CZ | K6: S_Heat_HLR | L6: MT_PSNG_RAIL_RE | M6: HHT_Gas | N6: Resources
B7: CHP_Coal_Hardcoal | C7: Gas_Natural | D7: 2045 | E7: Q2P | G7: DE | K7: S_Heat_HLI | L7: MT_PSNG_AIR_RE | M7: HHT_Geothermal | N7: Storages
B8: CHP_Coal_Hardcoal_CCS | C8: Nuclear | D8: 2050 | E8: Q2A | G8: DK | K8: S_CAES | L8: MT_PSNG_ROAD_CONV | M8: HHT_Oil | N8: Transformation
B9: CHP_Coal_Lignite | C9: Oil | E9: Q2N | G9: EE | K9: S_Gas_Methane | L9: MT_PSNG_RAIL_CONV | M9: HHT_H2 | N9: CHP
B10: CHP_Coal_Lignite_CCS | C10: Power | E10: Q3M | G10: ES | L10: MT_PSNG_AIR_CONV | M10: HLT_Biomass
B11: CHP_Gas_CCGT_Biogas | C11: Mobility_Freight | E11: Q3P | G11: FI | L11: MT_FRT_ROAD | M11: HLT_Coal_Hardcoal
B12: CHP_Gas_CCGT_Biogas_CCS | C12: Mobility_Passenger | E12: Q3A | G12: FR | L12: MT_FRT_RAIL | M12: HLT_Coal_Lignite
B13: CHP_Gas_CCGT_Natural | C13: Lignite | E13: Q3N | G13: GR | L13: MT_FRT_ROAD_RE | M13: HLT_Electric_Furnace
B14: CHP_Gas_CCGT_Natural_CCS | C14: Gas_Bio | E14: Q4M | G14: HR | L14: MT_FRT_ROAD_CONV | M14: HLT_Gas
B15: CHP_Gas_CCGT_SynGas | C15: Gas_Synth | E15: Q4P | G15: HU | L15: MT_FRT_RAIL_RE | M15: HLT_Geothermal
B16: CHP_Hydrogen_FuelCell | C16: Heat_Low_Residential | E16: Q4A | G16: IE | L16: MT_FRT_RAIL_CONV | M16: HLT_Heatpump
B17: CHP_Oil | C17: Heat_Low_Industrial | E17: Q4N | G17: IT | L17: MT_FRT_SHIP | M17: HLT_Oil
B18: D_Battery_Li-Ion | C18: Heat_Medium_Industrial | G18: LT | L18: MT_FRT_SHIP_CONV | M18: HLT_Rooftop_Commercial
B19: D_Battery_Redox | C19: Heat_High_Industrial | G19: LU | L19: MT_FRT_SHIP_RE | M19: HLT_Rooftop_Residential
B20: D_CAES | C20: Biofuel | G20: LV | M20: CHP_Nuclear
B21: D_Gas_H2 | C21: Powerfuel | G21: NL | M21: CHP_Biomass
B22: D_Gas_Methane | C22: LNG | G22: NO | M22: CHP_Coal_Hardcoal
B23: D_Heat_HLI | C23: LBG | G23: PL | M23: CHP_Coal_Lignite
B24: D_Heat_HLR | C24: LSG | G24: PT | M24: CHP_Gas
B25: D_PHS | C25: LH2 | G25: RO
B26: D_PHS_Residual | C26: Air | G26: SE
B27: FRT_Rail_Conv | C27: Powerfuel | G27: SI
B28: FRT_Rail_Electric | C28: DAC_Dummy | G28: SK
B29: FRT_Road_BEV | C29: ETS | G29: TR
B30: FRT_Road_H2 | C30: ETS_Source | G30: UK
B31: FRT_Road_ICE | C31: Heat_District | G31: NONEU_Balkan
B32: FRT_Road_LNG
B33: FRT_Road_OH
B34: FRT_Road_PHEV
B35: FRT_Ship_Bio
B36: FRT_Ship_Conv
B37: FRT_Ship_LNG
B38: HLI_Convert_DH
B39: HLR_Convert_DH
B40: HHI_BF_BOF
B41: HHI_BF_BOF_CCS
B42: HHI_Bio_BF_BOF
B43: HHI_DRI_EAF
... B145: Z_Import_Oil

Sheet Par_DaySplit
A1: YearSplit{l in TIMESLICE, y in YEAR} Units: Fraction of 8760 hours
A2: The fraction of the year in each time slice.
A3: Unit: Fraction of 8760 hours
A5: Year | B5: Q1N | C5: Q1M | D5: Q1P | E5: Q1A | F5: Q2N | G5: Q2M | H5: Q2P | I5: Q2A | J5: Q3N | K5: Q3M | L5: Q3P | M5: Q3A | N5: Q4N | O5: Q4M | P5: Q4P | Q5: Q4A
A6: 2018 | B6: 0.0016552511 | C6: 0.00017123288 | D6: 0.000456621 | E6: 0.000456621 | F6: 0.00091324201 | G6: 0.00034246575 | H6: 0.00091324201 | I6: 0.00057077626 | J6: 0.0010844749 | K6: 0.0002283105 | L6: 0.00079908676 | M6: 0.00062785388 | N6: 0.0017694064 | O6: 0.00039954338 | P6: 0.00028538813 | Q6: 0.00028538813
A7: 2020 | B7: 0.0016552511 | C7: 0.00017123288 | D7: 0.000456621 | E7: 0.000456621 | F7: 0.00091324201 | G7: 0.00034246575 | H7: 0.00091324201 | I7: 0.00057077626 | J7: 0.0010844749 | K7: 0.0002283105 | L7: 0.00079908676 | M7: 0.00062785388 | N7: 0.0017694064 | O7: 0.00039954338 | P7: 0.00028538813 | Q7: 0.00028538813
A8: 2025 | B8: 0.0016552511 | C8: 0.00017123288 | D8: 0.000456621 | E8: 0.000456621 | F8: 0.00091324201 | G8: 0.00034246575 | H8: 0.00091324201 | I8: 0.00057077626 | J8: 0.0010844749 | K8: 0.0002283105 | L8: 0.00079908676 | M8: 0.00062785388 | N8: 0.0017694064 | O8: 0.00039954338 | P8: 0.00028538813 | Q8: 0.00028538813
A9: 2030 | B9: 0.0016552511 | C9: 0.00017123288 | D9: 0.000456621 | E9: 0.000456621 | F9: 0.00091324201 | G9: 0.00034246575 | H9: 0.00091324201 | I9: 0.00057077626 | J9: 0.0010844749 | K9: 0.0002283105 | L9: 0.00079908676 | M9: 0.00062785388 | N9: 0.0017694064 | O9: 0.00039954338 | P9: 0.00028538813 | Q9: 0.00028538813
A10: 2035 | B10: 0.0016552511 | C10: 0.00017123288 | D10: 0.000456621 | E10: 0.000456621 | F10: 0.00091324201 | G10: 0.00034246575 | H10: 0.00091324201 | I10: 0.00057077626 | J10: 0.0010844749 | K10: 0.0002283105 | L10: 0.00079908676 | M10: 0.00062785388 | N10: 0.0017694064 | O10: 0.00039954338 | P10: 0.00028538813 | Q10: 0.00028538813
A11: 2040 | B11: 0.0016552511 | C11: 0.00017123288 | D11: 0.000456621 | E11: 0.000456621 | F11: 0.00091324201 | G11: 0.00034246575 | H11: 0.00091324201 | I11: 0.00057077626 | J11: 0.0010844749 | K11: 0.0002283105 | L11: 0.00079908676 | M11: 0.00062785388 | N11: 0.0017694064 | O11: 0.00039954338 | P11: 0.00028538813 | Q11: 0.00028538813
A12: 2045 | B12: 0.0016552511 | C12: 0.00017123288 | D12: 0.000456621 | E12: 0.000456621 | F12: 0.00091324201 | G12: 0.00034246575 | H12: 0.00091324201 | I12: 0.00057077626 | J12: 0.0010844749 | K12: 0.0002283105 | L12: 0.00079908676 | M12: 0.00062785388 | N12: 0.0017694064 | O12: 0.00039954338 | P12: 0.00028538813 | Q12: 0.00028538813
A13: 2050 | B13: 0.0016552511 | C13: 0.00017123288 | D13: 0.000456621 | E13: 0.000456621 | F13: 0.00091324201 | G13: 0.00034246575 | H13: 0.00091324201 | I13: 0.00057077626 | J13: 0.0010844749 | K13: 0.0002283105 | L13: 0.00079908676 | M13: 0.00062785388 | N13: 0.0017694064 | O13: 0.00039954338 | P13: 0.00028538813 | Q13: 0.00028538813

Sheet Par_YearSplit
A1: YearSplit{l in TIMESLICE, y in YEAR}
A2: The fraction of the year in each time slice.
A3: Unit: Fraction of 8760 hours
A5: Timeslice | B5: 2018 | C5: 2020 | D5: 2025 | E5: 2030 | F5: 2035 | G5: 2040 | H5: 2045 | I5: 2050
A6: Q1N | B6: 0.15104167 | C6: 0.15104167 | D6: 0.15104167 | E6: 0.15104167 | F6: 0.15104167 | G6: 0.15104167 | H6: 0.15104167 | I6: 0.15104167
A7: Q1M | B7: 0.015625 | C7: 0.015625 | D7: 0.015625 | E7: 0.015625 | F7: 0.015625 | G7: 0.015625 | H7: 0.015625 | I7: 0.015625
A8: Q1P | B8: 0.041666667 | C8: 0.041666667 | D8: 0.041666667 | E8: 0.041666667 | F8: 0.041666667 | G8: 0.041666667 | H8: 0.041666667 | I8: 0.041666667
A9: Q1A | B9: 0.041666667 | C9: 0.041666667 | D9: 0.041666667 | E9: 0.041666667 | F9: 0.041666667 | G9: 0.041666667 | H9: 0.041666667 | I9: 0.041666667
A10: Q2N | B10: 0.083333333 | C10: 0.083333333 | D10: 0.083333333 | E10: 0.083333333 | F10: 0.083333333 | G10: 0.083333333 | H10: 0.083333333 | I10: 0.083333333
A11: Q2M | B11: 0.03125 | C11: 0.03125 | D11: 0.03125 | E11: 0.03125 | F11: 0.03125 | G11: 0.03125 | H11: 0.03125 | I11: 0.03125
A12: Q2P | B12: 0.083333333 | C12: 0.083333333 | D12: 0.083333333 | E12: 0.083333333 | F12: 0.083333333 | G12: 0.083333333 | H12: 0.083333333 | I12: 0.083333333
A13: Q2A | B13: 0.052083333 | C13: 0.052083333 | D13: 0.052083333 | E13: 0.052083333 | F13: 0.052083333 | G13: 0.052083333 | H13: 0.052083333 | I13: 0.052083333
A14: Q3N | B14: 0.098958333 | C14: 0.098958333 | D14: 0.098958333 | E14: 0.098958333 | F14: 0.098958333 | G14: 0.098958333 | H14: 0.098958333 | I14: 0.098958333
A15: Q3M | B15: 0.020833333 | C15: 0.020833333 | D15: 0.020833333 | E15: 0.020833333 | F15: 0.020833333 | G15: 0.020833333 | H15: 0.020833333 | I15: 0.020833333
A16: Q3P | B16: 0.072916667 | C16: 0.072916667 | D16: 0.072916667 | E16: 0.072916667 | F16: 0.072916667 | G16: 0.072916667 | H16: 0.072916667 | I16: 0.072916667
... A21: Q4A | B21: 0.026041667 | C21: 0.026041667 | D21: 0.026041667 | E21: 0.026041667 | F21: 0.026041667 | G21: 0.026041667 | H21: 0.026041667 | I21: 0.026041667

Sheet Par_TagTechnologyToSector
A1: TagTechnologyToSector{t in TECHNOLOGY, se in SECTOR}
A2: Assigns Technologies to the different sectors.
A3: Unit: Binary
A5: Technology | B5: Power | C5: Industry | D5: Buildings | E5: Transportation | F5: Resources | G5: Storages | H5: Transformation | I5: CHP
A6: A_Rooftop_Commercial | F6: 1
A7: A_Rooftop_Residential | F7: 1
A8: D_Battery_Li-Ion | G8: 1
A9: D_Battery_Redox | G9: 1
A10: D_Gas_H2 | G10: 1
A11: D_Heat_HLR | G11: 1
A12: D_Heat_HLI | G12: 1
A13: D_PHS | G13: 1
A14: D_CAES | G14: 1
A15: FRT_Rail_Conv | E15: 1
A16: FRT_Rail_Electric | E16: 1
A17: FRT_Road_BEV | E17: 1
A18: FRT_Road_H2 | E18: 1
A19: FRT_Road_ICE | E19: 1
A20: FRT_Road_PHEV | E20: 1
A21: FRT_Road_OH | E21: 1
A22: FRT_Ship_Bio | E22: 1
A23: FRT_Ship_Conv | E23: 1
A24: P_Biomass | B24: 1
A25: P_Coal_Hardcoal | B25: 1
A26: P_Coal_Lignite | B26: 1
A27: P_Gas | B27: 1
A28: P_Nuclear | B28: 1
A29: P_Oil | B29: 1
A30: PSNG_Air_Bio | E30: 1
A31: PSNG_Air_Conv | E31: 1
A32: PSNG_Air_H2 | E32: 1
A33: PSNG_Rail_Conv | E33: 1
A34: PSNG_Rail_Electric | E34: 1
A35: PSNG_Road_BEV | E35: 1
A36: PSNG_Road_H2 | E36: 1
A37: PSNG_Road_ICE | E37: 1
A38: PSNG_Road_PHEV | E38: 1
A39: R_Coal_Hardcoal | F39: 1
A40: R_Coal_Lignite | F40: 1
A41: R_Gas | F41: 1
A42: R_Nuclear | F42: 1
A43: R_Oil | F43: 1
A44: RES_CSP | B44: 1
A45: RES_Geothermal | B45: 1
A46: RES_Hydro_Large | B46: 1
A47: RES_Hydro_Small | B47: 1
A48: RES_Ocean | B48: 1
A49: RES_PV_Rooftop_Commercial | B49: 1
A50: RES_PV_Rooftop_Residential | B50: 1
A51: RES_PV_Utility_Avg | B51: 1
A52: RES_PV_Utility_Inf | B52: 1
A53: RES_PV_Utility_Opt | B53: 1
A54: RES_Wind_Offshore_Transitional | B54: 1
A55: RES_Wind_Offshore_Shallow | B55: 1
... A59: RES_Wind_Onshore_Opt | B59: 1
A60: X_Electrolysis | H60: 1
A61: X_Fuel_Cell | H61: 1
A62: X_Methanation | H62: 1
A63: Z_Import_Hardcoal | F63: 1
A64: Z_Import_Gas | F64: 1
A65: Z_Import_Oil | F65: 1
A66: P_Biomass_CCS | B66: 1
A67: A_CCS_Capacity | F67: 1
A68: D_Gas_Methane | G68: 1
A69: HLR_Gas_Boiler | D69: 1
A70: HLR_Gas_CHP | B70: 1 | D70: 0
A71: HLR_Biomass | D71: 1
A72: HLR_Biomass_CHP | D72: 1
A73: HLR_Hardcoal | D73: 1
A74: HLR_Lignite | D74: 1
A75: HLR_Hardcoal_CHP | B75: 1 | D75: 0
A76: HLR_Lignite_CHP | B76: 1 | D76: 0
A77: HLR_Direct_Electric | D77: 1
A78: HLR_Solar_Thermal | D78: 1
A79: HLR_Heatpump_Aerial | D79: 1
A80: HLR_Heatpump_Ground | D80: 1
A81: HLR_Geothermal | D81: 1
A82: HLR_Oil_Boiler | D82: 1
A83: HLI_Gas_Boiler | C83: 1
A84: HLI_Gas_CHP | B84: 1 | C84: 0
A85: HLI_Biomass | C85: 1
A86: HLI_Biomass_CHP | B86: 1 | C86: 0
A87: HLI_Hardcoal | C87: 1
A88: HLI_Lignite | C88: 1
A89: HLI_Hardcoal_CHP | B89: 1 | C89: 0
A90: HLI_Lignite_CHP | B90: 1 | C90: 0
A91: HLI_Direct_Electric | C91: 1
A92: HLI_Solar_Thermal | C92: 1
A93: HLI_Fuelcell | C93: 1
A94: HLI_Geothermal | C94: 1
A95: HLI_Oil_Boiler | C95: 1
A96: HLI_Oil_CHP | B96: 1 | C96: 0
A97: HMI_Gas | C97: 1
A98: HMI_Biomass | C98: 1
A99: HMI_HardCoal | C99: 1
A100: HMI_Steam_Electric | C100: 1
A101: HMI_Oil | C101: 1
A102: HHI_BF_BOF | C102: 1
A103: HHI_DRI_EAF | C103: 1
A104: HHI_Scrap_EAF | C104: 1
...

Sheet Par_CapacityToActivityUnit
A1: CapacityToActivityUnit{r in REGION, t in TECHNOLOGY}
A2: Converts capacity to activity. Here we use a factor of 31.536, which is the level of energy production in PJ produced from 1 GW operating for 1 year (1GW * 8760 * 3600 / 10^6)
A3: Unit: PJ/GW-YR
A5: Region | B5: A_Rooftop_Commercial | C5: A_Rooftop_Residential | D5: D_Battery_Li-Ion | E5: D_Battery_Redox | F5: D_Gas_H2 | G5: D_Gas_Methane | H5: D_Heat_HLR | I5: D_Heat_HLI | J5: D_PHS | K5: D_PHS_Residual | L5: FRT_Rail_Conv | M5: FRT_Rail_Electric | N5: FRT_Road_BEV | O5: FRT_Road_H2 | P5: FRT_Road_ICE | Q5: FRT_Road_PHEV | R5: FRT_Road_OH | S5: FRT_Ship_Bio | T5: FRT_Ship_Conv | U5: P_Biomass | V5: P_Coal_Hardcoal | W5: P_Coal_Lignite | X5: P_Gas | Y5: P_Nuclear | Z5: P_Oil | AA5: PSNG_Air_Bio | AB5: PSNG_Air_Conv | AC5: PSNG_Air_H2 | AD5: PSNG_Rail_Conv | AE5: PSNG_Rail_Electric | AF5: PSNG_Road_BEV | AG5: PSNG_Road_H2 | AH5: PSNG_Road_ICE | AI5: PSNG_Road_PHEV | AJ5: R_Coal_Hardcoal | AK5: R_Coal_Lignite | AL5: R_Gas | AM5: R_Nuclear | AN5: R_Oil | AO5: RES_Biomass | AP5: RES_CSP | AQ5: RES_Geothermal | AR5: RES_Hydro_Large | AS5: RES_Hydro_Small | AT5: RES_Ocean | AU5: RES_PV_Rooftop_Commercial | AV5: RES_PV_Rooftop_Residential | AW5: RES_PV_Utility_Avg | AX5: RES_PV_Utility_Inf | AY5: RES_PV_Utility_Opt | AZ5: RES_Wind_Offshore_Transitional | BA5: RES_Wind_Offshore_Shallow | BB5: RES_Wind_Offshore_Deep | BC5: RES_Wind_Onshore_Avg | BD5: RES_Wind_Onshore_Inf | BE5: RES_Wind_Onshore_Opt | BF5: X_Electrolysis | BG5: X_Fuel_Cell | BH5: X_Methanation | BI5: Z_Import_Hardcoal | BJ5: Z_Import_Gas | BK5: Z_Import_Oil | BL5: HHT_H2 | BM5: D_CAES | BN5: CHP_Biomass_CCS | BO5: P_Biomass_CCS | BP5: A_CCS_Capacity | BQ5: D_Gas_Methane | BR5: HLR_Gas_Boiler | BS5: HLR_Gas_CHP | BT5: HLR_Biomass | BU5: HLR_Biomass_CHP | BV5: HLR_Hardcoal | BW5: HLR_Lignite | BX5: HLR_Hardcoal_CHP | BY5: HLR_Lignite_CHP | BZ5: HLR_Direct_Electric | CA5: HLR_Solar_Thermal | CB5: HLR_Heatpump_Aerial | CC5: HLR_Heatpump_Ground | CD5: HLR_Geothermal | CE5: HLR_Oil_Boiler | CF5: HLI_Gas_Boiler | CG5: HLI_Gas_CHP | CH5: HLI_Biomass | CI5: HLI_Biomass_CHP | CJ5: HLI_Hardcoal | CK5: HLI_Lignite | CL5: HLI_Hardcoal_CHP | CM5: HLI_Direct_Electric | CN5: HLI_Solar_Thermal | CO5: HLI_Fuelcell | CP5: HLI_Geothermal | CQ5: HLI_Oil_Boiler | CR5: HLI_Oil_CHP | CS5: HMI_Gas | CT5: HMI_Biomass | CU5: HMI_HardCoal | CV5: HMI_Steam_Electric | CW5: HMI_Oil | CX5: HHI_BF_BOF | CY5: HHI_DRI_EAF | CZ5: HHI_Scrap_EAF | DA5: HHI_H2DRI_EAF | DB5: HHI_Molten_Electrolysis | DC5: HHI_Bio_BF_BOF | DD5: HLI_Lignite_CHP | DE5: HHI_BF_BOF_CCS | DF5: HHI_DRI_EAF_CCS | DG5: HLI_Biomass_CHP_CCS | DH5: HLI_Hardcoal_CHP_CCS | DI5: HLI_Lignite_CHP_CCS | DJ5: HLR_Biomass_CHP_CCS | DK5: HLR_Hardcoal_CHP_CCS | DL5: HLR_Lignite_CHP_CCS | DM5: HMI_Gas_CCS | DN5: HMI_HardCoal_CCS | DO5: P_Coal_Hardcoal_CCS | DP5: P_Coal_Lignite_CCS | DQ5: P_Gas_CCS | DR5: X_SMR | DS5: X_SMR_CCS | DT5: X_DAC | DU5: A_Air | DV5: HLR_H2_Boiler | DW5: HLI_H2_Boiler | DX5: X_Biofuel | DY5: HMI_H2 | DZ5: X_Powerfuel | EA5: RES_Grass | EB5: RES_Wood | EC5: RES_Residues | ED5: RES_Paper_Cardboard | EE5: RES_Roundwood | EF5: RES_Biogas | EG5: X_Gasifier | EH5: X_Liquifier | EI5: FRT_Road_LNG | EJ5: FRT_Ship_LNG | EK5: PSNG_Road_LNG | EL5: P_H2_OCGT | EM5: A_Air | EN5: X_DAC_LT | EO5: X_DAC_HT | EP5: Z_Import_H2 | EQ5: Z_ETS_Buy | ER5: Z_ETS_Sell | ES5: CHP_Biomass_Solid | ET5: CHP_Coal_Hardcoal | EU5: CHP_Coal_Lignite | EV5: CHP_Gas_CCGT_Natural | EW5: CHP_Gas_CCGT_Biogas | EX5: CHP_Gas_CCGT_SynGas | EY5: CHP_Hydrogen_FuelCell | EZ5: CHP_Biomass_Solid_CCS | FA5: CHP_Coal_Hardcoal_CCS | FB5: CHP_Coal_Lignite_CCS | FC5: CHP_Gas_CCGT_Natural_CCS | FD5: CHP_Gas_CCGT_Biogas_CCS | FE5: HLI_Convert_DH | FF5: HLR_Convert_DH | FG5: CHP_Oil | FH5: P_Gas_CCGT | FI5: P_Gas_OCGT | FJ5: P_Gas_Engines | FK5: Res_PV_Utility_Tracking
A6: DE | B6: 1 | C6: 1 | D6: 31.536 | E6: 31.536 | F6: 31.536 | G6: 31.536 | H6: 31.536 | I6: 31.536 | J6: 31.536 | K6: 31.536 | L6: 1 | M6: 1 | N6: 1 | O6: 1 | P6: 1 | Q6: 1 | R6: 1 | S6: 1 | T6: 1 | U6: 31.536 | V6: 31.536 | W6: 31.536 | X6: 31.536 | Y6: 31.536 | Z6: 31.536 | AA6: 1 | AB6: 1 | AC6: 1 | AD6: 1 | AE6: 1 | AF6: 1 | AG6: 1 | AH6: 1 | AI6: 1 | AJ6: 31.536 | AK6: 31.536 | AL6: 31.536 | AM6: 31.536 | AN6: 31.536 | AO6: 0 | AP6: 31.536 | AQ6: 31.536 | AR6: 31.536 | AS6: 31.536 | AT6: 31.536 | AU6: 31.536 | AV6: 31.536 | AW6: 31.536 | AX6: 31.536 | AY6: 31.536 | AZ6: 31.536 | BA6: 31.536 | BB6: 31.536 | BC6: 31.536 | BD6: 31.536 | BE6: 31.536 | BF6: 31.536 | BG6: 31.536 | BH6: 31.536 | BI6: 31.536 | BJ6: 31.536 | BK6: 31.536 | BL6: 31.536 | BM6: 31.536 | BN6: 31.536 | BO6: 31.536 | BP6: 1 | BQ6: 1 | BR6: 31.536 | BS6: 31.536 | BT6: 31.536 | BU6: 31.536 | BV6: 31.536 | BW6: 31.536 | BX6: 31.536 | BY6: 31.536 | BZ6: 31.536 | CA6: 31.536 | CB6: 31.536 | CC6: 31.536 | CD6: 31.536 | CE6: 31.536 | CF6: 31.536 | CG6: 31.536 | CH6: 31.536 | CI6: 31.536 | CJ6: 31.536 | CK6: 31.536 | CL6: 31.536 | CM6: 31.536 | CN6: 31.536 | CO6: 31.536 | CP6: 31.536 | CQ6: 31.536 | CR6: 31.536 | CS6: 31.536 | CT6: 31.536 | CU6: 31.536 | CV6: 31.536 | CW6: 31.536 | CX6: 31.536 | CY6: 31.536 | CZ6: 31.536 | DA6: 31.536 | DB6: 31.536 | DC6: 31.536 | DD6: 31.536 | DE6: 31.536 | DF6: 31.536 | DG6: 31.536 | DH6: 31.536 | DI6: 31.536 | DJ6: 31.536 | DK6: 31.536 | DL6: 31.536 | DM6: 31.536 | DN6: 31.536 | DO6: 31.536 | DP6: 31.536 | DQ6: 31.536 | DR6: 31.536 | DS6: 31.536 | DT6: 31.536 | DU6: 1 | DV6: 31.536 | DW6: 31.536 | DX6: 31.536 | DY6: 31.536 | DZ6: 1 | EA6: 1 | EB6: 1 | EC6: 1 | ED6: 1 | EE6: 1 | EF6: 1 | EG6: 31.536 | EH6: 31.536 | EI6: 1 | EJ6: 1 | EK6: 1 | EL6: 31.536 | EM6: 1 | EN6: 1 | EO6: 1 | EP6: 31.536 | EQ6: 1 | ER6: 1 | ES6: 31.536 | ET6: 31.536 | EU6: 31.536 | EV6: 31.536 | EW6: 31.536 | EX6: 31.536 | EY6: 31.536 | EZ6: 31.536 | FA6: 31.536 | FB6: 31.536 | FC6: 31.536 | FD6: 31.536 | FE6: 1 | FF6: 1 | FG6: 31.536 | FH6: 31.536 | FI6: 31.536 | FJ6: 31.536 | FK6: 31.536

Sheet Par_Conversionls
A1: Conversionls{l in TIMESLICE, ls in SEASON}
A2: Set equal to 1 to assign a particular time slice to a season. Set equal to 0 in order not to assign a particular time slice to a season.
A3: Unit: Binary
A5: Timeslice | B5: 1 | C5: 2 | D5: 3 | E5: 4
A6: Q1N | B6: 1
A7: Q1M | B7: 1
A8: Q1P | B8: 1
A9: Q1A | B9: 1
A10: Q2N | C10: 1
A11: Q2M | C11: 1
A12: Q2P | C12: 1
A13: Q2A | C13: 1
A14: Q3N | D14: 1
A15: Q3M | D15: 1
A16: Q3P | D16: 1
A17: Q3A | D17: 1
A18: Q4N | E18: 1
A19: Q4M | E19: 1
A20: Q4P | E20: 1
A21: Q4A | E21: 1

Sheet Par_Conversionld
A1: Conversionld{l in TIMESLICE, ld in DAYTYPE}
A2: Set equal to 1 to assign a particular time slice to a day type. Set equal to 0 in order not to assign a particular time slice to a day type.
A3: Unit: Binary
A5: Timeslice | B5: 1
A6: Q1N | B6: 1
A7: Q1M | B7: 1
A8: Q1P | B8: 1
A9: Q1A | B9: 1
A10: Q2N | B10: 1
A11: Q2M | B11: 1
A12: Q2P | B12: 1
A13: Q2A | B13: 1
A14: Q3N | B14: 1
A15: Q3M | B15: 1
A16: Q3P | B16: 1
... A21: Q4A | B21: 1

Sheet Par_Conversionlh
A1: Conversionlh{l in TIMESLICE, lh in DAILYTIMEBRACKET}
A2: Set equal to 1 to assign a particular time slice to a daily time bracket. Set equal to 0 in order not to assign a particular time slice to a daily time bracket.
A3: Unit: Binary
B4: N | C4: M | D4: P | E4: A
A5: Timeslice | B5: 4 | C5: 1 | D5: 2 | E5: 3
A6: Q1N | B6: 1
A7: Q1M | C7: 1
A8: Q1P | D8: 1
A9: Q1A | E9: 1
A10: Q2N | B10: 1
A11: Q2M | C11: 1
A12: Q2P | D12: 1
A13: Q2A | E13: 1
A14: Q3N | B14: 1
A15: Q3M | C15: 1
A16: Q3P | D16: 1
A17: Q3A | E17: 1
A18: Q4N | B18: 1
A19: Q4M | C19: 1
A20: Q4P | D20: 1
A21: Q4A | E21: 1

Sheet Par_TradeRoute
A1: TradeRoute{f in FUEL, r in REGION1, rr in REGION2}
A2: Defines trade links between regions for specific fuels. If r is linked to rr, rr has also to be linked with r. Symmetrical matrix with diagonal of zeroes
A3: Unit: km
C5: FR | D5: AT | E5: BE | F5: BG | G5: CH | H5: CZ | I5: DE | J5: DK | K5: EE | L5: ES | M5: FI | N5: GR | O5: HR | P5: HU | Q5: IE | R5: IT | S5: LT | T5: LU | U5: LV | V5: NONEU_Balkan | W5: NL | X5: NO | Y5: PL | Z5: PT | AA5: RO | AB5: SE | AC5: SI | AD5: SK | AE5: UK | AF5: TR
A6: Biofuel | B6: AT | C6: 1462.5 | D6: 0 | E6: 770.24 | F6: 1022.45 | G6: 456.36 | H6: 254.84 | I6: 477.04 | J6: 973.03 | K6: 0 | L6: 1640.58 | M6: 0 | N6: 1188.01 | O6: 332.27 | P6: 400.59 | Q6: 0 | R6: 557.69 | S6: 1094.84 | T6: 640.32 | U6: 1264.26 | V6: 667.29 | W6: 804.24 | X6: 0 | Y6: 630.36 | Z6: 0 | AA6: 850.72 | AB6: 1698.79 | AC6: 171.24 | AD6: 416.67 | AE6: 1399.02 | AF6: 0
A7: Biofuel | B7: BE | C7: 300 | D7: 770.24 | E7: 0 | F7: 0 | G7: 501.4 | H7: 767.87 | I7: 406.5 | J7: 692.16 | K7: 0 | L7: 1325.38 | M7: 0 | N7: 0 | O7: 1075.07 | P7: 1146.05 | Q7: 924.14 | R7: 1040.22 | S7: 0 | T7: 140.4 | U7: 0 | V7: 0 | W7: 192.2 | X7: 1636.14 | Y7: 1037.53 | Z7: 0 | AA7: 0 | AB7: 1535.26 | AC7: 903.98 | AD7: 1089.56 | AE7: 645.59 | AF7: 0
A8: Biofuel | B8: BG | C8: 0 | D8: 1022.45 | E8: 0 | F8: 0 | G8: 1415.45 | H8: 1087.05 | I8: 1458.02 | J8: 0 | K8: 0 | L8: 0 | M8: 0 | N8: 453.95 | O8: 753.16 | P8: 671.18 | Q8: 0 | R8: 1075.51 | S8: 0 | T8: 0 | U8: 0 | V8: 489.51 | W8: 0 | X8: 0 | Y8: 1129.69 | Z8: 0 | AA8: 343.03 | AB8: 0 | AC8: 908.29 | AD8: 797.9 | AE8: 0 | AF8: 428
A9: Biofuel | B9: CH | C9: 350 | D9: 456.36 | E9: 501.4 | F9: 1415.45 | G9: 0 | H9: 619.89 | I9: 504.62 | J9: 1027.05 | K9: 0 | L9: 1204.01 | M9: 0 | N9: 0 | O9: 662.94 | P9: 850.87 | Q9: 0 | R9: 540.01 | S9: 0 | T9: 367.02 | U9: 0 | V9: 978.2 | W9: 637.55 | X9: 0 | Y9: 1001.53 | Z9: 0 | AA9: 1292.28 | AB9: 1857.41 | AC9: 511.84 | AD9: 869.38 | AE9: 1134.76 | AF9: 0
A10: Biofuel | B10: CZ | C10: 1630.33 | D10: 254.84 | E10: 767.87 | F10: 1087.05 | G10: 619.89 | H10: 0 | I10: 382.63 | J10: 777.76 | K10: 1194.05 | L10: 0 | M10: 0 | N10: 1334.1 | O10: 528.63 | P10: 415.87 | Q10: 0 | R10: 812.43 | S10: 850.9 | T10: 665.24 | U10: 1016.04 | V10: 829.38 | W10: 738.71 | X10: 1642 | Y10: 390.18 | Z10: 0 | AA10: 842.37 | AB10: 1454.22 | AC10: 404.31 | AD10: 323.69 | AE10: 1341.38 | AF10: 0
A11: Biofuel | B11: DE | C11: 500 | D11: 477.04 | E11: 406.5 | F11: 1458.02 | G11: 504.62 | H11: 382.63 | I11: 0 | J11: 540.49 | K11: 1281.04 | L11: 1624.96 | M11: 1750.79 | N11: 1662.66 | O11: 809.27 | P11: 790.13 | Q11: 1286.09 | R11: 934.15 | S11: 1015.33 | T11: 339.26 | U11: 1144.6 | V11: 1143.09 | W11: 356.15 | X11: 1503.63 | Y11: 633.87 | Z11: 0 | AA11: 1224.85 | AB11: 1354.27 | AC11: 643.65 | AD11: 705.3 | AE11: 959.53 | AF11: 0
A12: Biofuel | B12: DK | C12: 1789.51 | D12: 973.03 | E12: 692.16 | F12: 0 | G12: 1027.05 | H12: 777.76 | I12: 540.49 | J12: 0 | K12: 978.44 | L12: 0 | M12: 1298.09 | N12: 0 | O12: 1294.23 | P12: 1171.94 | Q12: 1213.43 | R12: 1472.56 | S12: 873.01 | T12: 737.81 | U12: 921.65 | V12: 0 | W12: 503.89 | X12: 700 | Y12: 745.5 | Z12: 0 | AA12: 1533.41 | AB12: 400 | AC12: 1144.12 | AD12: 1030.02 | AE12: 850.09 | AF12: 0
A13: Biofuel | B13: EE | C13: 0 | D13: 0 | E13: 0 | F13: 0 | G13: 0 | H13: 1194.05 | I13: 1281.04 | J13: 978.44 | K13: 0 | L13: 0 | M13: 647.91 | N13: 0 | O13: 0 | P13: 0 | Q13: 0 | R13: 0 | S13: 384.47 | T13: 0 | U13: 205.65 | V13: 0 | W13: 0 | X13: 885 | Y13: 825.43 | Z13: 0 | AA13: 0 | AB13: 661.72 | AC13: 0 | AD13: 1177.79 | AE13: 0 | AF13: 0
A14: Biofuel | B14: ES | C14: 229.59 | D14: 1640.58 | E14: 1325.38 | F14: 0 | G14: 1204.01 | H14: 0 | I14: 1624.96 | J14: 0 | K14: 0 | L14: 0 | M14: 0 | N14: 0 | O14: 1723.59 | P14: 0 | Q14: 1479.45 | R14: 1341.02 | S14: 0 | T14: 1307.36 | U14: 0 | V14: 0 | W14: 1513.18 | X14: 0 | Y14: 0 | Z14: 421.67 | AA14: 0 | AB14: 0 | AC14: 1632.96 | AD14: 0 | AE14: 1549.51 | AF14: 0
A15: Biofuel | B15: FI | C15: 0 | D15: 0 | E15: 0 | F15: 0 | G15: 0 | H15: 0 | I15: 1750.79 | J15: 1298.09 | K15: 647.91 | L15: 0 | M15: 0 | N15: 0 | O15: 0 | P15: 0 | Q15: 0 | R15: 0 | S15: 1026.31 | T15: 0 | U15: 852.16 | V15: 0 | W15: 0 | X15: 1000 | Y15: 1430.78 | Z15: 0 | AA15: 0 | AB15: 505.83 | AC15: 0 | AD15: 0 | AE15: 0 | AF15: 0
A16: Biofuel | B16: FR | C16: 0 | D16: 1462.5 | E16: 300 | F16: 0 | G16: 350 | H16: 1630.33 | I16: 500 | J16: 1789.51 | K16: 0 | L16: 229.59 | M16: 0 | N16: 2201.09 | O16: 1577.99 | P16: 1838.39 | Q16: 1284.49 | R16: 1000 | S16: 0 | T16: 1087.05 | U16: 0 | V16: 1809.09 | W16: 1285.66 | X16: 2702.36 | Y16: 2000.6 | Z16: 560.61 | AA16: 2252.62 | AB16: 2623.55 | AC16: 1472.14 | AD16: 1879.08 | AE16: 600 | AF16: 0
A17: Biofuel | B17: GR | C17: 2201.09 | D17: 1188.01 | E17: 0 | F17: 453.95 | G17: 0 | H17: 1334.1 | I17: 1662.66 | J17: 0 | K17: 0 | L17: 0 | M17: 0 | N17: 0 | O17: 859.98 | P17: 947.65 | Q17: 0 | R17: 1007.1 | S17: 0 | T17: 0 | U17: 0 | V17: 521.16 | W17: 0 | X17: 0 | Y17: 1480.09 | Z17: 0 | AA17: 772.6 | AB17: 0 | AC17: 1031.62 | AD17: 1109.61 | AE17: 0 | AF17: 868
... A455: ETS | B455: TR | C455: 1 | D455: 1 | E455: 1 | F455: 1 | G455: 1 | H455: 1 | I455: 1 | J455: 1 | K455: 1 | L455: 1 | M455: 1 | N455: 1 | O455: 1 | P455: 1 | Q455: 1 | R455: 1 | S455: 1 | T455: 1 | U455: 1 | V455: 1 | W455: 1 | X455: 1 | Y455: 1 | Z455: 1 | AA455: 1 | AB455: 1 | AC455: 1 | AD455: 1 | AE455: 1 | AF455: 0

Sheet Par_TradeCosts
A1: TradeCosts{f in FUEL, r in REGION1, rr in REGION2}
A2: Costs for trading a fuel from one region to another.
A3: Unit: M€/PJ
C5: FR | D5: AT | E5: BE | F5: BG | G5: CH | H5: CZ | I5: DE | J5: DK | K5: EE | L5: ES | M5: FI | N5: GR | O5: HR | P5: HU | Q5: IE | R5: IT | S5: LT | T5: LU | U5: LV | V5: NONEU_Balkan | W5: NL | X5: NO | Y5: PL | Z5: PT | AA5: RO | AB5: SE | AC5: SI | AD5: SK | AE5: UK | AF5: TR
A6: Distance | B6: AT | C6: =Par_TradeRoute!C6 -> 1462.5 | D6: =Par_TradeRoute!D6 -> 0 | E6: =Par_TradeRoute!E6 -> 770.24 | F6: =Par_TradeRoute!F6 -> 1022.45 | G6: =Par_TradeRoute!G6 -> 456.36 | H6: =Par_TradeRoute!H6 -> 254.84 | I6: =Par_TradeRoute!I6 -> 477.04 | J6: =Par_TradeRoute!J6 -> 973.03 | ... AF6: =Par_TradeRoute!AF6 -> 0
A7: Distance | B7: BE | C7: =Par_TradeRoute!C7 -> 300 | D7: =Par_TradeRoute!D7 -> 770.24 | E7: =Par_TradeRoute!E7 -> 0 | F7: =Par_TradeRoute!F7 -> 0 | G7: =Par_TradeRoute!G7 -> 501.4 | H7: =Par_TradeRoute!H7 -> 767.87 | I7: =Par_TradeRoute!I7 -> 406.5 | J7: =Par_TradeRoute!J7 -> 692.16 | ... AF7: =Par_TradeRoute!AF7 -> 0
A8: Distance | B8: BG | C8: =Par_TradeRoute!C8 -> 0 | D8: =Par_TradeRoute!D8 -> 1022.45 | E8: =Par_TradeRoute!E8 -> 0 | F8: =Par_TradeRoute!F8 -> 0 | G8: =Par_TradeRoute!G8 -> 1415.45 | H8: =Par_TradeRoute!H8 -> 1087.05 | I8: =Par_TradeRoute!I8 -> 1458.02 | J8: =Par_TradeRoute!J8 -> 0 | ... AF8: =Par_TradeRoute!AF8 -> 428
A9: Distance | B9: CH | C9: =Par_TradeRoute!C9 -> 350 | D9: =Par_TradeRoute!D9 -> 456.36 | E9: =Par_TradeRoute!E9 -> 501.4 | F9: =Par_TradeRoute!F9 -> 1415.45 | G9: =Par_TradeRoute!G9 -> 0 | H9: =Par_TradeRoute!H9 -> 619.89 | I9: =Par_TradeRoute!I9 -> 504.62 | J9: =Par_TradeRoute!J9 -> 1027.05 | ... AF9: =Par_TradeRoute!AF9 -> 0
A10: Distance | B10: CZ | C10: =Par_TradeRoute!C10 -> 1630.33 | D10: =Par_TradeRoute!D10 -> 254.84 | E10: =Par_TradeRoute!E10 -> 767.87 | F10: =Par_TradeRoute!F10 -> 1087.05 | G10: =Par_TradeRoute!G10 -> 619.89 | H10: =Par_TradeRoute!H10 -> 0 | I10: =Par_TradeRoute!I10 -> 382.63 | J10: =Par_TradeRoute!J10 -> 777.76 | ... AF10: =Par_TradeRoute!AF10 -> 0
A11: Distance | B11: DE | C11: =Par_TradeRoute!C11 -> 500 | D11: =Par_TradeRoute!D11 -> 477.04 | E11: =Par_TradeRoute!E11 -> 406.5 | F11: =Par_TradeRoute!F11 -> 1458.02 | G11: =Par_TradeRoute!G11 -> 504.62 | H11: =Par_TradeRoute!H11 -> 382.63 | I11: =Par_TradeRoute!I11 -> 0 | J11: =Par_TradeRoute!J11 -> 540.49 | ... AF11: =Par_TradeRoute!AF11 -> 0
A12: Distance | B12: DK | C12: =Par_TradeRoute!C12 -> 1789.51 | D12: =Par_TradeRoute!D12 -> 973.03 | E12: =Par_TradeRoute!E12 -> 692.16 | F12: =Par_TradeRoute!F12 -> 0 | G12: =Par_TradeRoute!G12 -> 1027.05 | H12: =Par_TradeRoute!H12 -> 777.76 | I12: =Par_TradeRoute!I12 -> 540.49 | J12: =Par_TradeRoute!J12 -> 0 | ... AF12: =Par_TradeRoute!AF12 -> 0
A13: Distance | B13: EE | C13: =Par_TradeRoute!C13 -> 0 | D13: =Par_TradeRoute!D13 -> 0 | E13: =Par_TradeRoute!E13 -> 0 | F13: =Par_TradeRoute!F13 -> 0 | G13: =Par_TradeRoute!G13 -> 0 | H13: =Par_TradeRoute!H13 -> 1194.05 | I13: =Par_TradeRoute!I13 -> 1281.04 | J13: =Par_TradeRoute!J13 -> 978.44 | ... AF13: =Par_TradeRoute!AF13 -> 0
A14: Distance | B14: ES | C14: =Par_TradeRoute!C14 -> 229.59 | D14: =Par_TradeRoute!D14 -> 1640.58 | E14: =Par_TradeRoute!E14 -> 1325.38 | F14: =Par_TradeRoute!F14 -> 0 | G14: =Par_TradeRoute!G14 -> 1204.01 | H14: =Par_TradeRoute!H14 -> 0 | I14: =Par_TradeRoute!I14 -> 1624.96 | J14: =Par_TradeRoute!J14 -> 0 | ... AF14: =Par_TradeRoute!AF14 -> 0
A15: Distance | B15: FI | C15: =Par_TradeRoute!C15 -> 0 | D15: =Par_TradeRoute!D15 -> 0 | E15: =Par_TradeRoute!E15 -> 0 | F15: =Par_TradeRoute!F15 -> 0 | G15: =Par_TradeRoute!G15 -> 0 | H15: =Par_TradeRoute!H15 -> 0 | I15: =Par_TradeRoute!I15 -> 1750.79 | J15: =Par_TradeRoute!J15 -> 1298.09 | ... AF15: =Par_TradeRoute!AF15 -> 0
A16: Distance | B16: FR | C16: =Par_TradeRoute!C16 -> 0 | D16: =Par_TradeRoute!D16 -> 1462.5 | E16: =Par_TradeRoute!E16 -> 300 | F16: =Par_TradeRoute!F16 -> 0 | G16: =Par_TradeRoute!G16 -> 350 | H16: =Par_TradeRoute!H16 -> 1630.33 | I16: =Par_TradeRoute!I16 -> 500 | J16: =Par_TradeRoute!J16 -> 1789.51 | ... AF16: =Par_TradeRoute!AF16 -> 0
A17: Distance | B17: GR | C17: =Par_TradeRoute!C17 -> 2201.09 | D17: =Par_TradeRoute!D17 -> 1188.01 | E17: =Par_TradeRoute!E17 -> 0 | F17: =Par_TradeRoute!F17 -> 453.95 | G17: =Par_TradeRoute!G17 -> 0 | H17: =Par_TradeRoute!H17 -> 1334.1 | I17: =Par_TradeRoute!I17 -> 1662.66 | J17: =Par_TradeRoute!J17 -> 0 | ... AF17: =Par_TradeRoute!AF17 -> 868
... A35: Distance | B35: UK | C35: =Par_TradeRoute!C35 -> 600 | D35: =Par_TradeRoute!D35 -> 1399.02 | E35: =Par_TradeRoute!E35 -> 645.59 | F35: =Par_TradeRoute!F35 -> 0 | G35: =Par_TradeRoute!G35 -> 1134.76 | H35: =Par_TradeRoute!H35 -> 1341.38 | I35: =Par_TradeRoute!I35 -> 959.53 | J35: =Par_TradeRoute!J35 -> 850.09 | ... AF35: =Par_TradeRoute!AF35 -> 0
A36: Hardcoal | B36: AT | C36: =ROUND(IF(C6>0, ((0.0014*C6+13.97)/1.15)*(10^12)/(1000*29308)/1000000, 0),3) -> 0.475 | D36: =ROUND(IF(D6>0, ((0.0014*D6+13.97)/1.15)*(10^12)/(1000*29308)/1000000, 0),3) -> 0 | E36: =ROUND(IF(E6>0, ((0.0014*E6+13.97)/1.15)*(10^12)/(1000*29308)/1000000, 0),3) -> 0.446 | F36: =ROUND(IF(F6>0, ((0.0014*F6+13.97)/1.15)*(10^12)/(1000*29308)/1000000, 0),3) -> 0.457 | G36: =ROUND(IF(G6>0, ((0.0014*G6+13.97)/1.15)*(10^12)/(1000*29308)/1000000, 0),3) -> 0.433 | H36: =ROUND(IF(H6>0, ((0.0014*H6+13.97)/1.15)*(10^12)/(1000*29308)/1000000, 0),3) -> 0.425 | I36: =ROUND(IF(I6>0, ((0.0014*I6+13.97)/1.15)*(10^12)/(1000*29308)/1000000, 0),3) -> 0.434 | J36: =ROUND(IF(J6>0, ((0.0014*J6+13.97)/1.15)*(10^12)/(1000*29308)/1000000, 0),3) -> 0.455 | ... AF36: =ROUND(IF(AF6>0, ((0.0014*AF6+13.97)/1.15)*(10^12)/(1000*29308)/1000000, 0),3) -> 0
A37: Hardcoal | B37: BE | C37: =ROUND(IF(C7>0, ((0.0014*C7+13.97)/1.15)*(10^12)/(1000*29308)/1000000, 0),3) -> 0.427 | D37: =ROUND(IF(D7>0, ((0.0014*D7+13.97)/1.15)*(10^12)/(1000*29308)/1000000, 0),3) -> 0.446 | E37: =ROUND(IF(E7>0, ((0.0014*E7+13.97)/1.15)*(10^12)/(1000*29308)/1000000, 0),3) -> 0 | F37: =ROUND(IF(F7>0, ((0.0014*F7+13.97)/1.15)*(10^12)/(1000*29308)/1000000, 0),3) -> 0 | G37: =ROUND(IF(G7>0, ((0.0014*G7+13.97)/1.15)*(10^12)/(1000*29308)/1000000, 0),3) -> 0.435 | H37: =ROUND(IF(H7>0, ((0.0014*H7+13.97)/1.15)*(10^12)/(1000*29308)/1000000, 0),3) -> 0.446 | I37: =ROUND(IF(I7>0, ((0.0014*I7+13.97)/1.15)*(10^12)/(1000*29308)/1000000, 0),3) -> 0.431 | J37: =ROUND(IF(J7>0, ((0.0014*J7+13.97)/1.15)*(10^12)/(1000*29308)/1000000, 0),3) -> 0.443 | ... AF37: =ROUND(IF(AF7>0, ((0.0014*AF7+13.97)/1.15)*(10^12)/(1000*29308)/1000000, 0),3) -> 0
A38: Hardcoal | B38: BG | C38: =ROUND(IF(C8>0, ((0.0014*C8+13.97)/1.15)*(10^12)/(1000*29308)/1000000, 0),3) -> 0 | D38: =ROUND(IF(D8>0, ((0.0014*D8+13.97)/1.15)*(10^12)/(1000*29308)/1000000, 0),3) -> 0.457 | E38: =ROUND(IF(E8>0, ((0.0014*E8+13.97)/1.15)*(10^12)/(1000*29308)/1000000, 0),3) -> 0 | F38: =ROUND(IF(F8>0, ((0.0014*F8+13.97)/1.15)*(10^12)/(1000*29308)/1000000, 0),3) -> 0 | G38: =ROUND(IF(G8>0, ((0.0014*G8+13.97)/1.15)*(10^12)/(1000*29308)/1000000, 0),3) -> 0.473 | H38: =ROUND(IF(H8>0, ((0.0014*H8+13.97)/1.15)*(10^12)/(1000*29308)/1000000, 0),3) -> 0.46 | I38: =ROUND(IF(I8>0, ((0.0014*I8+13.97)/1.15)*(10^12)/(1000*29308)/1000000, 0),3) -> 0.475 | J38: =ROUND(IF(J8>0, ((0.0014*J8+13.97)/1.15)*(10^12)/(1000*29308)/1000000, 0),3) -> 0 | ... AF38: =ROUND(IF(AF8>0, ((0.0014*AF8+13.97)/1.15)*(10^12)/(1000*29308)/1000000, 0),3) -> 0.432
A39: Hardcoal | B39: CH | C39: =ROUND(IF(C9>0, ((0.0014*C9+13.97)/1.15)*(10^12)/(1000*29308)/1000000, 0),3) -> 0.429 | D39: =ROUND(IF(D9>0, ((0.0014*D9+13.97)/1.15)*(10^12)/(1000*29308)/1000000, 0),3) -> 0.433 | E39: =ROUND(IF(E9>0, ((0.0014*E9+13.97)/1.15)*(10^12)/(1000*29308)/1000000, 0),3) -> 0.435 | F39: =ROUND(IF(F9>0, ((0.0014*F9+13.97)/1.15)*(10^12)/(1000*29308)/1000000, 0),3) -> 0.473 | G39: =ROUND(IF(G9>0, ((0.0014*G9+13.97)/1.15)*(10^12)/(1000*29308)/1000000, 0),3) -> 0 | H39: =ROUND(IF(H9>0, ((0.0014*H9+13.97)/1.15)*(10^12)/(1000*29308)/1000000, 0),3) -> 0.44 | I39: =ROUND(IF(I9>0, ((0.0014*I9+13.97)/1.15)*(10^12)/(1000*29308)/1000000, 0),3) -> 0.435 | J39: =ROUND(IF(J9>0, ((0.0014*J9+13.97)/1.15)*(10^12)/(1000*29308)/1000000, 0),3) -> 0.457 | ... AF39: =ROUND(IF(AF9>0, ((0.0014*AF9+13.97)/1.15)*(10^12)/(1000*29308)/1000000, 0),3) -> 0
A40: Hardcoal | B40: CZ | C40: =ROUND(IF(C10>0, ((0.0014*C10+13.97)/1.15)*(10^12)/(1000*29308)/1000000, 0),3) -> 0.482 | D40: =ROUND(IF(D10>0, ((0.0014*D10+13.97)/1.15)*(10^12)/(1000*29308)/1000000, 0),3) -> 0.425 | E40: =ROUND(IF(E10>0, ((0.0014*E10+13.97)/1.15)*(10^12)/(1000*29308)/1000000, 0),3) -> 0.446 | F40: =ROUND(IF(F10>0, ((0.0014*F10+13.97)/1.15)*(10^12)/(1000*29308)/1000000, 0),3) -> 0.46 | G40: =ROUND(IF(G10>0, ((0.0014*G10+13.97)/1.15)*(10^12)/(1000*29308)/1000000, 0),3) -> 0.44 | H40: =ROUND(IF(H10>0, ((0.0014*H10+13.97)/1.15)*(10^12)/(1000*29308)/1000000, 0),3) -> 0 | I40: =ROUND(IF(I10>0, ((0.0014*I10+13.97)/1.15)*(10^12)/(1000*29308)/1000000, 0),3) -> 0.43 | J40: =ROUND(IF(J10>0, ((0.0014*J10+13.97)/1.15)*(10^12)/(1000*29308)/1000000, 0),3) -> 0.447 | ... AF40: =ROUND(IF(AF10>0, ((0.0014*AF10+13.97)/1.15)*(10^12)/(1000*29308)/1000000, 0),3) -> 0
A41: Hardcoal | B41: DE | C41: =ROUND(IF(C11>0, ((0.0014*C11+13.97)/1.15)*(10^12)/(1000*29308)/1000000, 0),3) -> 0.435 | D41: =ROUND(IF(D11>0, ((0.0014*D11+13.97)/1.15)*(10^12)/(1000*29308)/1000000, 0),3) -> 0.434 | E41: =ROUND(IF(E11>0, ((0.0014*E11+13.97)/1.15)*(10^12)/(1000*29308)/1000000, 0),3) -> 0.431 | F41: =ROUND(IF(F11>0, ((0.0014*F11+13.97)/1.15)*(10^12)/(1000*29308)/1000000, 0),3) -> 0.475 | G41: =ROUND(IF(G11>0, ((0.0014*G11+13.97)/1.15)*(10^12)/(1000*29308)/1000000, 0),3) -> 0.435 | H41: =ROUND(IF(H11>0, ((0.0014*H11+13.97)/1.15)*(10^12)/(1000*29308)/1000000, 0),3) -> 0.43 | I41: =ROUND(IF(I11>0, ((0.0014*I11+13.97)/1.15)*(10^12)/(1000*29308)/1000000, 0),3) -> 0 | J41: =ROUND(IF(J11>0, ((0.0014*J11+13.97)/1.15)*(10^12)/(1000*29308)/1000000, 0),3) -> 0.437 | ... AF41: =ROUND(IF(AF11>0, ((0.0014*AF11+13.97)/1.15)*(10^12)/(1000*29308)/1000000, 0),3) -> 0
A42: Hardcoal | B42: DK | C42: =ROUND(IF(C12>0, ((0.0014*C12+13.97)/1.15)*(10^12)/(1000*29308)/1000000, 0),3) -> 0.489 | D42: =ROUND(IF(D12>0, ((0.0014*D12+13.97)/1.15)*(10^12)/(1000*29308)/1000000, 0),3) -> 0.455 | E42: =ROUND(IF(E12>0, ((0.0014*E12+13.97)/1.15)*(10^12)/(1000*29308)/1000000, 0),3) -> 0.443 | F42: =ROUND(IF(F12>0, ((0.0014*F12+13.97)/1.15)*(10^12)/(1000*29308)/1000000, 0),3) -> 0 | G42: =ROUND(IF(G12>0, ((0.0014*G12+13.97)/1.15)*(10^12)/(1000*29308)/1000000, 0),3) -> 0.457 | H42: =ROUND(IF(H12>0, ((0.0014*H12+13.97)/1.15)*(10^12)/(1000*29308)/1000000, 0),3) -> 0.447 | I42: =ROUND(IF(I12>0, ((0.0014*I12+13.97)/1.15)*(10^12)/(1000*29308)/1000000, 0),3) -> 0.437 | J42: =ROUND(IF(J12>0, ((0.0014*J12+13.97)/1.15)*(10^12)/(1000*29308)/1000000, 0),3) -> 0 | ... AF42: =ROUND(IF(AF12>0, ((0.0014*AF12+13.97)/1.15)*(10^12)/(1000*29308)/1000000, 0),3) -> 0
A43: Hardcoal | B43: EE | C43: =ROUND(IF(C13>0, ((0.0014*C13+13.97)/1.15)*(10^12)/(1000*29308)/1000000, 0),3) -> 0 | D43: =ROUND(IF(D13>0, ((0.0014*D13+13.97)/1.15)*(10^12)/(1000*29308)/1000000, 0),3) -> 0 | E43: =ROUND(IF(E13>0, ((0.0014*E13+13.97)/1.15)*(10^12)/(1000*29308)/1000000, 0),3) -> 0 | F43: =ROUND(IF(F13>0, ((0.0014*F13+13.97)/1.15)*(10^12)/(1000*29308)/1000000, 0),3) -> 0 | G43: =ROUND(IF(G13>0, ((0.0014*G13+13.97)/1.15)*(10^12)/(1000*29308)/1000000, 0),3) -> 0 | H43: =ROUND(IF(H13>0, ((0.0014*H13+13.97)/1.15)*(10^12)/(1000*29308)/1000000, 0),3) -> 0.464 | I43: =ROUND(IF(I13>0, ((0.0014*I13+13.97)/1.15)*(10^12)/(1000*29308)/1000000, 0),3) -> 0.468 | J43: =ROUND(IF(J13>0, ((0.0014*J13+13.97)/1.15)*(10^12)/(1000*29308)/1000000, 0),3) -> 0.455 | ... AF43: =ROUND(IF(AF13>0, ((0.0014*AF13+13.97)/1.15)*(10^12)/(1000*29308)/1000000, 0),3) -> 0
A44: Hardcoal | B44: ES | C44: =ROUND(IF(C14>0, ((0.0014*C14+13.97)/1.15)*(10^12)/(1000*29308)/1000000, 0),3) -> 0.424 | D44: =ROUND(IF(D14>0, ((0.0014*D14+13.97)/1.15)*(10^12)/(1000*29308)/1000000, 0),3) -> 0.483 | E44: =ROUND(IF(E14>0, ((0.0014*E14+13.97)/1.15)*(10^12)/(1000*29308)/1000000, 0),3) -> 0.47 | F44: =ROUND(IF(F14>0, ((0.0014*F14+13.97)/1.15)*(10^12)/(1000*29308)/1000000, 0),3) -> 0 | G44: =ROUND(IF(G14>0, ((0.0014*G14+13.97)/1.15)*(10^12)/(1000*29308)/1000000, 0),3) -> 0.465 | H44: =ROUND(IF(H14>0, ((0.0014*H14+13.97)/1.15)*(10^12)/(1000*29308)/1000000, 0),3) -> 0 | I44: =ROUND(IF(I14>0, ((0.0014*I14+13.97)/1.15)*(10^12)/(1000*29308)/1000000, 0),3) -> 0.482 | J44: =ROUND(IF(J14>0, ((0.0014*J14+13.97)/1.15)*(10^12)/(1000*29308)/1000000, 0),3) -> 0 | ... AF44: =ROUND(IF(AF14>0, ((0.0014*AF14+13.97)/1.15)*(10^12)/(1000*29308)/1000000, 0),3) -> 0
A45: Hardcoal | B45: FI | C45: =ROUND(IF(C15>0, ((0.0014*C15+13.97)/1.15)*(10^12)/(1000*29308)/1000000, 0),3) -> 0 | D45: =ROUND(IF(D15>0, ((0.0014*D15+13.97)/1.15)*(10^12)/(1000*29308)/1000000, 0),3) -> 0 | E45: =ROUND(IF(E15>0, ((0.0014*E15+13.97)/1.15)*(10^12)/(1000*29308)/1000000, 0),3) -> 0 | F45: =ROUND(IF(F15>0, ((0.0014*F15+13.97)/1.15)*(10^12)/(1000*29308)/1000000, 0),3) -> 0 | G45: =ROUND(IF(G15>0, ((0.0014*G15+13.97)/1.15)*(10^12)/(1000*29308)/1000000, 0),3) -> 0 | H45: =ROUND(IF(H15>0, ((0.0014*H15+13.97)/1.15)*(10^12)/(1000*29308)/1000000, 0),3) -> 0 | I45: =ROUND(IF(I15>0, ((0.0014*I15+13.97)/1.15)*(10^12)/(1000*29308)/1000000, 0),3) -> 0.487 | J45: =ROUND(IF(J15>0, ((0.0014*J15+13.97)/1.15)*(10^12)/(1000*29308)/1000000, 0),3) -> 0.468 | ... AF45: =ROUND(IF(AF15>0, ((0.0014*AF15+13.97)/1.15)*(10^12)/(1000*29308)/1000000, 0),3) -> 0
A46: Hardcoal | B46: FR | C46: =ROUND(IF(C16>0, ((0.0014*C16+13.97)/1.15)*(10^12)/(1000*29308)/1000000, 0),3) -> 0 | D46: =ROUND(IF(D16>0, ((0.0014*D16+13.97)/1.15)*(10^12)/(1000*29308)/1000000, 0),3) -> 0.475 | E46: =ROUND(IF(E16>0, ((0.0014*E16+13.97)/1.15)*(10^12)/(1000*29308)/1000000, 0),3) -> 0.427 | F46: =ROUND(IF(F16>0, ((0.0014*F16+13.97)/1.15)*(10^12)/(1000*29308)/1000000, 0),3) -> 0 | G46: =ROUND(IF(G16>0, ((0.0014*G16+13.97)/1.15)*(10^12)/(1000*29308)/1000000, 0),3) -> 0.429 | H46: =ROUND(IF(H16>0, ((0.0014*H16+13.97)/1.15)*(10^12)/(1000*29308)/1000000, 0),3) -> 0.482 | I46: =ROUND(IF(I16>0, ((0.0014*I16+13.97)/1.15)*(10^12)/(1000*29308)/1000000, 0),3) -> 0.435 | J46: =ROUND(IF(J16>0, ((0.0014*J16+13.97)/1.15)*(10^12)/(1000*29308)/1000000, 0),3) -> 0.489 | ... AF46: =ROUND(IF(AF16>0, ((0.0014*AF16+13.97)/1.15)*(10^12)/(1000*29308)/1000000, 0),3) -> 0
A47: Hardcoal | B47: GR | C47: =ROUND(IF(C17>0, ((0.0014*C17+13.97)/1.15)*(10^12)/(1000*29308)/1000000, 0),3) -> 0.506 | D47: =ROUND(IF(D17>0, ((0.0014*D17+13.97)/1.15)*(10^12)/(1000*29308)/1000000, 0),3) -> 0.464 | E47: =ROUND(IF(E17>0, ((0.0014*E17+13.97)/1.15)*(10^12)/(1000*29308)/1000000, 0),3) -> 0 | F47: =ROUND(IF(F17>0, ((0.0014*F17+13.97)/1.15)*(10^12)/(1000*29308)/1000000, 0),3) -> 0.433 | G47: =ROUND(IF(G17>0, ((0.0014*G17+13.97)/1.15)*(10^12)/(1000*29308)/1000000, 0),3) -> 0 | H47: =ROUND(IF(H17>0, ((0.0014*H17+13.97)/1.15)*(10^12)/(1000*29308)/1000000, 0),3) -> 0.47 | I47: =ROUND(IF(I17>0, ((0.0014*I17+13.97)/1.15)*(10^12)/(1000*29308)/1000000, 0),3) -> 0.484 | J47: =ROUND(IF(J17>0, ((0.0014*J17+13.97)/1.15)*(10^12)/(1000*29308)/1000000, 0),3) -> 0 | ... AF47: =ROUND(IF(AF17>0, ((0.0014*AF17+13.97)/1.15)*(10^12)/(1000*29308)/1000000, 0),3) -> 0.451
... A65: Hardcoal | B65: UK | C65: =ROUND(IF(C35>0, ((0.0014*C35+13.97)/1.15)*(10^12)/(1000*29308)/1000000, 0),3) -> 0.439 | D65: =ROUND(IF(D35>0, ((0.0014*D35+13.97)/1.15)*(10^12)/(1000*29308)/1000000, 0),3) -> 0.473 | E65: =ROUND(IF(E35>0, ((0.0014*E35+13.97)/1.15)*(10^12)/(1000*29308)/1000000, 0),3) -> 0.441 | F65: =ROUND(IF(F35>0, ((0.0014*F35+13.97)/1.15)*(10^12)/(1000*29308)/1000000, 0),3) -> 0 | G65: =ROUND(IF(G35>0, ((0.0014*G35+13.97)/1.15)*(10^12)/(1000*29308)/1000000, 0),3) -> 0.462 | H65: =ROUND(IF(H35>0, ((0.0014*H35+13.97)/1.15)*(10^12)/(1000*29308)/1000000, 0),3) -> 0.47 | I65: =ROUND(IF(I35>0, ((0.0014*I35+13.97)/1.15)*(10^12)/(1000*29308)/1000000, 0),3) -> 0.454 | J65: =ROUND(IF(J35>0, ((0.0014*J35+13.97)/1.15)*(10^12)/(1000*29308)/1000000, 0),3) -> 0.45 | ... AF65: =ROUND(IF(AF35>0, ((0.0014*AF35+13.97)/1.15)*(10^12)/(1000*29308)/1000000, 0),3) -> 0
A66: Biomass | B66: AT | C66: =C36 -> 0.475 | D66: =D36 -> 0 | E66: =E36 -> 0.446 | F66: =F36 -> 0.457 | G66: =G36 -> 0.433 | H66: =H36 -> 0.425 | I66: =I36 -> 0.434 | J66: =J36 -> 0.455 | ... AF66: =AF36 -> 0
A67: Biomass | B67: BE | C67: =C37 -> 0.427 | D67: =D37 -> 0.446 | E67: =E37 -> 0 | F67: =F37 -> 0 | G67: =G37 -> 0.435 | H67: =H37 -> 0.446 | I67: =I37 -> 0.431 | J67: =J37 -> 0.443 | ... AF67: =AF37 -> 0
A68: Biomass | B68: BG | C68: =C38 -> 0 | D68: =D38 -> 0.457 | E68: =E38 -> 0 | F68: =F38 -> 0 | G68: =G38 -> 0.473 | H68: =H38 -> 0.46 | I68: =I38 -> 0.475 | J68: =J38 -> 0 | ... AF68: =AF38 -> 0.432
A69: Biomass | B69: CH | C69: =C39 -> 0.429 | D69: =D39 -> 0.433 | E69: =E39 -> 0.435 | F69: =F39 -> 0.473 | G69: =G39 -> 0 | H69: =H39 -> 0.44 | I69: =I39 -> 0.435 | J69: =J39 -> 0.457 | ... AF69: =AF39 -> 0
A70: Biomass | B70: CZ | C70: =C40 -> 0.482 | D70: =D40 -> 0.425 | E70: =E40 -> 0.446 | F70: =F40 -> 0.46 | G70: =G40 -> 0.44 | H70: =H40 -> 0 | I70: =I40 -> 0.43 | J70: =J40 -> 0.447 | ... AF70: =AF40 -> 0
A71: Biomass | B71: DE | C71: =C41 -> 0.435 | D71: =D41 -> 0.434 | E71: =E41 -> 0.431 | F71: =F41 -> 0.475 | G71: =G41 -> 0.435 | H71: =H41 -> 0.43 | I71: =I41 -> 0 | J71: =J41 -> 0.437 | ... AF71: =AF41 -> 0
A72: Biomass | B72: DK | C72: =C42 -> 0.489 | D72: =D42 -> 0.455 | E72: =E42 -> 0.443 | F72: =F42 -> 0 | G72: =G42 -> 0.457 | H72: =H42 -> 0.447 | I72: =I42 -> 0.437 | J72: =J42 -> 0 | ... AF72: =AF42 -> 0
A73: Biomass | B73: EE | C73: =C43 -> 0 | D73: =D43 -> 0 | E73: =E43 -> 0 | F73: =F43 -> 0 | G73: =G43 -> 0 | H73: =H43 -> 0.464 | I73: =I43 -> 0.468 | J73: =J43 -> 0.455 | ... AF73: =AF43 -> 0
A74: Biomass | B74: ES | C74: =C44 -> 0.424 | D74: =D44 -> 0.483 | E74: =E44 -> 0.47 | F74: =F44 -> 0 | G74: =G44 -> 0.465 | H74: =H44 -> 0 | I74: =I44 -> 0.482 | J74: =J44 -> 0 | ... AF74: =AF44 -> 0
A75: Biomass | B75: FI | C75: =C45 -> 0 | D75: =D45 -> 0 | E75: =E45 -> 0 | F75: =F45 -> 0 | G75: =G45 -> 0 | H75: =H45 -> 0 | I75: =I45 -> 0.487 | J75: =J45 -> 0.468 | ... AF75: =AF45 -> 0
A76: Biomass | B76: FR | C76: =C46 -> 0 | D76: =D46 -> 0.475 | E76: =E46 -> 0.427 | F76: =F46 -> 0 | G76: =G46 -> 0.429 | H76: =H46 -> 0.482 | I76: =I46 -> 0.435 | J76: =J46 -> 0.489 | ... AF76: =AF46 -> 0
A77: Biomass | B77: GR | C77: =C47 -> 0.506 | D77: =D47 -> 0.464 | E77: =E47 -> 0 | F77: =F47 -> 0.433 | G77: =G47 -> 0 | H77: =H47 -> 0.47 | I77: =I47 -> 0.484 | J77: =J47 -> 0 | ... AF77: =AF47 -> 0.451
... A95: Biomass | B95: UK | C95: =C65 -> 0.439 | D95: =D65 -> 0.473 | E95: =E65 -> 0.441 | F95: =F65 -> 0 | G95: =G65 -> 0.462 | H95: =H65 -> 0.47 | I95: =I65 -> 0.454 | J95: =J65 -> 0.45 | ... AF95: =AF65 -> 0
A96: Oil | B96: AT | C96: =ROUND((EXP(7.032824+1*0.622482)*((C6/1.852)^ 0.40303))/(1.15*0.0059)/1000000,3) -> 4.58 | D96: =ROUND((EXP(7.032824+1*0.622482)*((D6/1.852)^ 0.40303))/(1.15*0.0059)/1000000,3) -> 0 | E96: =ROUND((EXP(7.032824+1*0.622482)*((E6/1.852)^ 0.40303))/(1.15*0.0059)/1000000,3) -> 3.537 | F96: =ROUND((EXP(7.032824+1*0.622482)*((F6/1.852)^ 0.40303))/(1.15*0.0059)/1000000,3) -> 3.965 | G96: =ROUND((EXP(7.032824+1*0.622482)*((G6/1.852)^ 0.40303))/(1.15*0.0059)/1000000,3) -> 2.864 | H96: =ROUND((EXP(7.032824+1*0.622482)*((H6/1.852)^ 0.40303))/(1.15*0.0059)/1000000,3) -> 2.265 | I96: =ROUND((EXP(7.032824+1*0.622482)*((I6/1.852)^ 0.40303))/(1.15*0.0059)/1000000,3) -> 2.916 | J96: =ROUND((EXP(7.032824+1*0.622482)*((J6/1.852)^ 0.40303))/(1.15*0.0059)/1000000,3) -> 3.886 | ... AF96: =ROUND((EXP(7.032824+1*0.622482)*((AF6/1.852)^ 0.40303))/(1.15*0.0059)/1000000,3) -> 0
A97: Oil | B97: BE | C97: =ROUND((EXP(7.032824+1*0.622482)*((C7/1.852)^ 0.40303))/(1.15*0.0059)/1000000,3) -> 2.419 | D97: =ROUND((EXP(7.032824+1*0.622482)*((D7/1.852)^ 0.40303))/(1.15*0.0059)/1000000,3) -> 3.537 | E97: =ROUND((EXP(7.032824+1*0.622482)*((E7/1.852)^ 0.40303))/(1.15*0.0059)/1000000,3) -> 0 | F97: =ROUND((EXP(7.032824+1*0.622482)*((F7/1.852)^ 0.40303))/(1.15*0.0059)/1000000,3) -> 0 | G97: =ROUND((EXP(7.032824+1*0.622482)*((G7/1.852)^ 0.40303))/(1.15*0.0059)/1000000,3) -> 2.975 | H97: =ROUND((EXP(7.032824+1*0.622482)*((H7/1.852)^ 0.40303))/(1.15*0.0059)/1000000,3) -> 3.533 | I97: =ROUND((EXP(7.032824+1*0.622482)*((I7/1.852)^ 0.40303))/(1.15*0.0059)/1000000,3) -> 2.734 | J97: =ROUND((EXP(7.032824+1*0.622482)*((J7/1.852)^ 0.40303))/(1.15*0.0059)/1000000,3) -> 3.388 | ... AF97: =ROUND((EXP(7.032824+1*0.622482)*((AF7/1.852)^ 0.40303))/(1.15*0.0059)/1000000,3) -> 0
A98: Oil | B98: BG | C98: =ROUND((EXP(7.032824+1*0.622482)*((C8/1.852)^ 0.40303))/(1.15*0.0059)/1000000,3) -> 0 | D98: =ROUND((EXP(7.032824+1*0.622482)*((D8/1.852)^ 0.40303))/(1.15*0.0059)/1000000,3) -> 3.965 | E98: =ROUND((EXP(7.032824+1*0.622482)*((E8/1.852)^ 0.40303))/(1.15*0.0059)/1000000,3) -> 0 | F98: =ROUND((EXP(7.032824+1*0.622482)*((F8/1.852)^ 0.40303))/(1.15*0.0059)/1000000,3) -> 0 | G98: =ROUND((EXP(7.032824+1*0.622482)*((G8/1.852)^ 0.40303))/(1.15*0.0059)/1000000,3) -> 4.52 | H98: =ROUND((EXP(7.032824+1*0.622482)*((H8/1.852)^ 0.40303))/(1.15*0.0059)/1000000,3) -> 4.064 | I98: =ROUND((EXP(7.032824+1*0.622482)*((I8/1.852)^ 0.40303))/(1.15*0.0059)/1000000,3) -> 4.574 | J98: =ROUND((EXP(7.032824+1*0.622482)*((J8/1.852)^ 0.40303))/(1.15*0.0059)/1000000,3) -> 0 | ... AF98: =ROUND((EXP(7.032824+1*0.622482)*((AF8/1.852)^ 0.40303))/(1.15*0.0059)/1000000,3) -> 2.791
A99: Oil | B99: CH | C99: =ROUND((EXP(7.032824+1*0.622482)*((C9/1.852)^ 0.40303))/(1.15*0.0059)/1000000,3) -> 2.574 | D99: =ROUND((EXP(7.032824+1*0.622482)*((D9/1.852)^ 0.40303))/(1.15*0.0059)/1000000,3) -> 2.864 | E99: =ROUND((EXP(7.032824+1*0.622482)*((E9/1.852)^ 0.40303))/(1.15*0.0059)/1000000,3) -> 2.975 | F99: =ROUND((EXP(7.032824+1*0.622482)*((F9/1.852)^ 0.40303))/(1.15*0.0059)/1000000,3) -> 4.52 | G99: =ROUND((EXP(7.032824+1*0.622482)*((G9/1.852)^ 0.40303))/(1.15*0.0059)/1000000,3) -> 0 | H99: =ROUND((EXP(7.032824+1*0.622482)*((H9/1.852)^ 0.40303))/(1.15*0.0059)/1000000,3) -> 3.241 | I99: =ROUND((EXP(7.032824+1*0.622482)*((I9/1.852)^ 0.40303))/(1.15*0.0059)/1000000,3) -> 2.983 | J99: =ROUND((EXP(7.032824+1*0.622482)*((J9/1.852)^ 0.40303))/(1.15*0.0059)/1000000,3) -> 3.972 | ... AF99: =ROUND((EXP(7.032824+1*0.622482)*((AF9/1.852)^ 0.40303))/(1.15*0.0059)/1000000,3) -> 0
A100: Oil | B100: CZ | C100: =ROUND((EXP(7.032824+1*0.622482)*((C10/1.852)^ 0.40303))/(1.15*0.0059)/1000000,3) -> 4.785 | D100: =ROUND((EXP(7.032824+1*0.622482)*((D10/1.852)^ 0.40303))/(1.15*0.0059)/1000000,3) -> 2.265 | E100: =ROUND((EXP(7.032824+1*0.622482)*((E10/1.852)^ 0.40303))/(1.15*0.0059)/1000000,3) -> 3.533 | F100: =ROUND((EXP(7.032824+1*0.622482)*((F10/1.852)^ 0.40303))/(1.15*0.0059)/1000000,3) -> 4.064 | G100: =ROUND((EXP(7.032824+1*0.622482)*((G10/1.852)^ 0.40303))/(1.15*0.0059)/1000000,3) -> 3.241 | H100: =ROUND((EXP(7.032824+1*0.622482)*((H10/1.852)^ 0.40303))/(1.15*0.0059)/1000000,3) -> 0 | I100: =ROUND((EXP(7.032824+1*0.622482)*((I10/1.852)^ 0.40303))/(1.15*0.0059)/1000000,3) -> 2.668 | J100: =ROUND((EXP(7.032824+1*0.622482)*((J10/1.852)^ 0.40303))/(1.15*0.0059)/1000000,3) -> 3.551 | ... AF100: =ROUND((EXP(7.032824+1*0.622482)*((AF10/1.852)^ 0.40303))/(1.15*0.0059)/1000000,3) -> 0
A101: Oil | B101: DE | C101: =ROUND((EXP(7.032824+1*0.622482)*((C11/1.852)^ 0.40303))/(1.15*0.0059)/1000000,3) -> 2.972 | D101: =ROUND((EXP(7.032824+1*0.622482)*((D11/1.852)^ 0.40303))/(1.15*0.0059)/1000000,3) -> 2.916 | E101: =ROUND((EXP(7.032824+1*0.622482)*((E11/1.852)^ 0.40303))/(1.15*0.0059)/1000000,3) -> 2.734 | F101: =ROUND((EXP(7.032824+1*0.622482)*((F11/1.852)^ 0.40303))/(1.15*0.0059)/1000000,3) -> 4.574 | G101: =ROUND((EXP(7.032824+1*0.622482)*((G11/1.852)^ 0.40303))/(1.15*0.0059)/1000000,3) -> 2.983 | H101: =ROUND((EXP(7.032824+1*0.622482)*((H11/1.852)^ 0.40303))/(1.15*0.0059)/1000000,3) -> 2.668 | I101: =ROUND((EXP(7.032824+1*0.622482)*((I11/1.852)^ 0.40303))/(1.15*0.0059)/1000000,3) -> 0 | J101: =ROUND((EXP(7.032824+1*0.622482)*((J11/1.852)^ 0.40303))/(1.15*0.0059)/1000000,3) -> 3.066 | ... AF101: =ROUND((EXP(7.032824+1*0.622482)*((AF11/1.852)^ 0.40303))/(1.15*0.0059)/1000000,3) -> 0
A102: Oil | B102: DK | C102: =ROUND((EXP(7.032824+1*0.622482)*((C12/1.852)^ 0.40303))/(1.15*0.0059)/1000000,3) -> 4.968 | D102: =ROUND((EXP(7.032824+1*0.622482)*((D12/1.852)^ 0.40303))/(1.15*0.0059)/1000000,3) -> 3.886 | E102: =ROUND((EXP(7.032824+1*0.622482)*((E12/1.852)^ 0.40303))/(1.15*0.0059)/1000000,3) -> 3.388 | F102: =ROUND((EXP(7.032824+1*0.622482)*((F12/1.852)^ 0.40303))/(1.15*0.0059)/1000000,3) -> 0 | G102: =ROUND((EXP(7.032824+1*0.622482)*((G12/1.852)^ 0.40303))/(1.15*0.0059)/1000000,3) -> 3.972 | H102: =ROUND((EXP(7.032824+1*0.622482)*((H12/1.852)^ 0.40303))/(1.15*0.0059)/1000000,3) -> 3.551 | I102: =ROUND((EXP(7.032824+1*0.622482)*((I12/1.852)^ 0.40303))/(1.15*0.0059)/1000000,3) -> 3.066 | J102: =ROUND((EXP(7.032824+1*0.622482)*((J12/1.852)^ 0.40303))/(1.15*0.0059)/1000000,3) -> 0 | ... AF102: =ROUND((EXP(7.032824+1*0.622482)*((AF12/1.852)^ 0.40303))/(1.15*0.0059)/1000000,3) -> 0
A103: Oil | B103: EE | C103: =ROUND((EXP(7.032824+1*0.622482)*((C13/1.852)^ 0.40303))/(1.15*0.0059)/1000000,3) -> 0 | D103: =ROUND((EXP(7.032824+1*0.622482)*((D13/1.852)^ 0.40303))/(1.15*0.0059)/1000000,3) -> 0 | E103: =ROUND((EXP(7.032824+1*0.622482)*((E13/1.852)^ 0.40303))/(1.15*0.0059)/1000000,3) -> 0 | F103: =ROUND((EXP(7.032824+1*0.622482)*((F13/1.852)^ 0.40303))/(1.15*0.0059)/1000000,3) -> 0 | G103: =ROUND((EXP(7.032824+1*0.622482)*((G13/1.852)^ 0.40303))/(1.15*0.0059)/1000000,3) -> 0 | H103: =ROUND((EXP(7.032824+1*0.622482)*((H13/1.852)^ 0.40303))/(1.15*0.0059)/1000000,3) -> 4.221 | I103: =ROUND((EXP(7.032824+1*0.622482)*((I13/1.852)^ 0.40303))/(1.15*0.0059)/1000000,3) -> 4.342 | J103: =ROUND((EXP(7.032824+1*0.622482)*((J13/1.852)^ 0.40303))/(1.15*0.0059)/1000000,3) -> 3.895 | ... AF103: =ROUND((EXP(7.032824+1*0.622482)*((AF13/1.852)^ 0.40303))/(1.15*0.0059)/1000000,3) -> 0
A104: Oil | B104: ES | C104: =ROUND((EXP(7.032824+1*0.622482)*((C14/1.852)^ 0.40303))/(1.15*0.0059)/1000000,3) -> 2.172 | D104: =ROUND((EXP(7.032824+1*0.622482)*((D14/1.852)^ 0.40303))/(1.15*0.0059)/1000000,3) -> 4.797 | E104: =ROUND((EXP(7.032824+1*0.622482)*((E14/1.852)^ 0.40303))/(1.15*0.0059)/1000000,3) -> 4.402 | F104: =ROUND((EXP(7.032824+1*0.622482)*((F14/1.852)^ 0.40303))/(1.15*0.0059)/1000000,3) -> 0 | G104: =ROUND((EXP(7.032824+1*0.622482)*((G14/1.852)^ 0.40303))/(1.15*0.0059)/1000000,3) -> 4.235 | H104: =ROUND((EXP(7.032824+1*0.622482)*((H14/1.852)^ 0.40303))/(1.15*0.0059)/1000000,3) -> 0 | I104: =ROUND((EXP(7.032824+1*0.622482)*((I14/1.852)^ 0.40303))/(1.15*0.0059)/1000000,3) -> 4.779 | J104: =ROUND((EXP(7.032824+1*0.622482)*((J14/1.852)^ 0.40303))/(1.15*0.0059)/1000000,3) -> 0 | ... AF104: =ROUND((EXP(7.032824+1*0.622482)*((AF14/1.852)^ 0.40303))/(1.15*0.0059)/1000000,3) -> 0
A105: Oil | B105: FI | C105: =ROUND((EXP(7.032824+1*0.622482)*((C15/1.852)^ 0.40303))/(1.15*0.0059)/1000000,3) -> 0 | D105: =ROUND((EXP(7.032824+1*0.622482)*((D15/1.852)^ 0.40303))/(1.15*0.0059)/1000000,3) -> 0 | E105: =ROUND((EXP(7.032824+1*0.622482)*((E15/1.852)^ 0.40303))/(1.15*0.0059)/1000000,3) -> 0 | F105: =ROUND((EXP(7.032824+1*0.622482)*((F15/1.852)^ 0.40303))/(1.15*0.0059)/1000000,3) -> 0 | G105: =ROUND((EXP(7.032824+1*0.622482)*((G15/1.852)^ 0.40303))/(1.15*0.0059)/1000000,3) -> 0 | H105: =ROUND((EXP(7.032824+1*0.622482)*((H15/1.852)^ 0.40303))/(1.15*0.0059)/1000000,3) -> 0 | I105: =ROUND((EXP(7.032824+1*0.622482)*((I15/1.852)^ 0.40303))/(1.15*0.0059)/1000000,3) -> 4.924 | J105: =ROUND((EXP(7.032824+1*0.622482)*((J15/1.852)^ 0.40303))/(1.15*0.0059)/1000000,3) -> 4.365 | ... AF105: =ROUND((EXP(7.032824+1*0.622482)*((AF15/1.852)^ 0.40303))/(1.15*0.0059)/1000000,3) -> 0
A106: Oil | B106: FR | C106: =ROUND((EXP(7.032824+1*0.622482)*((C16/1.852)^ 0.40303))/(1.15*0.0059)/1000000,3) -> 0 | D106: =ROUND((EXP(7.032824+1*0.622482)*((D16/1.852)^ 0.40303))/(1.15*0.0059)/1000000,3) -> 4.58 | E106: =ROUND((EXP(7.032824+1*0.622482)*((E16/1.852)^ 0.40303))/(1.15*0.0059)/1000000,3) -> 2.419 | F106: =ROUND((EXP(7.032824+1*0.622482)*((F16/1.852)^ 0.40303))/(1.15*0.0059)/1000000,3) -> 0 | G106: =ROUND((EXP(7.032824+1*0.622482)*((G16/1.852)^ 0.40303))/(1.15*0.0059)/1000000,3) -> 2.574 | H106: =ROUND((EXP(7.032824+1*0.622482)*((H16/1.852)^ 0.40303))/(1.15*0.0059)/1000000,3) -> 4.785 | I106: =ROUND((EXP(7.032824+1*0.622482)*((I16/1.852)^ 0.40303))/(1.15*0.0059)/1000000,3) -> 2.972 | J106: =ROUND((EXP(7.032824+1*0.622482)*((J16/1.852)^ 0.40303))/(1.15*0.0059)/1000000,3) -> 4.968 | ... AF106: =ROUND((EXP(7.032824+1*0.622482)*((AF16/1.852)^ 0.40303))/(1.15*0.0059)/1000000,3) -> 0
A107: Oil | B107: GR | C107: =ROUND((EXP(7.032824+1*0.622482)*((C17/1.852)^ 0.40303))/(1.15*0.0059)/1000000,3) -> 5.4 | D107: =ROUND((EXP(7.032824+1*0.622482)*((D17/1.852)^ 0.40303))/(1.15*0.0059)/1000000,3) -> 4.212 | E107: =ROUND((EXP(7.032824+1*0.622482)*((E17/1.852)^ 0.40303))/(1.15*0.0059)/1000000,3) -> 0 | F107: =ROUND((EXP(7.032824+1*0.622482)*((F17/1.852)^ 0.40303))/(1.15*0.0059)/1000000,3) -> 2.858 | G107: =ROUND((EXP(7.032824+1*0.622482)*((G17/1.852)^ 0.40303))/(1.15*0.0059)/1000000,3) -> 0 | H107: =ROUND((EXP(7.032824+1*0.622482)*((H17/1.852)^ 0.40303))/(1.15*0.0059)/1000000,3) -> 4.414 | I107: =ROUND((EXP(7.032824+1*0.622482)*((I17/1.852)^ 0.40303))/(1.15*0.0059)/1000000,3) -> 4.823 | J107: =ROUND((EXP(7.032824+1*0.622482)*((J17/1.852)^ 0.40303))/(1.15*0.0059)/1000000,3) -> 0 | ... AF107: =ROUND((EXP(7.032824+1*0.622482)*((AF17/1.852)^ 0.40303))/(1.15*0.0059)/1000000,3) -> 3.712
... A125: Oil | B125: UK | C125: =ROUND((EXP(7.032824+1*0.622482)*((C35/1.852)^ 0.40303))/(1.15*0.0059)/1000000,3) -> 3.198 | D125: =ROUND((EXP(7.032824+1*0.622482)*((D35/1.852)^ 0.40303))/(1.15*0.0059)/1000000,3) -> 4.499 | E125: =ROUND((EXP(7.032824+1*0.622482)*((E35/1.852)^ 0.40303))/(1.15*0.0059)/1000000,3) -> 3.294 | F125: =ROUND((EXP(7.032824+1*0.622482)*((F35/1.852)^ 0.40303))/(1.15*0.0059)/1000000,3) -> 0 | G125: =ROUND((EXP(7.032824+1*0.622482)*((G35/1.852)^ 0.40303))/(1.15*0.0059)/1000000,3) -> 4.135 | H125: =ROUND((EXP(7.032824+1*0.622482)*((H35/1.852)^ 0.40303))/(1.15*0.0059)/1000000,3) -> 4.423 | I125: =ROUND((EXP(7.032824+1*0.622482)*((I35/1.852)^ 0.40303))/(1.15*0.0059)/1000000,3) -> 3.865 | J125: =ROUND((EXP(7.032824+1*0.622482)*((J35/1.852)^ 0.40303))/(1.15*0.0059)/1000000,3) -> 3.68 | ... AF125: =ROUND((EXP(7.032824+1*0.622482)*((AF35/1.852)^ 0.40303))/(1.15*0.0059)/1000000,3) -> 0
A126: H2 | B126: AT | C126: =C96 -> 4.58 | D126: =D96 -> 0 | E126: =E96 -> 3.537 | F126: =F96 -> 3.965 | G126: =G96 -> 2.864 | H126: =H96 -> 2.265 | I126: =I96 -> 2.916 | J126: =J96 -> 3.886 | ... AF126: =AF96 -> 0
A127: H2 | B127: BE | C127: =C97 -> 2.419 | D127: =D97 -> 3.537 | E127: =E97 -> 0 | F127: =F97 -> 0 | G127: =G97 -> 2.975 | H127: =H97 -> 3.533 | I127: =I97 -> 2.734 | J127: =J97 -> 3.388 | ... AF127: =AF97 -> 0
A128: H2 | B128: BG | C128: =C98 -> 0 | D128: =D98 -> 3.965 | E128: =E98 -> 0 | F128: =F98 -> 0 | G128: =G98 -> 4.52 | H128: =H98 -> 4.064 | I128: =I98 -> 4.574 | J128: =J98 -> 0 | ... AF128: =AF98 -> 2.791
A129: H2 | B129: CH | C129: =C99 -> 2.574 | D129: =D99 -> 2.864 | E129: =E99 -> 2.975 | F129: =F99 -> 4.52 | G129: =G99 -> 0 | H129: =H99 -> 3.241 | I129: =I99 -> 2.983 | J129: =J99 -> 3.972 | ... AF129: =AF99 -> 0
A130: H2 | B130: CZ | C130: =C100 -> 4.785 | D130: =D100 -> 2.265 | E130: =E100 -> 3.533 | F130: =F100 -> 4.064 | G130: =G100 -> 3.241 | H130: =H100 -> 0 | I130: =I100 -> 2.668 | J130: =J100 -> 3.551 | ... AF130: =AF100 -> 0
A131: H2 | B131: DE | C131: =C101 -> 2.972 | D131: =D101 -> 2.916 | E131: =E101 -> 2.734 | F131: =F101 -> 4.574 | G131: =G101 -> 2.983 | H131: =H101 -> 2.668 | I131: =I101 -> 0 | J131: =J101 -> 3.066 | ... AF131: =AF101 -> 0
A132: H2 | B132: DK | C132: =C102 -> 4.968 | D132: =D102 -> 3.886 | E132: =E102 -> 3.388 | F132: =F102 -> 0 | G132: =G102 -> 3.972 | H132: =H102 -> 3.551 | I132: =I102 -> 3.066 | J132: =J102 -> 0 | ... AF132: =AF102 -> 0
A133: H2 | B133: EE | C133: =C103 -> 0 | D133: =D103 -> 0 | E133: =E103 -> 0 | F133: =F103 -> 0 | G133: =G103 -> 0 | H133: =H103 -> 4.221 | I133: =I103 -> 4.342 | J133: =J103 -> 3.895 | ... AF133: =AF103 -> 0
A134: H2 | B134: ES | C134: =C104 -> 2.172 | D134: =D104 -> 4.797 | E134: =E104 -> 4.402 | F134: =F104 -> 0 | G134: =G104 -> 4.235 | H134: =H104 -> 0 | I134: =I104 -> 4.779 | J134: =J104 -> 0 | ... AF134: =AF104 -> 0
A135: H2 | B135: FI | C135: =C105 -> 0 | D135: =D105 -> 0 | E135: =E105 -> 0 | F135: =F105 -> 0 | G135: =G105 -> 0 | H135: =H105 -> 0 | I135: =I105 -> 4.924 | J135: =J105 -> 4.365 | ... AF135: =AF105 -> 0
A136: H2 | B136: FR | C136: =C106 -> 0 | D136: =D106 -> 4.58 | E136: =E106 -> 2.419 | F136: =F106 -> 0 | G136: =G106 -> 2.574 | H136: =H106 -> 4.785 | I136: =I106 -> 2.972 | J136: =J106 -> 4.968 | ... AF136: =AF106 -> 0
A137: H2 | B137: GR | C137: =C107 -> 5.4 | D137: =D107 -> 4.212 | E137: =E107 -> 0 | F137: =F107 -> 2.858 | G137: =G107 -> 0 | H137: =H107 -> 4.414 | I137: =I107 -> 4.823 | J137: =J107 -> 0 | ... AF137: =AF107 -> 3.712
... A155: H2 | B155: UK | C155: =C125 -> 3.198 | D155: =D125 -> 4.499 | E155: =E125 -> 3.294 | F155: =F125 -> 0 | G155: =G125 -> 4.135 | H155: =H125 -> 4.423 | I155: =I125 -> 3.865 | J155: =J125 -> 3.68 | ... AF155: =AF125 -> 0
A156: Power | B156: AT | C156: =IF(C6>0,0.01,0) -> 0.01 | D156: =IF(D6>0,0.01,0) -> 0 | E156: =IF(E6>0,0.01,0) -> 0.01 | F156: =IF(F6>0,0.01,0) -> 0.01 | G156: =IF(G6>0,0.01,0) -> 0.01 | H156: =IF(H6>0,0.01,0) -> 0.01 | I156: =IF(I6>0,0.01,0) -> 0.01 | J156: =IF(J6>0,0.01,0) -> 0.01 | ... AF156: =IF(AF6>0,0.01,0) -> 0
A157: Power | B157: BE | C157: =IF(C7>0,0.01,0) -> 0.01 | D157: =IF(D7>0,0.01,0) -> 0.01 | E157: =IF(E7>0,0.01,0) -> 0 | F157: =IF(F7>0,0.01,0) -> 0 | G157: =IF(G7>0,0.01,0) -> 0.01 | H157: =IF(H7>0,0.01,0) -> 0.01 | I157: =IF(I7>0,0.01,0) -> 0.01 | J157: =IF(J7>0,0.01,0) -> 0.01 | ... AF157: =IF(AF7>0,0.01,0) -> 0
A158: Power | B158: BG | C158: =IF(C8>0,0.01,0) -> 0 | D158: =IF(D8>0,0.01,0) -> 0.01 | E158: =IF(E8>0,0.01,0) -> 0 | F158: =IF(F8>0,0.01,0) -> 0 | G158: =IF(G8>0,0.01,0) -> 0.01 | H158: =IF(H8>0,0.01,0) -> 0.01 | I158: =IF(I8>0,0.01,0) -> 0.01 | J158: =IF(J8>0,0.01,0) -> 0 | ... AF158: =IF(AF8>0,0.01,0) -> 0.01
A159: Power | B159: CH | C159: =IF(C9>0,0.01,0) -> 0.01 | D159: =IF(D9>0,0.01,0) -> 0.01 | E159: =IF(E9>0,0.01,0) -> 0.01 | F159: =IF(F9>0,0.01,0) -> 0.01 | G159: =IF(G9>0,0.01,0) -> 0 | H159: =IF(H9>0,0.01,0) -> 0.01 | I159: =IF(I9>0,0.01,0) -> 0.01 | J159: =IF(J9>0,0.01,0) -> 0.01 | ... AF159: =IF(AF9>0,0.01,0) -> 0
A160: Power | B160: CZ | C160: =IF(C10>0,0.01,0) -> 0.01 | D160: =IF(D10>0,0.01,0) -> 0.01 | E160: =IF(E10>0,0.01,0) -> 0.01 | F160: =IF(F10>0,0.01,0) -> 0.01 | G160: =IF(G10>0,0.01,0) -> 0.01 | H160: =IF(H10>0,0.01,0) -> 0 | I160: =IF(I10>0,0.01,0) -> 0.01 | J160: =IF(J10>0,0.01,0) -> 0.01 | ... AF160: =IF(AF10>0,0.01,0) -> 0
A161: Power | B161: DE | C161: =IF(C11>0,0.01,0) -> 0.01 | D161: =IF(D11>0,0.01,0) -> 0.01 | E161: =IF(E11>0,0.01,0) -> 0.01 | F161: =IF(F11>0,0.01,0) -> 0.01 | G161: =IF(G11>0,0.01,0) -> 0.01 | H161: =IF(H11>0,0.01,0) -> 0.01 | I161: =IF(I11>0,0.01,0) -> 0 | J161: =IF(J11>0,0.01,0) -> 0.01 | ... AF161: =IF(AF11>0,0.01,0) -> 0
A162: Power | B162: DK | C162: =IF(C12>0,0.01,0) -> 0.01 | D162: =IF(D12>0,0.01,0) -> 0.01 | E162: =IF(E12>0,0.01,0) -> 0.01 | F162: =IF(F12>0,0.01,0) -> 0 | G162: =IF(G12>0,0.01,0) -> 0.01 | H162: =IF(H12>0,0.01,0) -> 0.01 | I162: =IF(I12>0,0.01,0) -> 0.01 | J162: =IF(J12>0,0.01,0) -> 0 | ... AF162: =IF(AF12>0,0.01,0) -> 0
A163: Power | B163: EE | C163: =IF(C13>0,0.01,0) -> 0 | D163: =IF(D13>0,0.01,0) -> 0 | E163: =IF(E13>0,0.01,0) -> 0 | F163: =IF(F13>0,0.01,0) -> 0 | G163: =IF(G13>0,0.01,0) -> 0 | H163: =IF(H13>0,0.01,0) -> 0.01 | I163: =IF(I13>0,0.01,0) -> 0.01 | J163: =IF(J13>0,0.01,0) -> 0.01 | ... AF163: =IF(AF13>0,0.01,0) -> 0
A164: Power | B164: ES | C164: =IF(C14>0,0.01,0) -> 0.01 | D164: =IF(D14>0,0.01,0) -> 0.01 | E164: =IF(E14>0,0.01,0) -> 0.01 | F164: =IF(F14>0,0.01,0) -> 0 | G164: =IF(G14>0,0.01,0) -> 0.01 | H164: =IF(H14>0,0.01,0) -> 0 | I164: =IF(I14>0,0.01,0) -> 0.01 | J164: =IF(J14>0,0.01,0) -> 0 | ... AF164: =IF(AF14>0,0.01,0) -> 0
A165: Power | B165: FI | C165: =IF(C15>0,0.01,0) -> 0 | D165: =IF(D15>0,0.01,0) -> 0 | E165: =IF(E15>0,0.01,0) -> 0 | F165: =IF(F15>0,0.01,0) -> 0 | G165: =IF(G15>0,0.01,0) -> 0 | H165: =IF(H15>0,0.01,0) -> 0 | I165: =IF(I15>0,0.01,0) -> 0.01 | J165: =IF(J15>0,0.01,0) -> 0.01 | ... AF165: =IF(AF15>0,0.01,0) -> 0
A166: Power | B166: FR | C166: =IF(C16>0,0.01,0) -> 0 | D166: =IF(D16>0,0.01,0) -> 0.01 | E166: =IF(E16>0,0.01,0) -> 0.01 | F166: =IF(F16>0,0.01,0) -> 0 | G166: =IF(G16>0,0.01,0) -> 0.01 | H166: =IF(H16>0,0.01,0) -> 0.01 | I166: =IF(I16>0,0.01,0) -> 0.01 | J166: =IF(J16>0,0.01,0) -> 0.01 | ... AF166: =IF(AF16>0,0.01,0) -> 0
A167: Power | B167: GR | C167: =IF(C17>0,0.01,0) -> 0.01 | D167: =IF(D17>0,0.01,0) -> 0.01 | E167: =IF(E17>0,0.01,0) -> 0 | F167: =IF(F17>0,0.01,0) -> 0.01 | G167: =IF(G17>0,0.01,0) -> 0 | H167: =IF(H17>0,0.01,0) -> 0.01 | I167: =IF(I17>0,0.01,0) -> 0.01 | J167: =IF(J17>0,0.01,0) -> 0 | ... AF167: =IF(AF17>0,0.01,0) -> 0.01
... A185: Power | B185: UK | C185: =IF(C35>0,0.01,0) -> 0.01 | D185: =IF(D35>0,0.01,0) -> 0.01 | E185: =IF(E35>0,0.01,0) -> 0.01 | F185: =IF(F35>0,0.01,0) -> 0 | G185: =IF(G35>0,0.01,0) -> 0.01 | H185: =IF(H35>0,0.01,0) -> 0.01 | I185: =IF(I35>0,0.01,0) -> 0.01 | J185: =IF(J35>0,0.01,0) -> 0.01 | ... AF185: =IF(AF35>0,0.01,0) -> 0
A186: LH2 | B186: AT | C186: =ROUND((EXP(7.032824+1*0.622482)*((C6/1.852)^ 0.40303))/(1.15*0.0059)/1000000,3) -> 4.58 | D186: =ROUND((EXP(7.032824+1*0.622482)*((D6/1.852)^ 0.40303))/(1.15*0.0059)/1000000,3) -> 0 | E186: =ROUND((EXP(7.032824+1*0.622482)*((E6/1.852)^ 0.40303))/(1.15*0.0059)/1000000,3) -> 3.537 | F186: =ROUND((EXP(7.032824+1*0.622482)*((F6/1.852)^ 0.40303))/(1.15*0.0059)/1000000,3) -> 3.965 | G186: =ROUND((EXP(7.032824+1*0.622482)*((G6/1.852)^ 0.40303))/(1.15*0.0059)/1000000,3) -> 2.864 | H186: =ROUND((EXP(7.032824+1*0.622482)*((H6/1.852)^ 0.40303))/(1.15*0.0059)/1000000,3) -> 2.265 | I186: =ROUND((EXP(7.032824+1*0.622482)*((I6/1.852)^ 0.40303))/(1.15*0.0059)/1000000,3) -> 2.916 | J186: =ROUND((EXP(7.032824+1*0.622482)*((J6/1.852)^ 0.40303))/(1.15*0.0059)/1000000,3) -> 3.886 | ... AF186: =ROUND((EXP(7.032824+1*0.622482)*((AF6/1.852)^ 0.40303))/(1.15*0.0059)/1000000,3) -> 0
A187: LH2 | B187: BE | C187: =ROUND((EXP(7.032824+1*0.622482)*((C7/1.852)^ 0.40303))/(1.15*0.0059)/1000000,3) -> 2.419 | D187: =ROUND((EXP(7.032824+1*0.622482)*((D7/1.852)^ 0.40303))/(1.15*0.0059)/1000000,3) -> 3.537 | E187: =ROUND((EXP(7.032824+1*0.622482)*((E7/1.852)^ 0.40303))/(1.15*0.0059)/1000000,3) -> 0 | F187: =ROUND((EXP(7.032824+1*0.622482)*((F7/1.852)^ 0.40303))/(1.15*0.0059)/1000000,3) -> 0 | G187: =ROUND((EXP(7.032824+1*0.622482)*((G7/1.852)^ 0.40303))/(1.15*0.0059)/1000000,3) -> 2.975 | H187: =ROUND((EXP(7.032824+1*0.622482)*((H7/1.852)^ 0.40303))/(1.15*0.0059)/1000000,3) -> 3.533 | I187: =ROUND((EXP(7.032824+1*0.622482)*((I7/1.852)^ 0.40303))/(1.15*0.0059)/1000000,3) -> 2.734 | J187: =ROUND((EXP(7.032824+1*0.622482)*((J7/1.852)^ 0.40303))/(1.15*0.0059)/1000000,3) -> 3.388 | ... AF187: =ROUND((EXP(7.032824+1*0.622482)*((AF7/1.852)^ 0.40303))/(1.15*0.0059)/1000000,3) -> 0
A188: LH2 | B188: BG | C188: =ROUND((EXP(7.032824+1*0.622482)*((C8/1.852)^ 0.40303))/(1.15*0.0059)/1000000,3) -> 0 | D188: =ROUND((EXP(7.032824+1*0.622482)*((D8/1.852)^ 0.40303))/(1.15*0.0059)/1000000,3) -> 3.965 | E188: =ROUND((EXP(7.032824+1*0.622482)*((E8/1.852)^ 0.40303))/(1.15*0.0059)/1000000,3) -> 0 | F188: =ROUND((EXP(7.032824+1*0.622482)*((F8/1.852)^ 0.40303))/(1.15*0.0059)/1000000,3) -> 0 | G188: =ROUND((EXP(7.032824+1*0.622482)*((G8/1.852)^ 0.40303))/(1.15*0.0059)/1000000,3) -> 4.52 | H188: =ROUND((EXP(7.032824+1*0.622482)*((H8/1.852)^ 0.40303))/(1.15*0.0059)/1000000,3) -> 4.064 | I188: =ROUND((EXP(7.032824+1*0.622482)*((I8/1.852)^ 0.40303))/(1.15*0.0059)/1000000,3) -> 4.574 | J188: =ROUND((EXP(7.032824+1*0.622482)*((J8/1.852)^ 0.40303))/(1.15*0.0059)/1000000,3) -> 0 | ... AF188: =ROUND((EXP(7.032824+1*0.622482)*((AF8/1.852)^ 0.40303))/(1.15*0.0059)/1000000,3) -> 2.791
A189: LH2 | B189: CH | C189: =ROUND((EXP(7.032824+1*0.622482)*((C9/1.852)^ 0.40303))/(1.15*0.0059)/1000000,3) -> 2.574 | D189: =ROUND((EXP(7.032824+1*0.622482)*((D9/1.852)^ 0.40303))/(1.15*0.0059)/1000000,3) -> 2.864 | E189: =ROUND((EXP(7.032824+1*0.622482)*((E9/1.852)^ 0.40303))/(1.15*0.0059)/1000000,3) -> 2.975 | F189: =ROUND((EXP(7.032824+1*0.622482)*((F9/1.852)^ 0.40303))/(1.15*0.0059)/1000000,3) -> 4.52 | G189: =ROUND((EXP(7.032824+1*0.622482)*((G9/1.852)^ 0.40303))/(1.15*0.0059)/1000000,3) -> 0 | H189: =ROUND((EXP(7.032824+1*0.622482)*((H9/1.852)^ 0.40303))/(1.15*0.0059)/1000000,3) -> 3.241 | I189: =ROUND((EXP(7.032824+1*0.622482)*((I9/1.852)^ 0.40303))/(1.15*0.0059)/1000000,3) -> 2.983 | J189: =ROUND((EXP(7.032824+1*0.622482)*((J9/1.852)^ 0.40303))/(1.15*0.0059)/1000000,3) -> 3.972 | ... AF189: =ROUND((EXP(7.032824+1*0.622482)*((AF9/1.852)^ 0.40303))/(1.15*0.0059)/1000000,3) -> 0
A190: LH2 | B190: CZ | C190: =ROUND((EXP(7.032824+1*0.622482)*((C10/1.852)^ 0.40303))/(1.15*0.0059)/1000000,3) -> 4.785 | D190: =ROUND((EXP(7.032824+1*0.622482)*((D10/1.852)^ 0.40303))/(1.15*0.0059)/1000000,3) -> 2.265 | E190: =ROUND((EXP(7.032824+1*0.622482)*((E10/1.852)^ 0.40303))/(1.15*0.0059)/1000000,3) -> 3.533 | F190: =ROUND((EXP(7.032824+1*0.622482)*((F10/1.852)^ 0.40303))/(1.15*0.0059)/1000000,3) -> 4.064 | G190: =ROUND((EXP(7.032824+1*0.622482)*((G10/1.852)^ 0.40303))/(1.15*0.0059)/1000000,3) -> 3.241 | H190: =ROUND((EXP(7.032824+1*0.622482)*((H10/1.852)^ 0.40303))/(1.15*0.0059)/1000000,3) -> 0 | I190: =ROUND((EXP(7.032824+1*0.622482)*((I10/1.852)^ 0.40303))/(1.15*0.0059)/1000000,3) -> 2.668 | J190: =ROUND((EXP(7.032824+1*0.622482)*((J10/1.852)^ 0.40303))/(1.15*0.0059)/1000000,3) -> 3.551 | ... AF190: =ROUND((EXP(7.032824+1*0.622482)*((AF10/1.852)^ 0.40303))/(1.15*0.0059)/1000000,3) -> 0
A191: LH2 | B191: DE | C191: =ROUND((EXP(7.032824+1*0.622482)*((C11/1.852)^ 0.40303))/(1.15*0.0059)/1000000,3) -> 2.972 | D191: =ROUND((EXP(7.032824+1*0.622482)*((D11/1.852)^ 0.40303))/(1.15*0.0059)/1000000,3) -> 2.916 | E191: =ROUND((EXP(7.032824+1*0.622482)*((E11/1.852)^ 0.40303))/(1.15*0.0059)/1000000,3) -> 2.734 | F191: =ROUND((EXP(7.032824+1*0.622482)*((F11/1.852)^ 0.40303))/(1.15*0.0059)/1000000,3) -> 4.574 | G191: =ROUND((EXP(7.032824+1*0.622482)*((G11/1.852)^ 0.40303))/(1.15*0.0059)/1000000,3) -> 2.983 | H191: =ROUND((EXP(7.032824+1*0.622482)*((H11/1.852)^ 0.40303))/(1.15*0.0059)/1000000,3) -> 2.668 | I191: =ROUND((EXP(7.032824+1*0.622482)*((I11/1.852)^ 0.40303))/(1.15*0.0059)/1000000,3) -> 0 | J191: =ROUND((EXP(7.032824+1*0.622482)*((J11/1.852)^ 0.40303))/(1.15*0.0059)/1000000,3) -> 3.066 | ... AF191: =ROUND((EXP(7.032824+1*0.622482)*((AF11/1.852)^ 0.40303))/(1.15*0.0059)/1000000,3) -> 0
A192: LH2 | B192: DK | C192: =ROUND((EXP(7.032824+1*0.622482)*((C12/1.852)^ 0.40303))/(1.15*0.0059)/1000000,3) -> 4.968 | D192: =ROUND((EXP(7.032824+1*0.622482)*((D12/1.852)^ 0.40303))/(1.15*0.0059)/1000000,3) -> 3.886 | E192: =ROUND((EXP(7.032824+1*0.622482)*((E12/1.852)^ 0.40303))/(1.15*0.0059)/1000000,3) -> 3.388 | F192: =ROUND((EXP(7.032824+1*0.622482)*((F12/1.852)^ 0.40303))/(1.15*0.0059)/1000000,3) -> 0 | G192: =ROUND((EXP(7.032824+1*0.622482)*((G12/1.852)^ 0.40303))/(1.15*0.0059)/1000000,3) -> 3.972 | H192: =ROUND((EXP(7.032824+1*0.622482)*((H12/1.852)^ 0.40303))/(1.15*0.0059)/1000000,3) -> 3.551 | I192: =ROUND((EXP(7.032824+1*0.622482)*((I12/1.852)^ 0.40303))/(1.15*0.0059)/1000000,3) -> 3.066 | J192: =ROUND((EXP(7.032824+1*0.622482)*((J12/1.852)^ 0.40303))/(1.15*0.0059)/1000000,3) -> 0 | ... AF192: =ROUND((EXP(7.032824+1*0.622482)*((AF12/1.852)^ 0.40303))/(1.15*0.0059)/1000000,3) -> 0
A193: LH2 | B193: EE | C193: =ROUND((EXP(7.032824+1*0.622482)*((C13/1.852)^ 0.40303))/(1.15*0.0059)/1000000,3) -> 0 | D193: =ROUND((EXP(7.032824+1*0.622482)*((D13/1.852)^ 0.40303))/(1.15*0.0059)/1000000,3) -> 0 | E193: =ROUND((EXP(7.032824+1*0.622482)*((E13/1.852)^ 0.40303))/(1.15*0.0059)/1000000,3) -> 0 | F193: =ROUND((EXP(7.032824+1*0.622482)*((F13/1.852)^ 0.40303))/(1.15*0.0059)/1000000,3) -> 0 | G193: =ROUND((EXP(7.032824+1*0.622482)*((G13/1.852)^ 0.40303))/(1.15*0.0059)/1000000,3) -> 0 | H193: =ROUND((EXP(7.032824+1*0.622482)*((H13/1.852)^ 0.40303))/(1.15*0.0059)/1000000,3) -> 4.221 | I193: =ROUND((EXP(7.032824+1*0.622482)*((I13/1.852)^ 0.40303))/(1.15*0.0059)/1000000,3) -> 4.342 | J193: =ROUND((EXP(7.032824+1*0.622482)*((J13/1.852)^ 0.40303))/(1.15*0.0059)/1000000,3) -> 3.895 | ... AF193: =ROUND((EXP(7.032824+1*0.622482)*((AF13/1.852)^ 0.40303))/(1.15*0.0059)/1000000,3) -> 0
A194: LH2 | B194: ES | C194: =ROUND((EXP(7.032824+1*0.622482)*((C14/1.852)^ 0.40303))/(1.15*0.0059)/1000000,3) -> 2.172 | D194: =ROUND((EXP(7.032824+1*0.622482)*((D14/1.852)^ 0.40303))/(1.15*0.0059)/1000000,3) -> 4.797 | E194: =ROUND((EXP(7.032824+1*0.622482)*((E14/1.852)^ 0.40303))/(1.15*0.0059)/1000000,3) -> 4.402 | F194: =ROUND((EXP(7.032824+1*0.622482)*((F14/1.852)^ 0.40303))/(1.15*0.0059)/1000000,3) -> 0 | G194: =ROUND((EXP(7.032824+1*0.622482)*((G14/1.852)^ 0.40303))/(1.15*0.0059)/1000000,3) -> 4.235 | H194: =ROUND((EXP(7.032824+1*0.622482)*((H14/1.852)^ 0.40303))/(1.15*0.0059)/1000000,3) -> 0 | I194: =ROUND((EXP(7.032824+1*0.622482)*((I14/1.852)^ 0.40303))/(1.15*0.0059)/1000000,3) -> 4.779 | J194: =ROUND((EXP(7.032824+1*0.622482)*((J14/1.852)^ 0.40303))/(1.15*0.0059)/1000000,3) -> 0 | ... AF194: =ROUND((EXP(7.032824+1*0.622482)*((AF14/1.852)^ 0.40303))/(1.15*0.0059)/1000000,3) -> 0
A195: LH2 | B195: FI | C195: =ROUND((EXP(7.032824+1*0.622482)*((C15/1.852)^ 0.40303))/(1.15*0.0059)/1000000,3) -> 0 | D195: =ROUND((EXP(7.032824+1*0.622482)*((D15/1.852)^ 0.40303))/(1.15*0.0059)/1000000,3) -> 0 | E195: =ROUND((EXP(7.032824+1*0.622482)*((E15/1.852)^ 0.40303))/(1.15*0.0059)/1000000,3) -> 0 | F195: =ROUND((EXP(7.032824+1*0.622482)*((F15/1.852)^ 0.40303))/(1.15*0.0059)/1000000,3) -> 0 | G195: =ROUND((EXP(7.032824+1*0.622482)*((G15/1.852)^ 0.40303))/(1.15*0.0059)/1000000,3) -> 0 | H195: =ROUND((EXP(7.032824+1*0.622482)*((H15/1.852)^ 0.40303))/(1.15*0.0059)/1000000,3) -> 0 | I195: =ROUND((EXP(7.032824+1*0.622482)*((I15/1.852)^ 0.40303))/(1.15*0.0059)/1000000,3) -> 4.924 | J195: =ROUND((EXP(7.032824+1*0.622482)*((J15/1.852)^ 0.40303))/(1.15*0.0059)/1000000,3) -> 4.365 | ... AF195: =ROUND((EXP(7.032824+1*0.622482)*((AF15/1.852)^ 0.40303))/(1.15*0.0059)/1000000,3) -> 0
A196: LH2 | B196: FR | C196: =ROUND((EXP(7.032824+1*0.622482)*((C16/1.852)^ 0.40303))/(1.15*0.0059)/1000000,3) -> 0 | D196: =ROUND((EXP(7.032824+1*0.622482)*((D16/1.852)^ 0.40303))/(1.15*0.0059)/1000000,3) -> 4.58 | E196: =ROUND((EXP(7.032824+1*0.622482)*((E16/1.852)^ 0.40303))/(1.15*0.0059)/1000000,3) -> 2.419 | F196: =ROUND((EXP(7.032824+1*0.622482)*((F16/1.852)^ 0.40303))/(1.15*0.0059)/1000000,3) -> 0 | G196: =ROUND((EXP(7.032824+1*0.622482)*((G16/1.852)^ 0.40303))/(1.15*0.0059)/1000000,3) -> 2.574 | H196: =ROUND((EXP(7.032824+1*0.622482)*((H16/1.852)^ 0.40303))/(1.15*0.0059)/1000000,3) -> 4.785 | I196: =ROUND((EXP(7.032824+1*0.622482)*((I16/1.852)^ 0.40303))/(1.15*0.0059)/1000000,3) -> 2.972 | J196: =ROUND((EXP(7.032824+1*0.622482)*((J16/1.852)^ 0.40303))/(1.15*0.0059)/1000000,3) -> 4.968 | ... AF196: =ROUND((EXP(7.032824+1*0.622482)*((AF16/1.852)^ 0.40303))/(1.15*0.0059)/1000000,3) -> 0
A197: LH2 | B197: GR | C197: =ROUND((EXP(7.032824+1*0.622482)*((C17/1.852)^ 0.40303))/(1.15*0.0059)/1000000,3) -> 5.4 | D197: =ROUND((EXP(7.032824+1*0.622482)*((D17/1.852)^ 0.40303))/(1.15*0.0059)/1000000,3) -> 4.212 | E197: =ROUND((EXP(7.032824+1*0.622482)*((E17/1.852)^ 0.40303))/(1.15*0.0059)/1000000,3) -> 0 | F197: =ROUND((EXP(7.032824+1*0.622482)*((F17/1.852)^ 0.40303))/(1.15*0.0059)/1000000,3) -> 2.858 | G197: =ROUND((EXP(7.032824+1*0.622482)*((G17/1.852)^ 0.40303))/(1.15*0.0059)/1000000,3) -> 0 | H197: =ROUND((EXP(7.032824+1*0.622482)*((H17/1.852)^ 0.40303))/(1.15*0.0059)/1000000,3) -> 4.414 | I197: =ROUND((EXP(7.032824+1*0.622482)*((I17/1.852)^ 0.40303))/(1.15*0.0059)/1000000,3) -> 4.823 | J197: =ROUND((EXP(7.032824+1*0.622482)*((J17/1.852)^ 0.40303))/(1.15*0.0059)/1000000,3) -> 0 | ... AF197: =ROUND((EXP(7.032824+1*0.622482)*((AF17/1.852)^ 0.40303))/(1.15*0.0059)/1000000,3) -> 3.712
... A215: LH2 | B215: UK | C215: =ROUND((EXP(7.032824+1*0.622482)*((C35/1.852)^ 0.40303))/(1.15*0.0059)/1000000,3) -> 3.198 | D215: =ROUND((EXP(7.032824+1*0.622482)*((D35/1.852)^ 0.40303))/(1.15*0.0059)/1000000,3) -> 4.499 | E215: =ROUND((EXP(7.032824+1*0.622482)*((E35/1.852)^ 0.40303))/(1.15*0.0059)/1000000,3) -> 3.294 | F215: =ROUND((EXP(7.032824+1*0.622482)*((F35/1.852)^ 0.40303))/(1.15*0.0059)/1000000,3) -> 0 | G215: =ROUND((EXP(7.032824+1*0.622482)*((G35/1.852)^ 0.40303))/(1.15*0.0059)/1000000,3) -> 4.135 | H215: =ROUND((EXP(7.032824+1*0.622482)*((H35/1.852)^ 0.40303))/(1.15*0.0059)/1000000,3) -> 4.423 | I215: =ROUND((EXP(7.032824+1*0.622482)*((I35/1.852)^ 0.40303))/(1.15*0.0059)/1000000,3) -> 3.865 | J215: =ROUND((EXP(7.032824+1*0.622482)*((J35/1.852)^ 0.40303))/(1.15*0.0059)/1000000,3) -> 3.68 | ... AF215: =ROUND((EXP(7.032824+1*0.622482)*((AF35/1.852)^ 0.40303))/(1.15*0.0059)/1000000,3) -> 0
A216: LSG | B216: AT | C216: =ROUND((EXP(7.032824+1*0.622482)*((C6/1.852)^ 0.40303))/(1.15*0.0059)/1000000,3) -> 4.58 | D216: =ROUND((EXP(7.032824+1*0.622482)*((D6/1.852)^ 0.40303))/(1.15*0.0059)/1000000,3) -> 0 | E216: =ROUND((EXP(7.032824+1*0.622482)*((E6/1.852)^ 0.40303))/(1.15*0.0059)/1000000,3) -> 3.537 | F216: =ROUND((EXP(7.032824+1*0.622482)*((F6/1.852)^ 0.40303))/(1.15*0.0059)/1000000,3) -> 3.965 | G216: =ROUND((EXP(7.032824+1*0.622482)*((G6/1.852)^ 0.40303))/(1.15*0.0059)/1000000,3) -> 2.864 | H216: =ROUND((EXP(7.032824+1*0.622482)*((H6/1.852)^ 0.40303))/(1.15*0.0059)/1000000,3) -> 2.265 | I216: =ROUND((EXP(7.032824+1*0.622482)*((I6/1.852)^ 0.40303))/(1.15*0.0059)/1000000,3) -> 2.916 | J216: =ROUND((EXP(7.032824+1*0.622482)*((J6/1.852)^ 0.40303))/(1.15*0.0059)/1000000,3) -> 3.886 | ... AF216: =ROUND((EXP(7.032824+1*0.622482)*((AF6/1.852)^ 0.40303))/(1.15*0.0059)/1000000,3) -> 0
A217: LSG | B217: BE | C217: =ROUND((EXP(7.032824+1*0.622482)*((C7/1.852)^ 0.40303))/(1.15*0.0059)/1000000,3) -> 2.419 | D217: =ROUND((EXP(7.032824+1*0.622482)*((D7/1.852)^ 0.40303))/(1.15*0.0059)/1000000,3) -> 3.537 | E217: =ROUND((EXP(7.032824+1*0.622482)*((E7/1.852)^ 0.40303))/(1.15*0.0059)/1000000,3) -> 0 | F217: =ROUND((EXP(7.032824+1*0.622482)*((F7/1.852)^ 0.40303))/(1.15*0.0059)/1000000,3) -> 0 | G217: =ROUND((EXP(7.032824+1*0.622482)*((G7/1.852)^ 0.40303))/(1.15*0.0059)/1000000,3) -> 2.975 | H217: =ROUND((EXP(7.032824+1*0.622482)*((H7/1.852)^ 0.40303))/(1.15*0.0059)/1000000,3) -> 3.533 | I217: =ROUND((EXP(7.032824+1*0.622482)*((I7/1.852)^ 0.40303))/(1.15*0.0059)/1000000,3) -> 2.734 | J217: =ROUND((EXP(7.032824+1*0.622482)*((J7/1.852)^ 0.40303))/(1.15*0.0059)/1000000,3) -> 3.388 | ... AF217: =ROUND((EXP(7.032824+1*0.622482)*((AF7/1.852)^ 0.40303))/(1.15*0.0059)/1000000,3) -> 0
A218: LSG | B218: BG | C218: =ROUND((EXP(7.032824+1*0.622482)*((C8/1.852)^ 0.40303))/(1.15*0.0059)/1000000,3) -> 0 | D218: =ROUND((EXP(7.032824+1*0.622482)*((D8/1.852)^ 0.40303))/(1.15*0.0059)/1000000,3) -> 3.965 | E218: =ROUND((EXP(7.032824+1*0.622482)*((E8/1.852)^ 0.40303))/(1.15*0.0059)/1000000,3) -> 0 | F218: =ROUND((EXP(7.032824+1*0.622482)*((F8/1.852)^ 0.40303))/(1.15*0.0059)/1000000,3) -> 0 | G218: =ROUND((EXP(7.032824+1*0.622482)*((G8/1.852)^ 0.40303))/(1.15*0.0059)/1000000,3) -> 4.52 | H218: =ROUND((EXP(7.032824+1*0.622482)*((H8/1.852)^ 0.40303))/(1.15*0.0059)/1000000,3) -> 4.064 | I218: =ROUND((EXP(7.032824+1*0.622482)*((I8/1.852)^ 0.40303))/(1.15*0.0059)/1000000,3) -> 4.574 | J218: =ROUND((EXP(7.032824+1*0.622482)*((J8/1.852)^ 0.40303))/(1.15*0.0059)/1000000,3) -> 0 | ... AF218: =ROUND((EXP(7.032824+1*0.622482)*((AF8/1.852)^ 0.40303))/(1.15*0.0059)/1000000,3) -> 2.791
A219: LSG | B219: CH | C219: =ROUND((EXP(7.032824+1*0.622482)*((C9/1.852)^ 0.40303))/(1.15*0.0059)/1000000,3) -> 2.574 | D219: =ROUND((EXP(7.032824+1*0.622482)*((D9/1.852)^ 0.40303))/(1.15*0.0059)/1000000,3) -> 2.864 | E219: =ROUND((EXP(7.032824+1*0.622482)*((E9/1.852)^ 0.40303))/(1.15*0.0059)/1000000,3) -> 2.975 | F219: =ROUND((EXP(7.032824+1*0.622482)*((F9/1.852)^ 0.40303))/(1.15*0.0059)/1000000,3) -> 4.52 | G219: =ROUND((EXP(7.032824+1*0.622482)*((G9/1.852)^ 0.40303))/(1.15*0.0059)/1000000,3) -> 0 | H219: =ROUND((EXP(7.032824+1*0.622482)*((H9/1.852)^ 0.40303))/(1.15*0.0059)/1000000,3) -> 3.241 | I219: =ROUND((EXP(7.032824+1*0.622482)*((I9/1.852)^ 0.40303))/(1.15*0.0059)/1000000,3) -> 2.983 | J219: =ROUND((EXP(7.032824+1*0.622482)*((J9/1.852)^ 0.40303))/(1.15*0.0059)/1000000,3) -> 3.972 | ... AF219: =ROUND((EXP(7.032824+1*0.622482)*((AF9/1.852)^ 0.40303))/(1.15*0.0059)/1000000,3) -> 0
A220: LSG | B220: CZ | C220: =ROUND((EXP(7.032824+1*0.622482)*((C10/1.852)^ 0.40303))/(1.15*0.0059)/1000000,3) -> 4.785 | D220: =ROUND((EXP(7.032824+1*0.622482)*((D10/1.852)^ 0.40303))/(1.15*0.0059)/1000000,3) -> 2.265 | E220: =ROUND((EXP(7.032824+1*0.622482)*((E10/1.852)^ 0.40303))/(1.15*0.0059)/1000000,3) -> 3.533 | F220: =ROUND((EXP(7.032824+1*0.622482)*((F10/1.852)^ 0.40303))/(1.15*0.0059)/1000000,3) -> 4.064 | G220: =ROUND((EXP(7.032824+1*0.622482)*((G10/1.852)^ 0.40303))/(1.15*0.0059)/1000000,3) -> 3.241 | H220: =ROUND((EXP(7.032824+1*0.622482)*((H10/1.852)^ 0.40303))/(1.15*0.0059)/1000000,3) -> 0 | I220: =ROUND((EXP(7.032824+1*0.622482)*((I10/1.852)^ 0.40303))/(1.15*0.0059)/1000000,3) -> 2.668 | J220: =ROUND((EXP(7.032824+1*0.622482)*((J10/1.852)^ 0.40303))/(1.15*0.0059)/1000000,3) -> 3.551 | ... AF220: =ROUND((EXP(7.032824+1*0.622482)*((AF10/1.852)^ 0.40303))/(1.15*0.0059)/1000000,3) -> 0
...

Sheet Par_TradeCapacity
A1: TradeCapacity{y in YEAR, f in FUEL, r in REGION1, rr in REGION2}
A2: Defines the capacities for trade between two regions in a specific year and for a specific fuel.
A3: Unit: GW for Power; PJ for Gas
C5: AT | D5: BE | E5: BG | F5: CH | G5: CZ | H5: DE | I5: DK | J5: ES | K5: FI | L5: FR | M5: GR | N5: HR | O5: HU | P5: IE | Q5: IT | R5: LU | S5: NONEU_Balkan | T5: NL | U5: NO | V5: PL | W5: PT | X5: RO | Y5: SE | Z5: SI | AA5: SK | AB5: UK | AC5: EE | AD5: LT | AE5: LV | AF5: TR | AH5: TR
C6: 2018 | D6: 2018 | E6: 2018 | F6: 2018 | G6: 2018 | H6: 2018 | I6: 2018 | J6: 2018 | K6: 2018 | L6: 2018 | M6: 2018 | N6: 2018 | O6: 2018 | P6: 2018 | Q6: 2018 | R6: 2018 | S6: 2018 | T6: 2018 | U6: 2018 | V6: 2018 | W6: 2018 | X6: 2018 | Y6: 2018 | Z6: 2018 | AA6: 2018 | AB6: 2018 | AC6: 2018 | AD6: 2018 | AE6: 2018 | AF6: 2018
A7: Power | B7: AT | C7: 0 | F7: 0.43425 | G7: 0.9 | H7: 2 | O7: 0.8 | Q7: 0.071 | Z7: 0.95008333
A8: Power | B8: BE | D8: 0 | L8: 1.5 | T8: 1.426 | AH8: 1
A9: Power | B9: BG | E9: 0 | M9: 0.35 | S9: 0.35 | X9: 0.15 | AF9: 1
A10: Power | B10: CH | C10: 1.2 | F10: 0 | H10: 3.5 | L10: 1.1 | Q10: 1.336
A11: Power | B11: CZ | C11: 0.8 | G11: 0 | H11: 1.775 | V11: 0.1 | AA11: 1.7
A12: Power | B12: DE | C12: 2.2 | F12: 3.5 | G12: 1.1 | H12: 0 | I12: 3.1 | L12: 1.675 | R12: 0.98 | T12: 2.85 | U12: 1.444 | V12: 0.1 | Y12: 0.35395833
A13: Power | B13: DK | H13: 3.1 | I13: 0 | T13: 0.7 | U13: 1.7 | Y13: 2.44 | AB13: 1.4
A14: Power | B14: ES | J14: 0 | L14: 2.9 | W14: 4.1
A15: Power | B15: FI | K15: 0 | Y15: 1.95 | AC15: 0.365
A16: Power | B16: FR | D16: 2.6 | F16: 3.2 | H16: 1.8 | J16: 2.8 | L16: 0 | Q16: 0.866 | AB16: 2 | AH16: 1
A17: Power | B17: GR | E17: 0.5 | M17: 0 | Q17: 0.5 | S17: 0.3 | AF17: 1
A18: Power | B18: HR | N18: 0 | O18: 1 | S18: 1.1 | Z18: 1
A19: Power | B19: HU | C19: 0.8 | N19: 1.2 | O19: 0 | S19: 0.7 | X19: 0.4 | AA19: 0.8
A20: Power | B20: IE | P20: 0 | AB20: 0.45
A21: Power | B21: IT | C21: 0.1 | F21: 1.91 | L21: 1.16 | M21: 0.5 | Q21: 0 | Z21: 0.18
A22: Power | B22: LU | H22: 0.98 | R22: 0
A23: Power | B23: NONEU_Balkan | E23: 0.35 | M23: 0.3 | N23: 1.1 | O23: 0.7 | S23: 0 | X23: 0.2
A24: Power | B24: NL | D24: 1.426 | H24: 2.4 | I24: 0.7 | T24: 0 | U24: 0.723 | AB24: 1.016
A25: Power | B25: NO | H25: 1.444 | I25: 1.7 | T25: 0.723 | U25: 0 | Y25: 3.445 | AB25: 2.8
A26: Power | B26: PL | G26: 0.1 | H26: 0.225 | V26: 0 | Y26: 0.26591667 | AA26: 0.6
A27: Power | B27: PT | J27: 4.5 | W27: 0
A28: Power | B28: RO | E28: 0.6 | O28: 0.7 | S28: 0.2 | X28: 0
A29: Power | B29: SE | H29: 0.61 | I29: 2.44 | K29: 2.25 | U29: 3.695 | V29: 0.34166667 | Y29: 0
A30: Power | B30: SI | C30: 0.95 | N30: 1.2 | Q30: 0.203 | Z30: 0
A31: Power | B31: SK | G31: 1.2 | O31: 1.3 | V31: 0.5 | AA31: 0
A32: Power | B32: UK | I32: 1.4 | L32: 2 | P32: 0.45 | T32: 1.016 | U32: 2.8 | AB32: 0
A33: Power | B33: EE | K33: 0.365 | AC33: 0 | AE33: 0.8
A34: Power | B34: LT | AD34: 0 | AE34: 1.5
A35: Power | B35: LV | AC35: 0.75 | AD35: 1.45 | AE35: 0 | AH35: 0
A36: Power | B36: TR | E36: 1 | M36: 1 | AF36: 0
A37: gas_natural | B37: FR | D37: 0 | F37: 371.51679 | H37: 0 | J37: 235.4081 | AH37: 606.92489
A38: gas_natural | B38: AT | H38: 568.68891 | O38: 185.05788 | Q38: 1633.042 | Z38: 160.50552 | AA38: 353.14069 | AH38: 2900.435
A39: gas_natural | B39: BE | H39: 446.66921 | L39: 1241.2427 | R39: 54.215199 | T39: 560.98464 | AB39: 1146.2235 | AH39: 3449.3352
A40: gas_natural | B40: BG | M40: 0 | S40: 0 | X40: 20.516173 | AF40: 0 | AH40: 20.516173
A41: gas_natural | B41: CH | Q41: 888.22233 | AH41: 888.22233
A42: gas_natural | B42: CZ | H42: 1575.6649 | V42: 39.948042 | AA42: 994.13555 | AH42: 2609.7485
A43: gas_natural | B43: DE | C43: 517.0418 | D43: 502.4893 | F43: 830.33431 | G43: 2641.1206 | I43: 144.33342 | L43: 823.35767 | R43: 55.213901 | T43: 1329.4267 | V43: 303.91899 | AH43: 7147.2366
A44: gas_natural | B44: DK | H44: 129.87108 | T44: 564.97945 | Y44: 125.55099 | AH44: 820.40152
A45: gas_natural | B45: EE | AE45: 285.34316 | AH45: 285.34316
A46: gas_natural | B46: ES | L46: 321.01105 | W46: 205.44707 | AH46: 526.45812
A47: gas_natural | B47: HR | O47: 108.4304 | AH47: 108.4304
A48: gas_natural | B48: HU | N48: 109.4291 | S48: 202.68638 | X48: 73.618534 | AH48: 385.73401
A49: gas_natural | B49: IE | AB49: 126.9777 | AH49: 126.9777
A50: gas_natural | B50: IT | C50: 1633.042 | F50: 0 | Z50: 40.376056 | AH50: 1673.418
A51: gas_natural | B51: LT | AE51: 96.160643 | AH51: 96.160643
A52: gas_natural | B52: LV | AC52: 261.08899 | AD52: 92.736525 | AH52: 353.82551
A53: gas_natural | B53: NL | D53: 1138.3765 | H53: 2629.8277 | AB53: 704.79759 | AH53: 4473.0018
A54: gas_natural | B54: NO | D54: 616.12 | H54: 2354.98 | L54: 800.08 | T54: 754.76118 | AB54: 2576.82 | AH54: 6844.5524
A55: gas_natural | B55: PL | H55: 1328.3295 | AH55: 1328.3295
A56: gas_natural | B56: PT | J56: 114.13726 | AH56: 114.13726
A57: gas_natural | B57: RO | E57: 0 | O57: 0 | AH57: 0
A58: gas_natural | B58: NONEU_Balkan | S58: 20.259364 | AH58: 20.259364
A59: gas_natural | B59: SI | C59: 0 | N59: 76.614637 | Q59: 30.524149 | AH59: 107.13879
A60: gas_natural | B60: SK | C60: 2196.0009 | G60: 741.8922 | O60: 181.14297 | AH60: 3119.0361
A61: gas_natural | B61: TR | M61: 0 | AH61: 0
A62: gas_natural | B62: UK | D62: 898.97361 | P62: 487.9368 | T62: 0 | AH62: 1386.9104

Sheet Par_TradeCapacityGrowthCosts
A1: TradeCapacityGrowthCosts{f in FUEL, r in REGION1, rr in REGION2}
A2: Costs of expanding trade capacity.
A3: Unit: M€/GW
C5: AL | D5: AT | E5: BA | F5: BE | G5: BG | H5: CH | I5: CZ | J5: DE | K5: DK | L5: ES | M5: FI | N5: FR | O5: GR | P5: HR | Q5: HU | R5: IE | S5: IT | T5: LU | U5: ME | V5: MK | W5: NL | X5: NO | Y5: PL | Z5: PT | AA5: RO | AB5: RS | AC5: SE | AD5: SI | AE5: SK | AF5: UK | AG5: EE | AH5: LT | AI5: LV | AJ5: UA | AK5: RU | AL5: BY | AM5: NONEU_Balkan | AN5: TR
A6: Power | B6: AL | C6: 2.1425 | D6: 2.1425 | E6: 2.1425 | F6: 2.1425 | G6: 2.1425 | H6: 2.1425 | I6: 2.1425 | J6: 2.1425 | K6: 2.1425 | L6: 2.1425 | M6: 2.1425 | N6: 2.1425 | O6: 2.1425 | P6: 2.1425 | Q6: 2.1425 | R6: 2.1425 | S6: 2.1425 | T6: 2.1425 | U6: 2.1425 | V6: 2.1425 | W6: 2.1425 | X6: 2.1425 | Y6: 2.1425 | Z6: 2.1425 | AA6: 2.1425 | AB6: 2.1425 | AC6: 2.1425 | AD6: 2.1425 | AE6: 2.1425 | AF6: 2.1425 | AG6: 2.1425 | AH6: 2.1425 | AI6: 2.1425 | AJ6: 2.1425 | AK6: 2.1425 | AL6: 2.1425 | AM6: 2.1425 | AN6: 2.1425
A7: Power | B7: AT | C7: 2.1425 | D7: 2.1425 | E7: 2.1425 | F7: 2.1425 | G7: 2.1425 | H7: 2.1425 | I7: 2.1425 | J7: 2.1425 | K7: 2.1425 | L7: 2.1425 | M7: 2.1425 | N7: 2.1425 | O7: 2.1425 | P7: 2.1425 | Q7: 2.1425 | R7: 2.1425 | S7: 2.1425 | T7: 2.1425 | U7: 2.1425 | V7: 2.1425 | W7: 2.1425 | X7: 2.1425 | Y7: 2.1425 | Z7: 2.1425 | AA7: 2.1425 | AB7: 2.1425 | AC7: 2.1425 | AD7: 2.1425 | AE7: 2.1425 | AF7: 2.1425 | AG7: 2.1425 | AH7: 2.1425 | AI7: 2.1425 | AJ7: 2.1425 | AK7: 2.1425 | AL7: 2.1425 | AM7: 2.1425 | AN7: 2.1425
A8: Power | B8: BA | C8: 2.1425 | D8: 2.1425 | E8: 2.1425 | F8: 2.1425 | G8: 2.1425 | H8: 2.1425 | I8: 2.1425 | J8: 2.1425 | K8: 2.1425 | L8: 2.1425 | M8: 2.1425 | N8: 2.1425 | O8: 2.1425 | P8: 2.1425 | Q8: 2.1425 | R8: 2.1425 | S8: 2.1425 | T8: 2.1425 | U8: 2.1425 | V8: 2.1425 | W8: 2.1425 | X8: 2.1425 | Y8: 2.1425 | Z8: 2.1425 | AA8: 2.1425 | AB8: 2.1425 | AC8: 2.1425 | AD8: 2.1425 | AE8: 2.1425 | AF8: 2.1425 | AG8: 2.1425 | AH8: 2.1425 | AI8: 2.1425 | AJ8: 2.1425 | AK8: 2.1425 | AL8: 2.1425 | AM8: 2.1425 | AN8: 2.1425
A9: Power | B9: BE | C9: 2.1425 | D9: 2.1425 | E9: 2.1425 | F9: 2.1425 | G9: 2.1425 | H9: 2.1425 | I9: 2.1425 | J9: 2.1425 | K9: 2.1425 | L9: 2.1425 | M9: 2.1425 | N9: 2.1425 | O9: 2.1425 | P9: 2.1425 | Q9: 2.1425 | R9: 2.1425 | S9: 2.1425 | T9: 2.1425 | U9: 2.1425 | V9: 2.1425 | W9: 2.1425 | X9: 2.1425 | Y9: 2.1425 | Z9: 2.1425 | AA9: 2.1425 | AB9: 2.1425 | AC9: 2.1425 | AD9: 2.1425 | AE9: 2.1425 | AF9: 2.1425 | AG9: 2.1425 | AH9: 2.1425 | AI9: 2.1425 | AJ9: 2.1425 | AK9: 2.1425 | AL9: 2.1425 | AM9: 2.1425 | AN9: 2.1425
A10: Power | B10: BG | C10: 2.1425 | D10: 2.1425 | E10: 2.1425 | F10: 2.1425 | G10: 2.1425 | H10: 2.1425 | I10: 2.1425 | J10: 2.1425 | K10: 2.1425 | L10: 2.1425 | M10: 2.1425 | N10: 2.1425 | O10: 2.1425 | P10: 2.1425 | Q10: 2.1425 | R10: 2.1425 | S10: 2.1425 | T10: 2.1425 | U10: 2.1425 | V10: 2.1425 | W10: 2.1425 | X10: 2.1425 | Y10: 2.1425 | Z10: 2.1425 | AA10: 2.1425 | AB10: 2.1425 | AC10: 2.1425 | AD10: 2.1425 | AE10: 2.1425 | AF10: 2.1425 | AG10: 2.1425 | AH10: 2.1425 | AI10: 2.1425 | AJ10: 2.1425 | AK10: 2.1425 | AL10: 2.1425 | AM10: 2.1425 | AN10: 2.1425
A11: Power | B11: CH | C11: 2.1425 | D11: 2.1425 | E11: 2.1425 | F11: 2.1425 | G11: 2.1425 | H11: 2.1425 | I11: 2.1425 | J11: 2.1425 | K11: 2.1425 | L11: 2.1425 | M11: 2.1425 | N11: 2.1425 | O11: 2.1425 | P11: 2.1425 | Q11: 2.1425 | R11: 2.1425 | S11: 2.1425 | T11: 2.1425 | U11: 2.1425 | V11: 2.1425 | W11: 2.1425 | X11: 2.1425 | Y11: 2.1425 | Z11: 2.1425 | AA11: 2.1425 | AB11: 2.1425 | AC11: 2.1425 | AD11: 2.1425 | AE11: 2.1425 | AF11: 2.1425 | AG11: 2.1425 | AH11: 2.1425 | AI11: 2.1425 | AJ11: 2.1425 | AK11: 2.1425 | AL11: 2.1425 | AM11: 2.1425 | AN11: 2.1425
A12: Power | B12: CZ | C12: 2.1425 | D12: 2.1425 | E12: 2.1425 | F12: 2.1425 | G12: 2.1425 | H12: 2.1425 | I12: 2.1425 | J12: 2.1425 | K12: 2.1425 | L12: 2.1425 | M12: 2.1425 | N12: 2.1425 | O12: 2.1425 | P12: 2.1425 | Q12: 2.1425 | R12: 2.1425 | S12: 2.1425 | T12: 2.1425 | U12: 2.1425 | V12: 2.1425 | W12: 2.1425 | X12: 2.1425 | Y12: 2.1425 | Z12: 2.1425 | AA12: 2.1425 | AB12: 2.1425 | AC12: 2.1425 | AD12: 2.1425 | AE12: 2.1425 | AF12: 2.1425 | AG12: 2.1425 | AH12: 2.1425 | AI12: 2.1425 | AJ12: 2.1425 | AK12: 2.1425 | AL12: 2.1425 | AM12: 2.1425 | AN12: 2.1425
A13: Power | B13: DE | C13: 2.1425 | D13: 2.1425 | E13: 2.1425 | F13: 2.1425 | G13: 2.1425 | H13: 2.1425 | I13: 2.1425 | J13: 2.1425 | K13: 2.1425 | L13: 2.1425 | M13: 2.1425 | N13: 2.1425 | O13: 2.1425 | P13: 2.1425 | Q13: 2.1425 | R13: 2.1425 | S13: 2.1425 | T13: 2.1425 | U13: 2.1425 | V13: 2.1425 | W13: 2.1425 | X13: 2.1425 | Y13: 2.1425 | Z13: 2.1425 | AA13: 2.1425 | AB13: 2.1425 | AC13: 2.1425 | AD13: 2.1425 | AE13: 2.1425 | AF13: 2.1425 | AG13: 2.1425 | AH13: 2.1425 | AI13: 2.1425 | AJ13: 2.1425 | AK13: 2.1425 | AL13: 2.1425 | AM13: 2.1425 | AN13: 2.1425
A14: Power | B14: DK | C14: 2.1425 | D14: 2.1425 | E14: 2.1425 | F14: 2.1425 | G14: 2.1425 | H14: 2.1425 | I14: 2.1425 | J14: 2.1425 | K14: 2.1425 | L14: 2.1425 | M14: 2.1425 | N14: 2.1425 | O14: 2.1425 | P14: 2.1425 | Q14: 2.1425 | R14: 2.1425 | S14: 2.1425 | T14: 2.1425 | U14: 2.1425 | V14: 2.1425 | W14: 2.1425 | X14: 2.1425 | Y14: 2.1425 | Z14: 2.1425 | AA14: 2.1425 | AB14: 2.1425 | AC14: 2.1425 | AD14: 2.1425 | AE14: 2.1425 | AF14: 2.1425 | AG14: 2.1425 | AH14: 2.1425 | AI14: 2.1425 | AJ14: 2.1425 | AK14: 2.1425 | AL14: 2.1425 | AM14: 2.1425 | AN14: 2.1425
A15: Power | B15: ES | C15: 2.1425 | D15: 2.1425 | E15: 2.1425 | F15: 2.1425 | G15: 2.1425 | H15: 2.1425 | I15: 2.1425 | J15: 2.1425 | K15: 2.1425 | L15: 2.1425 | M15: 2.1425 | N15: 2.1425 | O15: 2.1425 | P15: 2.1425 | Q15: 2.1425 | R15: 2.1425 | S15: 2.1425 | T15: 2.1425 | U15: 2.1425 | V15: 2.1425 | W15: 2.1425 | X15: 2.1425 | Y15: 2.1425 | Z15: 2.1425 | AA15: 2.1425 | AB15: 2.1425 | AC15: 2.1425 | AD15: 2.1425 | AE15: 2.1425 | AF15: 2.1425 | AG15: 2.1425 | AH15: 2.1425 | AI15: 2.1425 | AJ15: 2.1425 | AK15: 2.1425 | AL15: 2.1425 | AM15: 2.1425 | AN15: 2.1425
A16: Power | B16: FI | C16: 2.1425 | D16: 2.1425 | E16: 2.1425 | F16: 2.1425 | G16: 2.1425 | H16: 2.1425 | I16: 2.1425 | J16: 2.1425 | K16: 2.1425 | L16: 2.1425 | M16: 2.1425 | N16: 2.1425 | O16: 2.1425 | P16: 2.1425 | Q16: 2.1425 | R16: 2.1425 | S16: 2.1425 | T16: 2.1425 | U16: 2.1425 | V16: 2.1425 | W16: 2.1425 | X16: 2.1425 | Y16: 2.1425 | Z16: 2.1425 | AA16: 2.1425 | AB16: 2.1425 | AC16: 2.1425 | AD16: 2.1425 | AE16: 2.1425 | AF16: 2.1425 | AG16: 2.1425 | AH16: 2.1425 | AI16: 2.1425 | AJ16: 2.1425 | AK16: 2.1425 | AL16: 2.1425 | AM16: 2.1425 | AN16: 2.1425
A17: Power | B17: FR | C17: 2.1425 | D17: 2.1425 | E17: 2.1425 | F17: 2.1425 | G17: 2.1425 | H17: 2.1425 | I17: 2.1425 | J17: 2.1425 | K17: 2.1425 | L17: 2.1425 | M17: 2.1425 | N17: 2.1425 | O17: 2.1425 | P17: 2.1425 | Q17: 2.1425 | R17: 2.1425 | S17: 2.1425 | T17: 2.1425 | U17: 2.1425 | V17: 2.1425 | W17: 2.1425 | X17: 2.1425 | Y17: 2.1425 | Z17: 2.1425 | AA17: 2.1425 | AB17: 2.1425 | AC17: 2.1425 | AD17: 2.1425 | AE17: 2.1425 | AF17: 2.1425 | AG17: 2.1425 | AH17: 2.1425 | AI17: 2.1425 | AJ17: 2.1425 | AK17: 2.1425 | AL17: 2.1425 | AM17: 2.1425 | AN17: 2.1425
... A43: Power | B43: TR | C43: 2.1425 | D43: 2.1425 | E43: 2.1425 | F43: 2.1425 | G43: 2.1425 | H43: 2.1425 | I43: 2.1425 | J43: 2.1425 | K43: 2.1425 | L43: 2.1425 | M43: 2.1425 | N43: 2.1425 | O43: 2.1425 | P43: 2.1425 | Q43: 2.1425 | R43: 2.1425 | S43: 2.1425 | T43: 2.1425 | U43: 2.1425 | V43: 2.1425 | W43: 2.1425 | X43: 2.1425 | Y43: 2.1425 | Z43: 2.1425 | AA43: 2.1425 | AB43: 2.1425 | AC43: 2.1425 | AD43: 2.1425 | AE43: 2.1425 | AF43: 2.1425 | AG43: 2.1425 | AH43: 2.1425 | AI43: 2.1425 | AJ43: 2.1425 | AK43: 2.1425 | AL43: 2.1425 | AM43: 2.1425 | AN43: 2.1425

Sheet Par_GrowthRateTradeCapacity
A1: GrowthRateTradeCapacity{y in YEAR, f in FUEL, r in REGION1, rr in REGION2}
A2: Defines by how much the trade capacity between two regions can grow
A3: Unit: Factor
D5: AL | E5: AT | F5: BA | G5: BE | H5: BG | I5: CH | J5: CZ | K5: DE | L5: DK | M5: ES | N5: FI | O5: FR | P5: GR | Q5: HR | R5: HU | S5: IE | T5: IT | U5: LU | V5: ME | W5: MK | X5: NL | Y5: NO | Z5: PL | AA5: PT | AB5: RO | AC5: RS | AD5: SE | AE5: SI | AF5: SK | AG5: UK | AH5: EE | AI5: LT | AJ5: LV | AK5: UA | AL5: RU | AM5: BY
A6: 2018 | B6: Power | C6: AL | D6: 2 | E6: 2 | F6: 2 | G6: 2 | H6: 2 | I6: 2 | J6: 2 | K6: 2 | L6: 2 | M6: 2 | N6: 2 | O6: 2 | P6: 2 | Q6: 2 | R6: 2 | S6: 2 | T6: 2 | U6: 2 | V6: 2 | W6: 2 | X6: 2 | Y6: 2 | Z6: 2 | AA6: 2 | AB6: 2 | AC6: 2 | AD6: 2 | AE6: 2 | AF6: 2 | AG6: 2 | AH6: 2 | AI6: 2 | AJ6: 2 | AK6: 2 | AL6: 2 | AM6: 2
A7: 2018 | B7: Power | C7: AT | D7: 2 | E7: 2 | F7: 2 | G7: 2 | H7: 2 | I7: 2 | J7: 2 | K7: 2 | L7: 2 | M7: 2 | N7: 2 | O7: 2 | P7: 2 | Q7: 2 | R7: 2 | S7: 2 | T7: 2 | U7: 2 | V7: 2 | W7: 2 | X7: 2 | Y7: 2 | Z7: 2 | AA7: 2 | AB7: 2 | AC7: 2 | AD7: 2 | AE7: 2 | AF7: 2 | AG7: 2 | AH7: 2 | AI7: 2 | AJ7: 2 | AK7: 2 | AL7: 2 | AM7: 2
A8: 2018 | B8: Power | C8: BA | D8: 2 | E8: 2 | F8: 2 | G8: 2 | H8: 2 | I8: 2 | J8: 2 | K8: 2 | L8: 2 | M8: 2 | N8: 2 | O8: 2 | P8: 2 | Q8: 2 | R8: 2 | S8: 2 | T8: 2 | U8: 2 | V8: 2 | W8: 2 | X8: 2 | Y8: 2 | Z8: 2 | AA8: 2 | AB8: 2 | AC8: 2 | AD8: 2 | AE8: 2 | AF8: 2 | AG8: 2 | AH8: 2 | AI8: 2 | AJ8: 2 | AK8: 2 | AL8: 2 | AM8: 2
A9: 2018 | B9: Power | C9: BE | D9: 2 | E9: 2 | F9: 2 | G9: 2 | H9: 2 | I9: 2 | J9: 2 | K9: 2 | L9: 2 | M9: 2 | N9: 2 | O9: 2 | P9: 2 | Q9: 2 | R9: 2 | S9: 2 | T9: 2 | U9: 2 | V9: 2 | W9: 2 | X9: 2 | Y9: 2 | Z9: 2 | AA9: 2 | AB9: 2 | AC9: 2 | AD9: 2 | AE9: 2 | AF9: 2 | AG9: 2 | AH9: 2 | AI9: 2 | AJ9: 2 | AK9: 2 | AL9: 2 | AM9: 2
A10: 2018 | B10: Power | C10: BG | D10: 2 | E10: 2 | F10: 2 | G10: 2 | H10: 2 | I10: 2 | J10: 2 | K10: 2 | L10: 2 | M10: 2 | N10: 2 | O10: 2 | P10: 2 | Q10: 2 | R10: 2 | S10: 2 | T10: 2 | U10: 2 | V10: 2 | W10: 2 | X10: 2 | Y10: 2 | Z10: 2 | AA10: 2 | AB10: 2 | AC10: 2 | AD10: 2 | AE10: 2 | AF10: 2 | AG10: 2 | AH10: 2 | AI10: 2 | AJ10: 2 | AK10: 2 | AL10: 2 | AM10: 2
A11: 2018 | B11: Power | C11: CH | D11: 2 | E11: 2 | F11: 2 | G11: 2 | H11: 2 | I11: 2 | J11: 2 | K11: 2 | L11: 2 | M11: 2 | N11: 2 | O11: 2 | P11: 2 | Q11: 2 | R11: 2 | S11: 2 | T11: 2 | U11: 2 | V11: 2 | W11: 2 | X11: 2 | Y11: 2 | Z11: 2 | AA11: 2 | AB11: 2 | AC11: 2 | AD11: 2 | AE11: 2 | AF11: 2 | AG11: 2 | AH11: 2 | AI11: 2 | AJ11: 2 | AK11: 2 | AL11: 2 | AM11: 2
A12: 2018 | B12: Power | C12: CZ | D12: 2 | E12: 2 | F12: 2 | G12: 2 | H12: 2 | I12: 2 | J12: 2 | K12: 2 | L12: 2 | M12: 2 | N12: 2 | O12: 2 | P12: 2 | Q12: 2 | R12: 2 | S12: 2 | T12: 2 | U12: 2 | V12: 2 | W12: 2 | X12: 2 | Y12: 2 | Z12: 2 | AA12: 2 | AB12: 2 | AC12: 2 | AD12: 2 | AE12: 2 | AF12: 2 | AG12: 2 | AH12: 2 | AI12: 2 | AJ12: 2 | AK12: 2 | AL12: 2 | AM12: 2
A13: 2018 | B13: Power | C13: DE | D13: 2 | E13: 2 | F13: 2 | G13: 2 | H13: 2 | I13: 2 | J13: 2 | K13: 2 | L13: 2 | M13: 2 | N13: 2 | O13: 2 | P13: 2 | Q13: 2 | R13: 2 | S13: 2 | T13: 2 | U13: 2 | V13: 2 | W13: 2 | X13: 2 | Y13: 2 | Z13: 2 | AA13: 2 | AB13: 2 | AC13: 2 | AD13: 2 | AE13: 2 | AF13: 2 | AG13: 2 | AH13: 2 | AI13: 2 | AJ13: 2 | AK13: 2 | AL13: 2 | AM13: 2
A14: 2018 | B14: Power | C14: DK | D14: 2 | E14: 2 | F14: 2 | G14: 2 | H14: 2 | I14: 2 | J14: 2 | K14: 2 | L14: 2 | M14: 2 | N14: 2 | O14: 2 | P14: 2 | Q14: 2 | R14: 2 | S14: 2 | T14: 2 | U14: 2 | V14: 2 | W14: 2 | X14: 2 | Y14: 2 | Z14: 2 | AA14: 2 | AB14: 2 | AC14: 2 | AD14: 2 | AE14: 2 | AF14: 2 | AG14: 2 | AH14: 2 | AI14: 2 | AJ14: 2 | AK14: 2 | AL14: 2 | AM14: 2
A15: 2018 | B15: Power | C15: ES | D15: 2 | E15: 2 | F15: 2 | G15: 2 | H15: 2 | I15: 2 | J15: 2 | K15: 2 | L15: 2 | M15: 2 | N15: 2 | O15: 2 | P15: 2 | Q15: 2 | R15: 2 | S15: 2 | T15: 2 | U15: 2 | V15: 2 | W15: 2 | X15: 2 | Y15: 2 | Z15: 2 | AA15: 2 | AB15: 2 | AC15: 2 | AD15: 2 | AE15: 2 | AF15: 2 | AG15: 2 | AH15: 2 | AI15: 2 | AJ15: 2 | AK15: 2 | AL15: 2 | AM15: 2
A16: 2018 | B16: Power | C16: FI | D16: 2 | E16: 2 | F16: 2 | G16: 2 | H16: 2 | I16: 2 | J16: 2 | K16: 2 | L16: 2 | M16: 2 | N16: 2 | O16: 2 | P16: 2 | Q16: 2 | R16: 2 | S16: 2 | T16: 2 | U16: 2 | V16: 2 | W16: 2 | X16: 2 | Y16: 2 | Z16: 2 | AA16: 2 | AB16: 2 | AC16: 2 | AD16: 2 | AE16: 2 | AF16: 2 | AG16: 2 | AH16: 2 | AI16: 2 | AJ16: 2 | AK16: 2 | AL16: 2 | AM16: 2
A17: 2018 | B17: Power | C17: FR | D17: 2 | E17: 2 | F17: 2 | G17: 2 | H17: 2 | I17: 2 | J17: 2 | K17: 2 | L17: 2 | M17: 2 | N17: 2 | O17: 2 | P17: 2 | Q17: 2 | R17: 2 | S17: 2 | T17: 2 | U17: 2 | V17: 2 | W17: 2 | X17: 2 | Y17: 2 | Z17: 2 | AA17: 2 | AB17: 2 | AC17: 2 | AD17: 2 | AE17: 2 | AF17: 2 | AG17: 2 | AH17: 2 | AI17: 2 | AJ17: 2 | AK17: 2 | AL17: 2 | AM17: 2
... A41: 2018 | B41: Power | C41: BY | D41: 2 | E41: 2 | F41: 2 | G41: 2 | H41: 2 | I41: 2 | J41: 2 | K41: 2 | L41: 2 | M41: 2 | N41: 2 | O41: 2 | P41: 2 | Q41: 2 | R41: 2 | S41: 2 | T41: 2 | U41: 2 | V41: 2 | W41: 2 | X41: 2 | Y41: 2 | Z41: 2 | AA41: 2 | AB41: 2 | AC41: 2 | AD41: 2 | AE41: 2 | AF41: 2 | AG41: 2 | AH41: 2 | AI41: 2 | AJ41: 2 | AK41: 2 | AL41: 2 | AM41: 2

Sheet Par_AnnualExogenousEmission
A1: AnnualExogenousEmission{r in REGION, e in EMISSION, y in YEAR)
A2: Amount of external Emissions for a year in a certain region.
A3: Unit: Megatonnes
A5: Region | B5: Emission | C5: 2018 | D5: 2020 | E5: 2025 | F5: 2030 | G5: 2035 | H5: 2040 | I5: 2045 | J5: 2050

Sheet Par_AnnualEmissionLimit
A1: AnnualEmissionLimit{e in EMISSION, y in YEAR}
A2: Limits the maximum amount of Emissions in a year.
A3: Unit: Megatonnes
B5: 2018 | C5: 2020 | D5: 2025 | E5: 2030 | F5: 2035 | G5: 2040 | H5: 2045 | I5: 2050
A6: CO2 | B6: 99999 | C6: 99999 | D6: 99999 | E6: 99999 | F6: 99999 | G6: 99999 | H6: 99999 | I6: 99999

Sheet Par_AnnualSectoralEmissionLimit
A1: AnnualSectoralEmissionLimit{e in EMISSION, se in SECTOR, y in YEAR}
A2: Limits the maximum amount of Emissions for a specific sector and region in a year.
A3: Unit: Megatonnes
A5: Emission | B5: Sector | C5: 2018 | D5: 2020 | E5: 2025 | F5: 2030 | G5: 2035 | H5: 2040 | I5: 2045 | J5: 2050
A6: CO2 | B6: Power | C6: 999999 | D6: 999999 | E6: 999999 | F6: 999999 | G6: 999999 | H6: 999999 | I6: 999999 | J6: 999999
A7: CO2 | B7: Industry | C7: 999999 | D7: 999999 | E7: 999999 | F7: 999999 | G7: 999999 | H7: 999999 | I7: 999999 | J7: 999999
A8: CO2 | B8: Buildings | C8: 999999 | D8: 999999 | E8: 999999 | F8: 999999 | G8: 999999 | H8: 999999 | I8: 999999 | J8: 999999
A9: CO2 | B9: Transportation | C9: 999999 | D9: 999999 | E9: 999999 | F9: 999999 | G9: 999999 | H9: 999999 | I9: 999999 | J9: 999999
A10: CO2 | B10: Resources | C10: 999999 | D10: 999999 | E10: 999999 | F10: 999999 | G10: 999999 | H10: 999999 | I10: 999999 | J10: 999999
A11: CO2 | B11: Storages | C11: 999999 | D11: 999999 | E11: 999999 | F11: 999999 | G11: 999999 | H11: 999999 | I11: 999999 | J11: 999999
A12: CO2 | B12: Transformation | C12: 999999 | D12: 999999 | E12: 999999 | F12: 999999 | G12: 999999 | H12: 999999 | I12: 999999 | J12: 999999
A13: CO2 | B13: CHP | C13: 999999 | D13: 999999 | E13: 999999 | F13: 999999 | G13: 999999 | H13: 999999 | I13: 999999 | J13: 999999

Sheet Par_RegionalAnnualEmissionLimit
A1: RegionalAnnualEmissionLimit{r in REGION, e in EMISSION, y in YEAR}
A2: Limits the maximum amount of Emissions for a certain region in a year.
A3: Unit: Megatonnes
A5: Region | B5: Emission | C5: 2018 | D5: 2020 | E5: 2025 | F5: 2030 | G5: 2035 | H5: 2040 | I5: 2045 | J5: 2050
A6: AL | B6: CO2 | C6: 999999 | D6: 999999 | E6: 999999 | F6: 999999 | G6: 999999 | H6: 999999 | I6: 999999 | J6: 999999
A7: AT | B7: CO2 | C7: 999999 | D7: 999999 | E7: 999999 | F7: 999999 | G7: 999999 | H7: 999999 | I7: 999999 | J7: 999999
A8: BA | B8: CO2 | C8: 999999 | D8: 999999 | E8: 999999 | F8: 999999 | G8: 999999 | H8: 999999 | I8: 999999 | J8: 999999
A9: BE | B9: CO2 | C9: 999999 | D9: 999999 | E9: 999999 | F9: 999999 | G9: 999999 | H9: 999999 | I9: 999999 | J9: 999999
A10: BG | B10: CO2 | C10: 999999 | D10: 999999 | E10: 999999 | F10: 999999 | G10: 999999 | H10: 999999 | I10: 999999 | J10: 999999
A11: CH | B11: CO2 | C11: 999999 | D11: 999999 | E11: 999999 | F11: 999999 | G11: 999999 | H11: 999999 | I11: 999999 | J11: 999999
A12: CZ | B12: CO2 | C12: 999999 | D12: 999999 | E12: 999999 | F12: 999999 | G12: 999999 | H12: 999999 | I12: 999999 | J12: 999999
A13: DE | B13: CO2 | C13: 999999 | D13: 999999 | E13: 999999 | F13: 999999 | G13: 999999 | H13: 999999 | I13: 999999 | J13: 999999
A14: DK | B14: CO2 | C14: 999999 | D14: 999999 | E14: 999999 | F14: 999999 | G14: 999999 | H14: 999999 | I14: 999999 | J14: 999999
A15: ES | B15: CO2 | C15: 999999 | D15: 999999 | E15: 999999 | F15: 999999 | G15: 999999 | H15: 999999 | I15: 999999 | J15: 999999
A16: FI | B16: CO2 | C16: 999999 | D16: 999999 | E16: 999999 | F16: 999999 | G16: 999999 | H16: 999999 | I16: 999999 | J16: 999999
... A43: NONEU_Balkan | B43: CO2 | C43: 999999 | D43: 999999 | E43: 999999 | F43: 999999 | G43: 999999 | H43: 999999 | I43: 999999 | J43: 999999

Sheet Par_EmissionActivityRatio
A1: EmissionActivityRatio{r in REGION, t in TECHNOLOGY, e in EMISSION, m in MODEOFOPERATION, y in YEAR}
A2: Emissions factor per unit of activity.
A3: Unit: Fraction
E5: 2018 | F5: 2020 | G5: 2025 | H5: 2030 | I5: 2035 | J5: 2040 | K5: 2045 | L5: 2050
A6: DE | B6: CHP_Coal_Hardcoal | C6: CO2 | D6: 1 | E6: 1 | F6: 1 | G6: 1 | H6: 1 | I6: 1 | J6: 1 | K6: 1 | L6: 1
A7: DE | B7: CHP_Coal_Lignite | C7: CO2 | D7: 1 | E7: 1 | F7: 1 | G7: 1 | H7: 1 | I7: 1 | J7: 1 | K7: 1 | L7: 1
A8: DE | B8: CHP_Gas | C8: CO2 | D8: 1 | E8: 1 | F8: 1 | G8: 1 | H8: 1 | I8: 1 | J8: 1 | K8: 1 | L8: 1
A9: DE | B9: FRT_Rail_Conv | C9: CO2 | D9: 1 | E9: 1 | F9: 1 | G9: 1 | H9: 1 | I9: 1 | J9: 1 | K9: 1 | L9: 1
A10: DE | B10: FRT_Road_ICE | C10: CO2 | D10: 1 | E10: 1 | F10: 1 | G10: 1 | H10: 1 | I10: 1 | J10: 1 | K10: 1 | L10: 1
A11: DE | B11: FRT_Road_ICE | C11: CO2 | D11: 2 | E11: 0 | F11: 0 | G11: 0 | H11: 0 | I11: 0 | J11: 0 | K11: 0 | L11: 0
A12: DE | B12: FRT_Road_PHEV | C12: CO2 | D12: 1 | E12: 1 | F12: 1 | G12: 1 | H12: 1 | I12: 1 | J12: 1 | K12: 1 | L12: 1
A13: DE | B13: FRT_Road_PHEV | C13: CO2 | D13: 2 | E13: 0 | F13: 0 | G13: 0 | H13: 0 | I13: 0 | J13: 0 | K13: 0 | L13: 0
A14: DE | B14: FRT_Ship_Conv | C14: CO2 | D14: 1 | E14: 1 | F14: 1 | G14: 1 | H14: 1 | I14: 1 | J14: 1 | K14: 1 | L14: 1
A15: DE | B15: HHT_Coal_Hardcoal | C15: CO2 | D15: 1 | E15: 1 | F15: 1 | G15: 1 | H15: 1 | I15: 1 | J15: 1 | K15: 1 | L15: 1
A16: DE | B16: HHT_Coal_Lignite | C16: CO2 | D16: 1 | E16: 1 | F16: 1 | G16: 1 | H16: 1 | I16: 1 | J16: 1 | K16: 1 | L16: 1
A17: DE | B17: HHT_Gas | C17: CO2 | D17: 1 | E17: 1 | F17: 1 | G17: 1 | H17: 1 | I17: 1 | J17: 1 | K17: 1 | L17: 1
... A113: DE | B113: P_Gas_Engines | C113: CO2 | D113: 1 | E113: 1 | F113: 1 | G113: 1 | H113: 1 | I113: 1 | J113: 1 | K113: 1 | L113: 1

Sheet Par_EmissionPenaltyTagTech
A1: EmissionPenaltyTagTech{r in REGION, t in TECHNOLOGY, e in EMISSION, y in YEAR}
A2: Tags all technologies which produce emissions.
A3: Unit: Binary
A5: Region | B5: Technology | C5: Emission | D5: 2018 | E5: 2020 | F5: 2025 | G5: 2030 | H5: 2035 | I5: 2040 | J5: 2045 | K5: 2050
A6: DE | B6: CHP_Coal_Hardcoal | C6: CO2 | D6: 1 | E6: 1 | F6: 1 | G6: 1 | H6: 1 | I6: 1 | J6: 1 | K6: 1
A7: DE | B7: CHP_Coal_Lignite | C7: CO2 | D7: 1 | E7: 1 | F7: 1 | G7: 1 | H7: 1 | I7: 1 | J7: 1 | K7: 1
A8: DE | B8: CHP_Gas | C8: CO2 | D8: 1 | E8: 1 | F8: 1 | G8: 1 | H8: 1 | I8: 1 | J8: 1 | K8: 1
A9: DE | B9: FRT_Rail_Conv | C9: CO2 | D9: 1 | E9: 1 | F9: 1 | G9: 1 | H9: 1 | I9: 1 | J9: 1 | K9: 1
A10: DE | B10: FRT_Road_ICE | C10: CO2 | D10: 1 | E10: 1 | F10: 1 | G10: 1 | H10: 1 | I10: 1 | J10: 1 | K10: 1
A11: DE | B11: FRT_Road_PHEV | C11: CO2 | D11: 1 | E11: 1 | F11: 1 | G11: 1 | H11: 1 | I11: 1 | J11: 1 | K11: 1
A12: DE | B12: FRT_Ship_Conv | C12: CO2 | D12: 1 | E12: 1 | F12: 1 | G12: 1 | H12: 1 | I12: 1 | J12: 1 | K12: 1
A13: DE | B13: P_Coal_Hardcoal | C13: CO2 | D13: 1 | E13: 1 | F13: 1 | G13: 1 | H13: 1 | I13: 1 | J13: 1 | K13: 1
A14: DE | B14: P_Coal_Lignite | C14: CO2 | D14: 1 | E14: 1 | F14: 1 | G14: 1 | H14: 1 | I14: 1 | J14: 1 | K14: 1
A15: DE | B15: P_Gas | C15: CO2 | D15: 1 | E15: 1 | F15: 1 | G15: 1 | H15: 1 | I15: 1 | J15: 1 | K15: 1
A16: DE | B16: P_Oil | C16: CO2 | D16: 1 | E16: 1 | F16: 1 | G16: 1 | H16: 1 | I16: 1 | J16: 1 | K16: 1
... A101: DE | B101: P_Gas_Engines | C101: CO2 | D101: 1 | E101: 1 | F101: 1 | G101: 1 | H101: 1 | I101: 1 | J101: 1 | K101: 1

Sheet Par_EmissionContentPerFuel
A1: EmissionContentPerFuel{f in FUEL, e in EMISSION}
A2: Emission content per unit of energy per fuel
A3: Unit: Megatonnes/PJ
A5: Hardcoal | B5: CO2 | C5: =0.0946 -> 0.0946
A6: Lignite | B6: CO2 | C6: =101000/1000000 -> 0.101
A7: Gas_Natural | B7: CO2 | C7: =0.0561 -> 0.0561
A8: Oil | B8: CO2 | C8: =73300/1000000 -> 0.0733
A9: Biomass | B9: CO2 | C9: 0.11
A10: Air | B10: CO2 | C10: 1
A11: LNG | B11: CO2 | C11: =C7 -> 0.0561
A12: ETS | B12: CO2 | C12: 1
A13: ETS_Source | B13: CO2 | C13: 1

Sheet Par_EmissionsPenalty
A1: EmissionsPenalty{r in REGION, e in EMISSION, y in YEAR}
A2: Externality cost per unit of emission
A3: Unit: M€/Megatonnes
C5: 2018 | D5: 2020 | E5: 2025 | F5: 2030 | G5: 2035 | H5: 2040 | I5: 2045 | J5: 2050
A6: AT | B6: CO2 | C6: 15.06 | D6: 30 | E6: 325 | F6: 577.85714 | G6: 830.71429 | H6: 1184.7143 | I6: 1492.5404 | J6: 1800
A7: BE | B7: CO2 | C7: 15.06 | D7: 30 | E7: 325 | F7: 577.85714 | G7: 830.71429 | H7: 1184.7143 | I7: 1492.5404 | J7: 1800
A8: BG | B8: CO2 | C8: 15.06 | D8: 30 | E8: 325 | F8: 577.85714 | G8: 830.71429 | H8: 1184.7143 | I8: 1492.5404 | J8: 1800
A9: CH | B9: CO2 | C9: 15.06 | D9: 30 | E9: 325 | F9: 577.85714 | G9: 830.71429 | H9: 1184.7143 | I9: 1492.5404 | J9: 1800
A10: CZ | B10: CO2 | C10: 15.06 | D10: 30 | E10: 325 | F10: 577.85714 | G10: 830.71429 | H10: 1184.7143 | I10: 1492.5404 | J10: 1800
A11: DE | B11: CO2 | C11: 15.06 | D11: 30 | E11: 325 | F11: 577.85714 | G11: 830.71429 | H11: 1184.7143 | I11: 1492.5404 | J11: 1800
A12: DK | B12: CO2 | C12: 15.06 | D12: 30 | E12: 325 | F12: 577.85714 | G12: 830.71429 | H12: 1184.7143 | I12: 1492.5404 | J12: 1800
A13: EE | B13: CO2 | C13: 15.06 | D13: 30 | E13: 325 | F13: 577.85714 | G13: 830.71429 | H13: 1184.7143 | I13: 1492.5404 | J13: 1800
A14: ES | B14: CO2 | C14: 15.06 | D14: 30 | E14: 325 | F14: 577.85714 | G14: 830.71429 | H14: 1184.7143 | I14: 1492.5404 | J14: 1800
A15: FI | B15: CO2 | C15: 15.06 | D15: 30 | E15: 325 | F15: 577.85714 | G15: 830.71429 | H15: 1184.7143 | I15: 1492.5404 | J15: 1800
A16: FR | B16: CO2 | C16: 15.06 | D16: 30 | E16: 325 | F16: 577.85714 | G16: 830.71429 | H16: 1184.7143 | I16: 1492.5404 | J16: 1800
A17: GR | B17: CO2 | C17: 15.06 | D17: 30 | E17: 325 | F17: 577.85714 | G17: 830.71429 | H17: 1184.7143 | I17: 1492.5404 | J17: 1800
... A35: NONEU_Balkan | B35: CO2 | C35: 15.06 | D35: 30 | E35: 325 | F35: 577.85714 | G35: 830.71429 | H35: 1184.7143 | I35: 1492.5404 | J35: 1800

Sheet Par_SpecifiedAnnualDemand
A1: SpecifiedAnnualDemand{r in REGION, f in FUEL, y in YEAR}
A2: The annual demand for each output fuel. Hourly Data parameters distribute this demand over the timesteps.
A3: Unit: PJ/mtkm/mpkm
A5: Region | B5: Fuel | C5: 2018 | D5: 2020 | E5: 2025 | F5: 2030 | G5: 2035 | H5: 2040 | I5: 2045 | J5: 2050
A6: AT | B6: Heat_High_Industrial | C6: 54.695611 | D6: 51.433066 | E6: 47.977354 | F6: 44.103118 | G6: 39.940241 | H6: 35.771695 | I6: 32.024874 | J6: 28.40877
A7: BE | B7: Heat_High_Industrial | C7: 142.61127 | D7: 130.30308 | E7: 117.36923 | F7: 104.81484 | G7: 93.947321 | H7: 84.507816 | I7: 76.010519 | J7: 68.752743
A8: BG | B8: Heat_High_Industrial | C8: 23.31606 | D8: 23.882827 | E8: 24.045981 | F8: 23.665366 | G8: 23.110984 | H8: 22.843441 | I8: 22.404889 | J8: 22.151871
A9: CH | B9: Heat_High_Industrial | C9: 24.718933 | D9: 24.338903 | E9: 24.084575 | F9: 23.89791 | G9: 23.103506 | H9: 22.202266 | I9: 21.458626 | J9: 21.243508
A10: CZ | B10: Heat_High_Industrial | C10: 92.015738 | D10: 84.592409 | E10: 76.570809 | F10: 68.920402 | G10: 61.512515 | H10: 53.47798 | I10: 45.971587 | J10: 39.293853
A11: DE | B11: Heat_High_Industrial | C11: 750.09953 | D11: 715.77325 | E11: 671.4654 | F11: 620.70097 | G11: 565.44756 | H11: 507.59531 | I11: 459.46983 | J11: 420.72265
A12: DK | B12: Heat_High_Industrial | C12: 9.0995284 | D12: 8.8957921 | E12: 8.3889507 | F12: 7.8888852 | G12: 7.4404631 | H12: 7.0114353 | I12: 6.5898455 | J12: 6.313482
A13: EE | B13: Heat_High_Industrial | C13: 1.7581848 | D13: 1.3970122 | E13: 1.1119949 | F13: 0.96186763 | G13: 0.87320869 | H13: 0.81849206 | I13: 0.78104142 | J13: 0.75275521
A14: ES | B14: Heat_High_Industrial | C14: 225.07204 | D14: 220.50176 | E14: 212.88898 | F14: 204.64267 | G14: 195.77165 | H14: 185.7461 | I14: 175.94316 | J14: 168.72296
A15: FI | B15: Heat_High_Industrial | C15: 24.552804 | D15: 23.340318 | E15: 21.676756 | F15: 20.073221 | G15: 18.737237 | H15: 17.733385 | I15: 16.868211 | J15: 16.189695
A16: FR | B16: Heat_High_Industrial | C16: 290.46787 | D16: 270.65085 | E16: 240.73941 | F16: 212.38854 | G16: 188.27764 | H16: 167.66974 | I16: 150.68945 | J16: 136.90289
... A215: UK | B215: Power | C215: 798.4 | D215: 790.416 | E215: 782.51184 | F215: 774.68672 | G215: 766.93985 | H215: 759.27046 | I215: 751.67775 | J215: 744.16097
B218: FRT | C218: =SUM(C126:C155) -> 3113.3203 | D218: =SUM(D126:D155) -> 3206.7199 | E218: =SUM(E126:E155) -> 3302.9215 | F218: =SUM(F126:F155) -> 3402.0091 | G218: =SUM(G126:G155) -> 3504.0694 | H218: =SUM(H126:H155) -> 3609.1915 | I218: =SUM(I126:I155) -> 3717.4672 | J218: =SUM(J126:J155) -> 3828.9913
B219: FRT | C219: 1.06 | D219: 1.03 | E219: 1.03 | F219: 1.03 | G219: 1.03 | H219: 1.03 | I219: 1.03 | J219: 1.03
B220: FRT | C220: =C218*C219 -> 3300.1195 | D220: =C220*D219 -> 3399.1231 | E220: =D220*E219 -> 3501.0968 | F220: =E220*F219 -> 3606.1297 | G220: =F220*G219 -> 3714.3136 | H220: =G220*H219 -> 3825.743 | I220: =H220*I219 -> 3940.5153 | J220: =I220*J219 -> 4058.7307
B223: PSNG | C223: =SUM(C156:C185) -> 6543.6954 | D223: =SUM(D156:D185) -> 6530.6081 | E223: =SUM(E156:E185) -> 6517.5468 | F223: =SUM(F156:F185) -> 6484.9591 | G223: =SUM(G156:G185) -> 6452.5343 | H223: =SUM(H156:H185) -> 6420.2716 | I223: =SUM(I156:I185) -> 6388.1703 | J223: =SUM(J156:J185) -> 6356.2294
B224: PSNG | C224: 1 | D224: 0.998 | E224: 0.998 | F224: 0.995 | G224: 0.995 | H224: 0.995 | I224: 0.995 | J224: 0.995
B225: PSNG | C225: =C223*C224 -> 6543.6954 | D225: =C225*D224 -> 6530.6081 | E225: =D225*E224 -> 6517.5468 | F225: =E225*F224 -> 6484.9591 | G225: =F225*G224 -> 6452.5343 | H225: =G225*H224 -> 6420.2716 | I225: =H225*I224 -> 6388.1703 | J225: =I225*J224 -> 6356.2294

Sheet Par_ReserveMargin
A1: ReserveMargin{r in REGION, y in YEAR}
A2: The reserve (installed) capacity required relative to the peak demand.
A3: Unit: Ratio
A5: Region | B5: 2018 | C5: 2020 | D5: 2025 | E5: 2030 | F5: 2035 | G5: 2040 | H5: 2045 | I5: 2050
A6: AL | B6: 0.1 | C6: 0.105 | D6: 0.11 | E6: 0.115 | F6: 0.11 | G6: 0.1 | H6: 0.085 | I6: 0.07
A7: AT | B7: 0.1 | C7: 0.105 | D7: 0.11 | E7: 0.115 | F7: 0.11 | G7: 0.1 | H7: 0.085 | I7: 0.07
A8: BA | B8: 0.1 | C8: 0.105 | D8: 0.11 | E8: 0.115 | F8: 0.11 | G8: 0.1 | H8: 0.085 | I8: 0.07
A9: BE | B9: 0.1 | C9: 0.105 | D9: 0.11 | E9: 0.115 | F9: 0.11 | G9: 0.1 | H9: 0.085 | I9: 0.07
A10: BG | B10: 0.1 | C10: 0.105 | D10: 0.11 | E10: 0.115 | F10: 0.11 | G10: 0.1 | H10: 0.085 | I10: 0.07
A11: CH | B11: 0.1 | C11: 0.105 | D11: 0.11 | E11: 0.115 | F11: 0.11 | G11: 0.1 | H11: 0.085 | I11: 0.07
A12: CZ | B12: 0.1 | C12: 0.105 | D12: 0.11 | E12: 0.115 | F12: 0.11 | G12: 0.1 | H12: 0.085 | I12: 0.07
A13: DE | B13: 0.1 | C13: 0.105 | D13: 0.11 | E13: 0.115 | F13: 0.11 | G13: 0.1 | H13: 0.085 | I13: 0.07
A14: DK | B14: 0.1 | C14: 0.105 | D14: 0.11 | E14: 0.115 | F14: 0.11 | G14: 0.1 | H14: 0.085 | I14: 0.07
A15: ES | B15: 0.1 | C15: 0.105 | D15: 0.11 | E15: 0.115 | F15: 0.11 | G15: 0.1 | H15: 0.085 | I15: 0.07
A16: FI | B16: 0.1 | C16: 0.105 | D16: 0.11 | E16: 0.115 | F16: 0.11 | G16: 0.1 | H16: 0.085 | I16: 0.07
... A43: NONEU_Balkan | B43: 0.1 | C43: 0.105 | D43: 0.11 | E43: 0.115 | F43: 0.11 | G43: 0.1 | H43: 0.085 | I43: 0.07

Sheet Par_ReserveMarginTagFuel
A1: ReserveMarginTagFuel{r in REGION, f in FUEL, y in YEAR}
A2: Indicates if the output fuel has a reserve margin associated with it
A3: Unit: Binary
A5: Region | B5: Fuel | C5: 2018 | D5: 2020 | E5: 2025 | F5: 2030 | G5: 2035 | H5: 2040 | I5: 2045 | J5: 2050
A6: DE | B6: power | C6: 1 | D6: 1 | E6: 1 | F6: 1 | G6: 1 | H6: 1 | I6: 1 | J6: 1

Sheet Par_ReserveMarginTagTechnology
A1: ReserveMarginTagTechnology{r in REGION, t in TECHNOLOGY, y in YEAR}
A2: Amount the technology contributes to the reserve margin 1=100% 0.2=20%.
A3: Unit: Fraction
A5: Region | B5: Technology | C5: 2018 | D5: 2020 | E5: 2025 | F5: 2030 | G5: 2035 | H5: 2040 | I5: 2045 | J5: 2050
A6: DE | B6: D_Battery_Li-Ion | C6: 1 | D6: 1 | E6: 1 | F6: 1 | G6: 1 | H6: 1 | I6: 1 | J6: 1
A7: DE | B7: D_Battery_Redox | C7: 1 | D7: 1 | E7: 1 | F7: 1 | G7: 1 | H7: 1 | I7: 1 | J7: 1
A8: DE | B8: D_PHS | C8: 1 | D8: 1 | E8: 1 | F8: 1 | G8: 1 | H8: 1 | I8: 1 | J8: 1
A9: DE | B9: D_CAES | C9: 1 | D9: 1 | E9: 1 | F9: 1 | G9: 1 | H9: 1 | I9: 1 | J9: 1
A10: DE | B10: P_Oil | C10: 1 | D10: 1 | E10: 1 | F10: 1 | G10: 1 | H10: 1 | I10: 1 | J10: 1
A11: DE | B11: X_Fuel_Cell | C11: 1 | D11: 1 | E11: 1 | F11: 1 | G11: 1 | H11: 1 | I11: 1 | J11: 1
A12: DE | B12: P_Gas_CCS | C12: 1 | D12: 1 | E12: 1 | F12: 1 | G12: 1 | H12: 1 | I12: 1 | J12: 1
A13: DE | B13: RES_Hydro_Large | C13: 1 | D13: 1 | E13: 1 | F13: 1 | G13: 1 | H13: 1 | I13: 1 | J13: 1
A14: DE | B14: P_H2_OCGT | C14: 1 | D14: 1 | E14: 1 | F14: 1 | G14: 1 | H14: 1 | I14: 1 | J14: 1
A15: DE | B15: P_Gas_CCGT | C15: 1 | D15: 1 | E15: 1 | F15: 1 | G15: 1 | H15: 1 | I15: 1 | J15: 1
A16: DE | B16: P_Gas_Engines | C16: 1 | D16: 1 | E16: 1 | F16: 1 | G16: 1 | H16: 1 | I16: 1 | J16: 1
... A24: DE | B24: CHP_Oil | C24: 1 | D24: 1 | E24: 1 | F24: 1 | G24: 1 | H24: 1 | I24: 1 | J24: 1

Sheet Par_InputActivityRatio
A1: InputActivityRatio{r in REGION, t in TECHNOLOGY, f in FUEL, m in MODEOFOPERATION, y in YEAR}
A2: The input (use) of fuel per unit of activity for each technology. Describes, in combination with the OutputActivityRatio, the efficiency of the technology.
A3: Unit: Fraction
A5: Region | B5: Technology | C5: Fuel | D5: ModeOfOperation | E5: 2018 | F5: 2020 | G5: 2025 | H5: 2030 | I5: 2035 | J5: 2040 | K5: 2045 | L5: 2050
A6: DE | B6: CHP_Biomass_CCS | C6: Biomass | D6: 1 | E6: 3.3333333 | F6: 3.113961 | G6: 3.0391608 | H6: 2.9670209 | I6: 2.897422 | J6: 2.8302521 | K6: 2.7654056 | L6: 2.7027829
A7: DE | B7: CHP_Biomass_Solid | C7: Biomass | D7: 1 | E7: 2.8901734 | F7: 2.8901734 | G7: 2.8901734 | H7: 2.8901734 | I7: 2.8901734 | J7: 2.8901734 | K7: 2.8901734 | L7: 2.8901734 | P7: JRC TIMES | Q7: Power only
A8: DE | B8: CHP_Biomass_Solid | C8: Biomass | D8: 2 | E8: 3.5714286 | F8: 3.5714286 | G8: 3.5714286 | H8: 3.5714286 | I8: 3.5714286 | J8: 3.5714286 | K8: 3.5714286 | L8: 3.5714286 | P8: JRC TIMES | Q8: Power+Heat
A9: DE | B9: CHP_Biomass_Solid_CCS | C9: Biomass | D9: 1 | E9: 3.0346821 | F9: 3.0346821 | G9: 3.0346821 | H9: 3.0346821 | I9: 3.0346821 | J9: 3.0346821 | K9: 3.0346821 | L9: 3.0346821 | P9: JRC TIMES | Q9: Power only | R9: 5% eff loss due to CO2 capture
A10: DE | B10: CHP_Biomass_Solid_CCS | C10: Biomass | D10: 2 | E10: 3.75 | F10: 3.75 | G10: 3.75 | H10: 3.75 | I10: 3.75 | J10: 3.75 | K10: 3.75 | L10: 3.75 | P10: JRC TIMES | Q10: Power+Heat | R10: 5% eff loss due to CO2 capture
A11: DE | B11: CHP_Coal_Hardcoal | C11: Hardcoal | D11: 1 | E11: 2.6525199 | F11: 2.6525199 | G11: 2.6525199 | H11: 2.6525199 | I11: 2.6525199 | J11: 2.6525199 | K11: 2.6525199 | L11: 2.6525199 | P11: JRC TIMES | Q11: Power only
A12: DE | B12: CHP_Coal_Hardcoal | C12: Hardcoal | D12: 2 | E12: 3.5335689 | F12: 3.5335689 | G12: 3.5335689 | H12: 3.5335689 | I12: 3.5335689 | J12: 3.5335689 | K12: 3.5335689 | L12: 3.5335689 | P12: JRC TIMES | Q12: Power+Heat
A13: DE | B13: CHP_Coal_Hardcoal_CCS | C13: Hardcoal | D13: 1 | E13: 2.7851459 | F13: 2.7851459 | G13: 2.7851459 | H13: 2.7851459 | I13: 2.7851459 | J13: 2.7851459 | K13: 2.7851459 | L13: 2.7851459 | P13: JRC TIMES | Q13: Power only | R13: 5% eff loss due to CO2 capture
A14: DE | B14: CHP_Coal_Hardcoal_CCS | C14: Hardcoal | D14: 2 | E14: 3.7102473 | F14: 3.7102473 | G14: 3.7102473 | H14: 3.7102473 | I14: 3.7102473 | J14: 3.7102473 | K14: 3.7102473 | L14: 3.7102473 | P14: JRC TIMES | Q14: Power+Heat | R14: 5% eff loss due to CO2 capture
A15: DE | B15: CHP_Coal_Lignite | C15: Lignite | D15: 1 | E15: 2.8248588 | F15: 2.8248588 | G15: 2.8248588 | H15: 2.8248588 | I15: 2.8248588 | J15: 2.8248588 | K15: 2.8248588 | L15: 2.8248588 | P15: JRC TIMES | Q15: Power only
A16: DE | B16: CHP_Coal_Lignite | C16: Lignite | D16: 2 | E16: 3.7593985 | F16: 3.7593985 | G16: 3.7593985 | H16: 3.7593985 | I16: 3.7593985 | J16: 3.7593985 | K16: 3.7593985 | L16: 3.7593985 | P16: JRC TIMES | Q16: Power+Heat
A17: DE | B17: CHP_Coal_Lignite_CCS | C17: Lignite | D17: 1 | E17: 2.9661017 | F17: 2.9661017 | G17: 2.9661017 | H17: 2.9661017 | I17: 2.9661017 | J17: 2.9661017 | K17: 2.9661017 | L17: 2.9661017 | P17: JRC TIMES | Q17: Power only | R17: 5% eff loss due to CO2 capture
A18: DE | B18: CHP_Coal_Lignite_CCS | C18: Lignite | D18: 2 | E18: 3.9473684 | F18: 3.9473684 | G18: 3.9473684 | H18: 3.9473684 | I18: 3.9473684 | J18: 3.9473684 | K18: 3.9473684 | L18: 3.9473684 | P18: JRC TIMES | Q18: Power+Heat | R18: 5% eff loss due to CO2 capture
A19: DE | B19: CHP_Gas | C19: Gas_Bio | D19: 2 | E19: 1.754386 | F19: 1.6930243 | G19: 1.6603175 | H19: 1.628906 | I19: 1.611537 | J19: 1.5945578 | K19: 1.5779592 | L19: 1.561732
A20: DE | B20: CHP_Gas | C20: Gas_Synth | D20: 3 | E20: 1.754386 | F20: 1.6930243 | G20: 1.6603175 | H20: 1.628906 | I20: 1.611537 | J20: 1.5945578 | K20: 1.5779592 | L20: 1.561732
A21: DE | B21: CHP_Gas_CCGT_Biogas | C21: Gas_Bio | D21: 1 | E21: 1.8484288 | F21: 1.8484288 | G21: 1.8484288 | H21: 1.8484288 | I21: 1.8484288 | J21: 1.8484288 | K21: 1.8484288 | L21: 1.8484288 | P21: JRC TIMES | Q21: Power only
A22: DE | B22: CHP_Gas_CCGT_Biogas | C22: Gas_Bio | D22: 2 | E22: 2.0080321 | F22: 2.0080321 | G22: 2.0080321 | H22: 2.0080321 | I22: 2.0080321 | J22: 2.0080321 | K22: 2.0080321 | L22: 2.0080321 | P22: JRC TIMES | Q22: Power+Heat
A23: DE | B23: CHP_Gas_CCGT_Biogas_CCS | C23: Gas_Bio | D23: 1 | E23: 1.9408503 | F23: 1.9408503 | G23: 1.9408503 | H23: 1.9408503 | I23: 1.9408503 | J23: 1.9408503 | K23: 1.9408503 | L23: 1.9408503 | P23: JRC TIMES | Q23: Power only | R23: 5% eff loss due to CO2 capture
A24: DE | B24: CHP_Gas_CCGT_Biogas_CCS | C24: Gas_Bio | D24: 2 | E24: 2.1084337 | F24: 2.1084337 | G24: 2.1084337 | H24: 2.1084337 | I24: 2.1084337 | J24: 2.1084337 | K24: 2.1084337 | L24: 2.1084337 | P24: JRC TIMES | Q24: Power+Heat | R24: 5% eff loss due to CO2 capture
A25: DE | B25: CHP_Gas_CCGT_Natural | C25: Gas_Natural | D25: 1 | E25: 1.8484288 | F25: 1.8484288 | G25: 1.8484288 | H25: 1.8484288 | I25: 1.8484288 | J25: 1.8484288 | K25: 1.8484288 | L25: 1.8484288 | P25: JRC TIMES | Q25: Power only
A26: DE | B26: CHP_Gas_CCGT_Natural | C26: Gas_Natural | D26: 2 | E26: 2.0080321 | F26: 2.0080321 | G26: 2.0080321 | H26: 2.0080321 | I26: 2.0080321 | J26: 2.0080321 | K26: 2.0080321 | L26: 2.0080321 | P26: JRC TIMES | Q26: Power+Heat
A27: DE | B27: CHP_Gas_CCGT_Natural_CCS | C27: Gas_Natural | D27: 1 | E27: 1.9408503 | F27: 1.9408503 | G27: 1.9408503 | H27: 1.9408503 | I27: 1.9408503 | J27: 1.9408503 | K27: 1.9408503 | L27: 1.9408503 | P27: JRC TIMES | Q27: Power only | R27: 5% eff loss due to CO2 capture
A28: DE | B28: CHP_Gas_CCGT_Natural_CCS | C28: Gas_Natural | D28: 2 | E28: 2.1084337 | F28: 2.1084337 | G28: 2.1084337 | H28: 2.1084337 | I28: 2.1084337 | J28: 2.1084337 | K28: 2.1084337 | L28: 2.1084337 | P28: JRC TIMES | Q28: Power+Heat | R28: 5% eff loss due to CO2 capture
A29: DE | B29: CHP_Gas_CCGT_SynGas | C29: Gas_Synth | D29: 1 | E29: 1.8484288 | F29: 1.8484288 | G29: 1.8484288 | H29: 1.8484288 | I29: 1.8484288 | J29: 1.8484288 | K29: 1.8484288 | L29: 1.8484288 | P29: JRC TIMES | Q29: Power only
A30: DE | B30: CHP_Gas_CCGT_SynGas | C30: Gas_Synth | D30: 2 | E30: 2.0080321 | F30: 2.0080321 | G30: 2.0080321 | H30: 2.0080321 | I30: 2.0080321 | J30: 2.0080321 | K30: 2.0080321 | L30: 2.0080321 | P30: JRC TIMES | Q30: Power+Heat
A31: DE | B31: CHP_Hydrogen_FuelCell | C31: H2 | D31: 2 | E31: 1 | F31: 1 | G31: 1 | H31: 1 | I31: 1 | J31: 1 | K31: 1 | L31: 1 | P31: old data (90% eff, Kevin) | Q31: Power+Heat
A32: DE | B32: CHP_Oil | C32: Oil | D32: 1 | E32: 2.8248588 | F32: 2.8248588 | G32: 2.8248588 | H32: 2.8248588 | I32: 2.8248588 | J32: 2.8248588 | K32: 2.8248588 | L32: 2.8248588 | P32: using lignite values
A33: DE | B33: CHP_Oil | C33: Oil | D33: 2 | E33: 3.7593985 | F33: 3.7593985 | G33: 3.7593985 | H33: 3.7593985 | I33: 3.7593985 | J33: 3.7593985 | K33: 3.7593985 | L33: 3.7593985 | P33: using lignite values
A34: DE | B34: D_Battery_Li-Ion | C34: Power | D34: 1 | E34: 1 | F34: 1 | G34: 1 | H34: 1 | I34: 1 | J34: 1 | K34: 1 | L34: 1
A35: DE | B35: D_Battery_Redox | C35: Power | D35: 1 | E35: 1 | F35: 1 | G35: 1 | H35: 1 | I35: 1 | J35: 1 | K35: 1 | L35: 1
A36: DE | B36: D_CAES | C36: Power | D36: 1 | E36: 1 | F36: 1 | G36: 1 | H36: 1 | I36: 1 | J36: 1 | K36: 1 | L36: 1
A37: DE | B37: D_Gas_H2 | C37: H2 | D37: 1 | E37: 1 | F37: 1 | G37: 1 | H37: 1 | I37: 1 | J37: 1 | K37: 1 | L37: 1
A38: DE | B38: D_Gas_Methane | C38: Gas_Natural | D38: 1 | E38: 1 | F38: 1 | G38: 1 | H38: 1 | I38: 1 | J38: 1 | K38: 1 | L38: 1
A39: DE | B39: D_Heat_HLI | C39: Heat_Low_Industrial | D39: 1 | E39: 1 | F39: 1 | G39: 1 | H39: 1 | I39: 1 | J39: 1 | K39: 1 | L39: 1
A40: DE | B40: D_Heat_HLR | C40: Heat_Low_Residential | D40: 1 | E40: 1 | F40: 1 | G40: 1 | H40: 1 | I40: 1 | J40: 1 | K40: 1 | L40: 1
A41: DE | B41: D_PHS | C41: Power | D41: 1 | E41: 1 | F41: 1 | G41: 1 | H41: 1 | I41: 1 | J41: 1 | K41: 1 | L41: 1
A42: DE | B42: D_PHS_Residual | C42: Power | D42: 1 | E42: 1 | F42: 1 | G42: 1 | H42: 1 | I42: 1 | J42: 1 | K42: 1 | L42: 1
A43: DE | B43: FRT_Rail_Conv | C43: Oil | D43: 1 | E43: 0.31 | F43: 0.3085 | G43: 0.3069 | H43: 0.3054 | I43: 0.3039 | J43: 0.3023 | K43: 0.3008 | L43: 0.2993
A44: DE | B44: FRT_Rail_Conv | C44: Biofuel | D44: 2 | E44: 0.31 | F44: 0.3085 | G44: 0.3069 | H44: 0.3054 | I44: 0.3039 | J44: 0.3023 | K44: 0.3008 | L44: 0.2993
A45: DE | B45: FRT_Rail_Conv | C45: Powerfuel | D45: 3 | E45: 0.31 | F45: 0.3085 | G45: 0.3069 | H45: 0.3054 | I45: 0.3039 | J45: 0.3023 | K45: 0.3008 | L45: 0.2993
... A165: DE | B165: P_Gas | C165: Gas_Synth | D165: 3 | E165: 1.7241379 | F165: 1.6648526 | G165: 1.6332553 | H165: 1.6028966 | I165: 1.5987272 | J165: 1.5945578 | K165: 1.5779592 | L165: 1.561732
A166: DE | B166: P_Gas_CCGT | C166: Gas_Natural | D166: 1 | E166: 1.7241379 | F166: 1.6666667 | G166: 1.6393443 | H166: 1.6129032 | I166: 1.6129032 | J166: 1.6129032 | K166: 1.6 | L166: 1.5873016 | P166: ETRI 2014
A167: DE | B167: P_Gas_CCGT | C167: Gas_Bio | D167: 2 | E167: 1.7241379 | F167: 1.6666667 | G167: 1.6393443 | H167: 1.6129032 | I167: 1.6129032 | J167: 1.6129032 | K167: 1.6 | L167: 1.5873016 | P167: ETRI 2014
A168: DE | B168: P_Gas_CCGT | C168: Gas_Synth | D168: 3 | E168: 1.7241379 | F168: 1.6666667 | G168: 1.6393443 | H168: 1.6129032 | I168: 1.6129032 | J168: 1.6129032 | K168: 1.6 | L168: 1.5873016 | P168: ETRI 2014
A169: DE | B169: P_Gas_CCS | C169: Gas_Natural | D169: 1 | E169: 1.8518519 | F169: 1.8495339 | G169: 1.843739 | H169: 1.8379441 | I169: 1.8321492 | J169: 1.8263542 | K169: 1.8205593 | L169: 1.8147644
A170: DE | B170: P_Gas_CCS | C170: Gas_Bio | D170: 2 | E170: 1.8518519 | F170: 1.8495339 | G170: 1.843739 | H170: 1.8379441 | I170: 1.8321492 | J170: 1.8263542 | K170: 1.8205593 | L170: 1.8147644
A171: DE | B171: P_Gas_CCS | C171: Gas_Synth | D171: 3 | E171: 1.8518519 | F171: 1.8495339 | G171: 1.843739 | H171: 1.8379441 | I171: 1.8321492 | J171: 1.8263542 | K171: 1.8205593 | L171: 1.8147644
A172: DE | B172: P_Gas_Engines | C172: Gas_Natural | D172: 1 | E172: 2.8571429 | F172: 2.7777778 | G172: 2.7027027 | H172: 2.6315789 | I172: 2.5641026 | J172: 2.5641026 | K172: 2.5641026 | L172: 2.5641026
A173: DE | B173: P_Gas_Engines | C173: Gas_Bio | D173: 2 | E173: 2.8571429 | F173: 2.7777778 | G173: 2.7027027 | H173: 2.6315789 | I173: 2.5641026 | J173: 2.5641026 | K173: 2.5641026 | L173: 2.5641026
A174: DE | B174: P_Gas_Engines | C174: Gas_Synth | D174: 3 | E174: 2.8571429 | F174: 2.7777778 | G174: 2.7027027 | H174: 2.6315789 | I174: 2.5641026 | J174: 2.5641026 | K174: 2.5641026 | L174: 2.5641026
A175: DE | B175: P_Gas_OCGT | C175: Gas_Natural | D175: 1 | E175: 2.6315789 | F175: 2.5 | G175: 2.3809524 | H175: 2.2727273 | I175: 2.2222222 | J175: 2.2222222 | K175: 2.2222222 | L175: 2.2222222
A176: DE | B176: P_Gas_OCGT | C176: Gas_Bio | D176: 2 | E176: 2.6315789 | F176: 2.5 | G176: 2.3809524 | H176: 2.2727273 | I176: 2.2222222 | J176: 2.2222222 | K176: 2.2222222 | L176: 2.2222222
A177: DE | B177: P_Gas_OCGT | C177: Gas_Synth | D177: 3 | E177: 2.6315789 | F177: 2.5 | G177: 2.3809524 | H177: 2.2727273 | I177: 2.2222222 | J177: 2.2222222 | K177: 2.2222222 | L177: 2.2222222
A178: DE | B178: P_H2_OCGT | C178: H2 | D178: 1 | E178: 2.6315789 | F178: 2.4857143 | G178: 2.3349206 | H178: 2.2 | I178: 2.1232804 | J178: 2.0941799 | K178: 2.0650794 | L178: 2.0359788
A179: DE | B179: P_Nuclear | C179: Nuclear | D179: 1 | E179: 2.7027027 | F179: 2.6980695 | G179: 2.6507937 | H179: 2.6049409 | I179: 2.4653061 | J179: 2.3396178 | K179: 2.3302235 | L179: 2.3208293
A180: DE | B180: P_Oil | C180: Oil | D180: 1 | E180: 2.6315789 | F180: 2.6271393 | G180: 2.6160401 | H180: 2.6049409 | I180: 2.5938417 | J180: 2.5827426 | K180: 2.5716434 | L180: 2.5605442
... A230: DE | B230: Z_ETS_Sell | C230: ETS_Source | D230: 1 | E230: 1 | F230: 1 | G230: 1 | H230: 1 | I230: 1 | J230: 1 | K230: 1 | L230: 1

Sheet Par_OutputActivityRatio
A1: OutputActivityRatio{r in REGION, t in TECHNOLOGY, f in FUEL, m in MODEOFOPERATION, y in YEAR}
A2: Ratio of output to activity. Desribes, together with the InputActivityRatio, the efficiency of the technology.
A3: Unit: Fraction
A5: Region | B5: Technology | C5: Fuel | D5: ModeOfOperation | E5: 2018 | F5: 2020 | G5: 2025 | H5: 2030 | I5: 2035 | J5: 2040 | K5: 2045 | L5: 2050
A6: DE | B6: A_Rooftop_Commercial | C6: Area_Rooftop_Commercial | D6: 1 | E6: 1 | F6: 1 | G6: 1 | H6: 1 | I6: 1 | J6: 1 | K6: 1 | L6: 1
A7: DE | B7: A_Rooftop_Residential | C7: Area_Rooftop_Residential | D7: 1 | E7: 1 | F7: 1 | G7: 1 | H7: 1 | I7: 1 | J7: 1 | K7: 1 | L7: 1
A8: DE | B8: D_Battery_Li-Ion | C8: Power | D8: 2 | E8: 1 | F8: 1 | G8: 1 | H8: 1 | I8: 1 | J8: 1 | K8: 1 | L8: 1
A9: DE | B9: D_Battery_Redox | C9: Power | D9: 2 | E9: 1 | F9: 1 | G9: 1 | H9: 1 | I9: 1 | J9: 1 | K9: 1 | L9: 1
A10: DE | B10: D_Gas_H2 | C10: H2 | D10: 2 | E10: 1 | F10: 1 | G10: 1 | H10: 1 | I10: 1 | J10: 1 | K10: 1 | L10: 1
A11: DE | B11: D_Gas_Methane | C11: Gas_Natural | D11: 2 | E11: 1 | F11: 1 | G11: 1 | H11: 1 | I11: 1 | J11: 1 | K11: 1 | L11: 1
A12: DE | B12: D_Heat_HLI | C12: Heat_Low_Industrial | D12: 2 | E12: 1 | F12: 1 | G12: 1 | H12: 1 | I12: 1 | J12: 1 | K12: 1 | L12: 1
A13: DE | B13: D_Heat_HLR | C13: Heat_Low_Residential | D13: 2 | E13: 1 | F13: 1 | G13: 1 | H13: 1 | I13: 1 | J13: 1 | K13: 1 | L13: 1
A14: DE | B14: D_PHS | C14: Power | D14: 2 | E14: 1 | F14: 1 | G14: 1 | H14: 1 | I14: 1 | J14: 1 | K14: 1 | L14: 1
A15: DE | B15: D_PHS_Residual | C15: Power | D15: 2 | E15: 1 | F15: 1 | G15: 1 | H15: 1 | I15: 1 | J15: 1 | K15: 1 | L15: 1
A16: DE | B16: D_CAES | C16: Power | D16: 2 | E16: 1 | F16: 1 | G16: 1 | H16: 1 | I16: 1 | J16: 1 | K16: 1 | L16: 1
A17: DE | B17: FRT_Rail_Conv | C17: Mobility_Freight | D17: 1 | E17: 1 | F17: 1 | G17: 1 | H17: 1 | I17: 1 | J17: 1 | K17: 1 | L17: 1
... A238: DE | B238: Z_ETS_Sell | C238: ETS_Source | D238: 2 | E238: 1 | F238: 1 | G238: 1 | H238: 1 | I238: 1 | J238: 1 | K238: 1 | L238: 1
A239: DE | B239: CHP_Biomass_Solid | C239: Power | D239: 1 | E239: 1 | F239: 1 | G239: 1 | H239: 1 | I239: 1 | J239: 1 | K239: 1 | L239: 1 | P239: JRC TIMES | Q239: Power only
A240: DE | B240: CHP_Coal_Hardcoal | C240: Power | D240: 1 | E240: 1 | F240: 1 | G240: 1 | H240: 1 | I240: 1 | J240: 1 | K240: 1 | L240: 1 | P240: JRC TIMES | Q240: Power only
A241: DE | B241: CHP_Coal_Lignite | C241: Power | D241: 1 | E241: 1 | F241: 1 | G241: 1 | H241: 1 | I241: 1 | J241: 1 | K241: 1 | L241: 1 | P241: JRC TIMES | Q241: Power only
A242: DE | B242: CHP_Gas_CCGT_Natural | C242: Power | D242: 1 | E242: 1 | F242: 1 | G242: 1 | H242: 1 | I242: 1 | J242: 1 | K242: 1 | L242: 1 | P242: JRC TIMES | Q242: Power only
A243: DE | B243: CHP_Gas_CCGT_Biogas | C243: Power | D243: 1 | E243: 1 | F243: 1 | G243: 1 | H243: 1 | I243: 1 | J243: 1 | K243: 1 | L243: 1 | P243: JRC TIMES | Q243: Power only
A244: DE | B244: CHP_Gas_CCGT_SynGas | C244: Power | D244: 1 | E244: 1 | F244: 1 | G244: 1 | H244: 1 | I244: 1 | J244: 1 | K244: 1 | L244: 1 | P244: JRC TIMES | Q244: Power only
A245: DE | B245: CHP_Biomass_Solid_CCS | C245: Power | D245: 1 | E245: 1 | F245: 1 | G245: 1 | H245: 1 | I245: 1 | J245: 1 | K245: 1 | L245: 1 | P245: JRC TIMES | Q245: Power only
A246: DE | B246: CHP_Coal_Hardcoal_CCS | C246: Power | D246: 1 | E246: 1 | F246: 1 | G246: 1 | H246: 1 | I246: 1 | J246: 1 | K246: 1 | L246: 1 | P246: JRC TIMES | Q246: Power only
A247: DE | B247: CHP_Coal_Lignite_CCS | C247: Power | D247: 1 | E247: 1 | F247: 1 | G247: 1 | H247: 1 | I247: 1 | J247: 1 | K247: 1 | L247: 1 | P247: JRC TIMES | Q247: Power only
A248: DE | B248: CHP_Gas_CCGT_Natural_CCS | C248: Power | D248: 1 | E248: 1 | F248: 1 | G248: 1 | H248: 1 | I248: 1 | J248: 1 | K248: 1 | L248: 1 | P248: JRC TIMES | Q248: Power only
A249: DE | B249: CHP_Gas_CCGT_Biogas_CCS | C249: Power | D249: 1 | E249: 1 | F249: 1 | G249: 1 | H249: 1 | I249: 1 | J249: 1 | K249: 1 | L249: 1 | P249: JRC TIMES | Q249: Power only
A250: DE | B250: CHP_Biomass_Solid | C250: Power | D250: 2 | E250: 1 | F250: 1 | G250: 1 | H250: 1 | I250: 1 | J250: 1 | K250: 1 | L250: 1 | P250: JRC TIMES | Q250: Power+Heat
... A261: DE | B261: CHP_Hydrogen_FuelCell | C261: Power | D261: 2 | E261: 0.5 | F261: 0.5 | G261: 0.5 | H261: 0.5 | I261: 0.5 | J261: 0.5 | K261: 0.5 | L261: 0.5 | P261: old data (90% eff, Kevin) | Q261: Power+Heat
A262: DE | B262: CHP_Biomass_Solid | C262: Heat_District | D262: 2 | E262: 2.568 | F262: 2.568 | G262: 2.568 | H262: 2.568 | I262: 2.568 | J262: 2.568 | K262: 2.568 | L262: 2.568 | P262: JRC TIMES | Q262: Power+Heat | R262: 2.568 | S262: normalized to power with additional efficiencies
A263: DE | B263: CHP_Coal_Hardcoal | C263: Heat_District | D263: 2 | E263: 1.531 | F263: 1.531 | G263: 1.531 | H263: 1.531 | I263: 1.531 | J263: 1.531 | K263: 1.531 | L263: 1.531 | P263: JRC TIMES | Q263: Power+Heat | R263: 1.531 | S263: normalized to power with additional efficiencies
A264: DE | B264: CHP_Coal_Lignite | C264: Heat_District | D264: 2 | E264: 1.651 | F264: 1.651 | G264: 1.651 | H264: 1.651 | I264: 1.651 | J264: 1.651 | K264: 1.651 | L264: 1.651 | P264: JRC TIMES | Q264: Power+Heat | R264: 1.651 | S264: normalized to power with additional efficiencies
A265: DE | B265: CHP_Gas_CCGT_Natural | C265: Heat_District | D265: 2 | E265: 1.006 | F265: 1.006 | G265: 1.006 | H265: 1.006 | I265: 1.006 | J265: 1.006 | K265: 1.006 | L265: 1.006 | P265: JRC TIMES | Q265: Power+Heat | R265: 1.006 | S265: normalized to power with additional efficiencies
A266: DE | B266: CHP_Gas_CCGT_Biogas | C266: Heat_District | D266: 2 | E266: 1.006 | F266: 1.006 | G266: 1.006 | H266: 1.006 | I266: 1.006 | J266: 1.006 | K266: 1.006 | L266: 1.006 | P266: JRC TIMES | Q266: Power+Heat | R266: 1.006 | S266: normalized to power with additional efficiencies
A267: DE | B267: CHP_Gas_CCGT_SynGas | C267: Heat_District | D267: 2 | E267: 1.006 | F267: 1.006 | G267: 1.006 | H267: 1.006 | I267: 1.006 | J267: 1.006 | K267: 1.006 | L267: 1.006 | P267: JRC TIMES | Q267: Power+Heat | R267: 1.006 | S267: normalized to power with additional efficiencies
A268: DE | B268: CHP_Biomass_Solid_CCS | C268: Heat_District | D268: 2 | E268: 2.568 | F268: 2.568 | G268: 2.568 | H268: 2.568 | I268: 2.568 | J268: 2.568 | K268: 2.568 | L268: 2.568 | P268: JRC TIMES | Q268: Power+Heat | R268: 2.568 | S268: normalized to power with additional efficiencies
A269: DE | B269: CHP_Coal_Hardcoal_CCS | C269: Heat_District | D269: 2 | E269: 1.832 | F269: 1.832 | G269: 1.832 | H269: 1.832 | I269: 1.832 | J269: 1.832 | K269: 1.832 | L269: 1.832 | P269: JRC TIMES | Q269: Power+Heat | R269: 1.832 | S269: normalized to power with additional efficiencies
A270: DE | B270: CHP_Coal_Lignite_CCS | C270: Heat_District | D270: 2 | E270: 1.006 | F270: 1.006 | G270: 1.006 | H270: 1.006 | I270: 1.006 | J270: 1.006 | K270: 1.006 | L270: 1.006 | P270: JRC TIMES | Q270: Power+Heat | R270: 1.006 | S270: normalized to power with additional efficiencies
A271: DE | B271: CHP_Gas_CCGT_Natural_CCS | C271: Heat_District | D271: 2 | E271: 1.006 | F271: 1.006 | G271: 1.006 | H271: 1.006 | I271: 1.006 | J271: 1.006 | K271: 1.006 | L271: 1.006 | P271: JRC TIMES | Q271: Power+Heat | R271: 1.006 | S271: normalized to power with additional efficiencies
A272: DE | B272: CHP_Gas_CCGT_Biogas_CCS | C272: Heat_District | D272: 2 | E272: 1.006 | F272: 1.006 | G272: 1.006 | H272: 1.006 | I272: 1.006 | J272: 1.006 | K272: 1.006 | L272: 1.006 | P272: JRC TIMES | Q272: Power+Heat | R272: 1.006 | S272: normalized to power with additional efficiencies
A273: DE | B273: CHP_Hydrogen_FuelCell | C273: Heat_District | D273: 2 | E273: 0.4 | F273: 0.4 | G273: 0.4 | H273: 0.4 | I273: 0.4 | J273: 0.4 | K273: 0.4 | L273: 0.4 | P273: old data (90% eff, Kevin) | Q273: Power+Heat
A274: DE | B274: HLI_Convert_DH | C274: Heat_Low_Industrial | D274: 1 | E274: 1 | F274: 1 | G274: 1 | H274: 1 | I274: 1 | J274: 1 | K274: 1 | L274: 1
A275: DE | B275: HLR_Convert_DH | C275: Heat_Low_Residential | D275: 1 | E275: 1 | F275: 1 | G275: 1 | H275: 1 | I275: 1 | J275: 1 | K275: 1 | L275: 1
A276: DE | B276: CHP_Oil | C276: Power | D276: 1 | E276: 1 | F276: 1 | G276: 1 | H276: 1 | I276: 1 | J276: 1 | K276: 1 | L276: 1 | P276: using lignite values
A277: DE | B277: CHP_Oil | C277: Power | D277: 2 | E277: 1 | F277: 1 | G277: 1 | H277: 1 | I277: 1 | J277: 1 | K277: 1 | L277: 1 | P277: using lignite values
A278: DE | B278: CHP_Oil | C278: Heat_District | D278: 2 | E278: 1.651 | F278: 1.651 | G278: 1.651 | H278: 1.651 | I278: 1.651 | J278: 1.651 | K278: 1.651 | L278: 1.651 | P278: using lignite values
A279: DE | B279: Res_PV_Utility_Tracking | C279: Power | D279: 1 | E279: 1 | F279: 1 | G279: 1 | H279: 1 | I279: 1 | J279: 1 | K279: 1 | L279: 1
A280: DE | B280: P_Gas_CCGT | C280: Power | D280: 1 | E280: 1 | F280: 1 | G280: 1 | H280: 1 | I280: 1 | J280: 1 | K280: 1 | L280: 1
A281: DE | B281: P_Gas_OCGT | C281: Power | D281: 1 | E281: 1 | F281: 1 | G281: 1 | H281: 1 | I281: 1 | J281: 1 | K281: 1 | L281: 1
A282: DE | B282: P_Gas_Engines | C282: Power | D282: 1 | E282: 1 | F282: 1 | G282: 1 | H282: 1 | I282: 1 | J282: 1 | K282: 1 | L282: 1
A283: DE | B283: P_Gas_CCGT | C283: Power | D283: 2 | E283: 1 | F283: 1 | G283: 1 | H283: 1 | I283: 1 | J283: 1 | K283: 1 | L283: 1
A284: DE | B284: P_Gas_OCGT | C284: Power | D284: 2 | E284: 1 | F284: 1 | G284: 1 | H284: 1 | I284: 1 | J284: 1 | K284: 1 | L284: 1
A285: DE | B285: P_Gas_Engines | C285: Power | D285: 2 | E285: 1 | F285: 1 | G285: 1 | H285: 1 | I285: 1 | J285: 1 | K285: 1 | L285: 1
A286: DE | B286: P_Gas_CCGT | C286: Power | D286: 3 | E286: 1 | F286: 1 | G286: 1 | H286: 1 | I286: 1 | J286: 1 | K286: 1 | L286: 1
A287: DE | B287: P_Gas_OCGT | C287: Power | D287: 3 | E287: 1 | F287: 1 | G287: 1 | H287: 1 | I287: 1 | J287: 1 | K287: 1 | L287: 1
A288: DE | B288: P_Gas_Engines | C288: Power | D288: 3 | E288: 1 | F288: 1 | G288: 1 | H288: 1 | I288: 1 | J288: 1 | K288: 1 | L288: 1

Sheet Par_CapitalCost
A1: CapitalCost{r in REGION, t in TECHNOLOGY, y in YEAR}
A2: Total capital cost (including interest paid during construction)per unit of capacity for new capacity additions
A3: Unit: M€/GW
A5: Region | B5: Technology | C5: 2018 | D5: 2020 | E5: 2025 | F5: 2030 | G5: 2035 | H5: 2040 | I5: 2045 | J5: 2050
A6: DE | B6: X_Powerfuel | C6: 947 | D6: 947 | E6: 947 | F6: 947 | G6: 947 | H6: 852.3 | I6: 852.3 | J6: 852.3 | N6: JRC-TIMES+DEA | O6: 10% on PP, PP prices from JRC TIMES
A7: DE | B7: RES_Grass | C7: 0.01 | D7: 0.01 | E7: 0.01 | F7: 0.01 | G7: 0.01 | H7: 0.01 | I7: 0.01 | J7: 0.01 | N7: JRC-TIMES+DEA | O7: 10% on PP, PP prices from JRC TIMES
A8: DE | B8: RES_Wood | C8: 0.01 | D8: 0.01 | E8: 0.01 | F8: 0.01 | G8: 0.01 | H8: 0.01 | I8: 0.01 | J8: 0.01 | N8: JRC-TIMES+DEA | O8: 10% on PP, PP prices from JRC TIMES
A9: DE | B9: RES_Residues | C9: 0.01 | D9: 0.01 | E9: 0.01 | F9: 0.01 | G9: 0.01 | H9: 0.01 | I9: 0.01 | J9: 0.01 | N9: JRC-TIMES+DEA | O9: 10% on PP, PP prices from JRC TIMES
A10: DE | B10: RES_Paper_Cardboard | C10: 0.01 | D10: 0.01 | E10: 0.01 | F10: 0.01 | G10: 0.01 | H10: 0.01 | I10: 0.01 | J10: 0.01 | N10: JRC-TIMES+DEA | O10: 10% on PP, PP prices from JRC TIMES
A11: DE | B11: RES_Roundwood | C11: 0.01 | D11: 0.01 | E11: 0.01 | F11: 0.01 | G11: 0.01 | H11: 0.01 | I11: 0.01 | J11: 0.01 | N11: JRC-TIMES+DEA | O11: 10% on PP, PP prices from JRC TIMES
A12: DE | B12: RES_Biogas | C12: 771 | D12: 731 | E12: 706 | F12: 680 | G12: 653 | H12: 632 | I12: 609 | J12: 589 | N12: own assumption | O12: 50% higher than normal PP
A13: DE | B13: X_Gasifier | C13: 1 | D13: 1 | E13: 1 | F13: 1 | G13: 1 | H13: 1 | I13: 1 | J13: 1 | N13: own assumption | O13: 50% higher than normal PP
A14: DE | B14: X_Liquifier | C14: 1 | D14: 1 | E14: 1 | F14: 1 | G14: 1 | H14: 1 | I14: 1 | J14: 1 | N14: own assumption | O14: 50% higher than normal PP
A15: DE | B15: FRT_Road_LNG | C15: 6.122449 | D15: 6.3240317 | E15: 6.5206164 | F15: 6.7122032 | G15: 6.8987922 | H15: 7.0803832 | I15: 7.2569763 | J15: 7.4285714 | N15: own assumption | O15: 50% higher than normal PP
A16: DE | B16: FRT_Ship_LNG | C16: 10.303618 | D16: 10.466105 | E16: 10.605653 | F16: 10.722262 | G16: 10.815931 | H16: 10.886661 | I16: 10.934451 | J16: 10.959302 | N16: own assumption | O16: 50% higher than normal PP
A17: DE | B17: PSNG_Road_LNG | C17: 48 | D17: 45.888268 | E17: 43.433889 | F17: 40.636863 | G17: 37.49719 | H17: 34.014869 | I17: 30.189901 | J17: 26.022286 | N17: own assumption | O17: old data (90% eff, Kevin) | P17: Power+Heat
A18: DE | B18: P_H2_OCGT | C18: 516 | D18: 516 | E18: 473 | F18: 473 | G18: 451.5 | H18: 451.5 | I18: 451.5 | J18: 451.5 | N18: marginal costs
A19: DE | B19: X_DAC_LT | C19: 730 | D19: 730 | E19: 534 | F19: 338 | G19: 287.5 | H19: 237 | I19: 218 | J19: 199 | N19: marginal costs
A20: DE | B20: X_DAC_HT | C20: 815 | D20: 815 | E20: 596.5 | F20: 378 | G20: 321.5 | H20: 265 | I20: 243.5 | J20: 222 | N20: Mapping and analyses of the current and future (2020 - 2030) heating/cooling fuel deployment (fossil/renewables), EUROPEAN COMMISSION DIRECTORATE-GENERAL FOR ENERGY, 2012
A21: DE | B21: CHP_Biomass_Solid | C21: 2200 | D21: 2090 | E21: 1980 | F21: 1925 | G21: 1870 | H21: 1870 | I21: 1870 | J21: 1870 | N21: JRC-TIMES+DEA | O21: 10% on PP, PP prices from JRC TIMES
A22: DE | B22: CHP_Coal_Hardcoal | C22: 2750 | D22: 2750 | E22: 2750 | F22: 2750 | G22: 2750 | H22: 2750 | I22: 2750 | J22: 2750 | N22: JRC-TIMES+DEA | O22: 10% on PP, PP prices from JRC TIMES
A23: DE | B23: CHP_Coal_Lignite | C23: 2200 | D23: 2200 | E23: 2200 | F23: 2200 | G23: 2200 | H23: 2200 | I23: 2200 | J23: 2200 | N23: JRC-TIMES+DEA | O23: 10% on PP, PP prices from JRC TIMES
A24: DE | B24: CHP_Gas_CCGT_Natural | C24: 935 | D24: 858 | E24: 847 | F24: 836 | G24: 825 | H24: 814 | I24: 814 | J24: 814 | N24: JRC-TIMES+DEA | O24: 10% on PP, PP prices from JRC TIMES
A25: DE | B25: CHP_Gas_CCGT_Biogas | C25: 935 | D25: 858 | E25: 847 | F25: 836 | G25: 825 | H25: 814 | I25: 814 | J25: 814 | N25: JRC-TIMES+DEA | O25: 10% on PP, PP prices from JRC TIMES
A26: DE | B26: CHP_Gas_CCGT_SynGas | C26: 935 | D26: 858 | E26: 847 | F26: 836 | G26: 825 | H26: 814 | I26: 814 | J26: 814 | N26: JRC-TIMES+DEA | O26: 10% on PP, PP prices from JRC TIMES
A27: DE | B27: CHP_Biomass_Solid_CCS | C27: 6342.105 | D27: 6342.105 | E27: 6342.105 | F27: 6342.105 | G27: 6342.105 | H27: 6342.105 | I27: 6342.105 | J27: 6342.105 | N27: own assumption | O27: 50% higher than normal PP
A28: DE | B28: CHP_Coal_Hardcoal_CCS | C28: 4125 | D28: 4125 | E28: 4125 | F28: 4125 | G28: 4125 | H28: 4125 | I28: 4125 | J28: 4125 | N28: own assumption | O28: 50% higher than normal PP
A29: DE | B29: CHP_Coal_Lignite_CCS | C29: 3300 | D29: 3300 | E29: 3300 | F29: 3300 | G29: 3300 | H29: 3300 | I29: 3300 | J29: 3300 | N29: own assumption | O29: 50% higher than normal PP
A30: DE | B30: CHP_Gas_CCGT_Natural_CCS | C30: 1402.5 | D30: 1287 | E30: 1270.5 | F30: 1254 | G30: 1237.5 | H30: 1221 | I30: 1221 | J30: 1221 | N30: own assumption | O30: 50% higher than normal PP
A31: DE | B31: CHP_Gas_CCGT_Biogas_CCS | C31: 1402.5 | D31: 1287 | E31: 1270.5 | F31: 1254 | G31: 1237.5 | H31: 1221 | I31: 1221 | J31: 1221 | N31: own assumption | O31: 50% higher than normal PP
A32: DE | B32: CHP_Hydrogen_FuelCell | C32: 1100 | D32: 1081.25 | E32: 1034.375 | F32: 987.5 | G32: 940.625 | H32: 893.75 | I32: 846.875 | J32: 800 | N32: own assumption | O32: old data (90% eff, Kevin) | P32: Power+Heat
A33: DE | B33: HLI_Convert_DH | C33: 1 | D33: 1 | E33: 1 | F33: 1 | G33: 1 | H33: 1 | I33: 1 | J33: 1 | N33: marginal costs
A34: DE | B34: HLR_Convert_DH | C34: 1 | D34: 1 | E34: 1 | F34: 1 | G34: 1 | H34: 1 | I34: 1 | J34: 1 | N34: marginal costs
A35: DE | B35: CHP_Oil | C35: 930 | D35: 930 | E35: 930 | F35: 930 | G35: 930 | H35: 930 | I35: 930 | J35: 930 | N35: Mapping and analyses of the current and future (2020 - 2030) heating/cooling fuel deployment (fossil/renewables), EUROPEAN COMMISSION DIRECTORATE-GENERAL FOR ENERGY, 2012
A36: DE | B36: Res_PV_Utility_Tracking | C36: 1200 | D36: 612 | E36: 444 | F36: 360 | G36: 312 | H36: 276 | I36: 252 | J36: 228
A37: DE | B37: P_Gas_CCGT | C37: 700 | D37: 642.35294 | E37: 634.11765 | F37: 625.88235 | G37: 617.64706 | H37: 609.41176 | I37: 609.41176 | J37: 609.41176 | N37: EWI
A38: DE | B38: P_Gas_OCGT | C38: 400 | D38: 381.39535 | E38: 372.09302 | F38: 372.09302 | G38: 372.09302 | H38: 372.09302 | I38: 372.09302 | J38: 372.09302 | N38: EWI
A39: DE | B39: P_Gas_Engines | C39: 620 | D39: 590 | E39: 580 | F39: 570 | G39: 560 | H39: 560 | I39: 560 | J39: 560 | N39: EWI

Sheet Par_VariableCost
A1: VariableCost{r in REGION, t in TECHNOLOGY, m in MODEOFOPERATION, y in YEAR}
A2: Cost per unit of activity of the technology.
A3: Unit: M€/PJ
A5: Region | B5: Technology | C5: ModeOfOperation | D5: 2018 | E5: 2020 | F5: 2025 | G5: 2030 | H5: 2035 | I5: 2040 | J5: 2045 | K5: 2050
A6: DE | B6: FRT_Rail_Conv | C6: 1 | D6: 0 | E6: 0 | F6: 0 | G6: 0 | H6: 0 | I6: 0 | J6: 0 | K6: 0
A7: DE | B7: FRT_Rail_Electric | C7: 1 | D7: 0 | E7: 0 | F7: 0 | G7: 0 | H7: 0 | I7: 0 | J7: 0 | K7: 0
A8: DE | B8: FRT_Road_BEV | C8: 1 | D8: 0 | E8: 0 | F8: 0 | G8: 0 | H8: 0 | I8: 0 | J8: 0 | K8: 0
A9: DE | B9: FRT_Road_H2 | C9: 1 | D9: 0 | E9: 0 | F9: 0 | G9: 0 | H9: 0 | I9: 0 | J9: 0 | K9: 0
A10: DE | B10: FRT_Road_ICE | C10: 1 | D10: 0 | E10: 0 | F10: 0 | G10: 0 | H10: 0 | I10: 0 | J10: 0 | K10: 0
A11: DE | B11: FRT_Road_PHEV | C11: 1 | D11: 0 | E11: 0 | F11: 0 | G11: 0 | H11: 0 | I11: 0 | J11: 0 | K11: 0
A12: DE | B12: FRT_Ship_Bio | C12: 1 | D12: 0 | E12: 0 | F12: 0 | G12: 0 | H12: 0 | I12: 0 | J12: 0 | K12: 0
A13: DE | B13: FRT_Ship_Conv | C13: 1 | D13: 0 | E13: 0 | F13: 0 | G13: 0 | H13: 0 | I13: 0 | J13: 0 | K13: 0
A14: DE | B14: FRT_Ship_H2 | C14: 1 | D14: 0 | E14: 0 | F14: 0 | G14: 0 | H14: 0 | I14: 0 | J14: 0 | K14: 0
A15: DE | B15: P_Coal_Hardcoal | C15: 1 | D15: 0 | E15: 0 | F15: 0 | G15: 0 | H15: 0 | I15: 0 | J15: 0 | K15: 0
A16: DE | B16: P_Coal_Lignite | C16: 1 | D16: 0 | E16: 0 | F16: 0 | G16: 0 | H16: 0 | I16: 0 | J16: 0 | K16: 0
A17: DE | B17: P_Gas | C17: 1 | D17: 0 | E17: 0 | F17: 0 | G17: 0 | H17: 0 | I17: 0 | J17: 0 | K17: 0
... A103: DE | B103: Z_Import_H2 | C103: 1 | D103: 99 | E103: 48.75 | F103: 33.25 | G103: 26.825 | H103: 20.7 | I103: 14.875 | J103: 14.45 | K103: 14.025
A104: DE | B104: HLI_Convert_DH | C104: 1 | D104: 0.001 | E104: 0.001 | F104: 0.001 | G104: 0.001 | H104: 0.001 | I104: 0.001 | J104: 0.001 | K104: 0.001 | O104: assumption | P104: 1.4733517
A105: DE | B105: HLR_Convert_DH | C105: 1 | D105: 0.001 | E105: 0.001 | F105: 0.001 | G105: 0.001 | H105: 0.001 | I105: 0.001 | J105: 0.001 | K105: 0.001

Sheet Par_FixedCost
A1: FixedCost{r in REGION, t in TECHNOLOGY, y in YEAR}
A2: The annual cost per unit of capacity of a technology.
A3: Unit: M€/GW
A5: Region | B5: Technology | C5: 2018 | D5: 2020 | E5: 2025 | F5: 2030 | G5: 2035 | H5: 2040 | I5: 2045 | J5: 2050
A6: DE | B6: X_Powerfuel | C6: =[5]Par_CapitalCost!C6*0.03 -> 28.41 | D6: =[5]Par_CapitalCost!D6*0.03 -> 28.41 | E6: =[5]Par_CapitalCost!E6*0.03 -> 28.41 | F6: =[5]Par_CapitalCost!F6*0.03 -> 28.41 | G6: =[5]Par_CapitalCost!G6*0.03 -> 28.41 | H6: =[5]Par_CapitalCost!H6*0.03 -> 25.569 | I6: =[5]Par_CapitalCost!I6*0.03 -> 25.569 | J6: =[5]Par_CapitalCost!J6*0.03 -> 25.569
A7: DE | B7: RES_Grass | C7: 0.01 | D7: 0.01 | E7: 0.01 | F7: 0.01 | G7: 0.01 | H7: 0.01 | I7: 0.01 | J7: 0.01
A8: DE | B8: RES_Wood | C8: 0.01 | D8: 0.01 | E8: 0.01 | F8: 0.01 | G8: 0.01 | H8: 0.01 | I8: 0.01 | J8: 0.01
A9: DE | B9: RES_Residues | C9: 0.01 | D9: 0.01 | E9: 0.01 | F9: 0.01 | G9: 0.01 | H9: 0.01 | I9: 0.01 | J9: 0.01
A10: DE | B10: RES_Paper_Cardboard | C10: 0.01 | D10: 0.01 | E10: 0.01 | F10: 0.01 | G10: 0.01 | H10: 0.01 | I10: 0.01 | J10: 0.01
A11: DE | B11: RES_Roundwood | C11: 0.01 | D11: 0.01 | E11: 0.01 | F11: 0.01 | G11: 0.01 | H11: 0.01 | I11: 0.01 | J11: 0.01
A12: DE | B12: RES_Biogas | C12: =[5]Par_CapitalCost!C12*0.03 -> 23.13 | D12: =[5]Par_CapitalCost!D12*0.03 -> 21.93 | E12: =[5]Par_CapitalCost!E12*0.03 -> 21.18 | F12: =[5]Par_CapitalCost!F12*0.03 -> 20.4 | G12: =[5]Par_CapitalCost!G12*0.03 -> 19.59 | H12: =[5]Par_CapitalCost!H12*0.03 -> 18.96 | I12: =[5]Par_CapitalCost!I12*0.03 -> 18.27 | J12: =[5]Par_CapitalCost!J12*0.03 -> 17.67
A13: DE | B13: X_Gasifier | C13: 1 | D13: 0.95714286 | E13: 0.91428571 | F13: 0.87142857 | G13: 0.82857143 | H13: 0.78571429 | I13: 0.74285714 | J13: 0.7
A14: DE | B14: X_Liquifier | C14: 1 | D14: 0.95714286 | E14: 0.91428571 | F14: 0.87142857 | G14: 0.82857143 | H14: 0.78571429 | I14: 0.74285714 | J14: 0.7
A15: DE | B15: FRT_Road_LNG | C15: 6.122449 | D15: 6.0641399 | E15: 6.0058309 | F15: 5.9475219 | G15: 5.8892128 | H15: 5.8309038 | I15: 5.7725948 | J15: 5.7142857
A16: DE | B16: FRT_Ship_LNG | C16: 10.303618 | D16: 10.035991 | E16: 9.7683647 | F16: 9.5007383 | G16: 9.2331118 | H16: 8.9654854 | I16: 8.697859 | J16: 8.4302326
A17: DE | B17: PSNG_Road_LNG | C17: 48 | D17: 44.002449 | E17: 40.004898 | F17: 36.007347 | G17: 32.009796 | H17: 28.012245 | I17: 24.014694 | J17: 20.017143
A18: DE | B18: P_H2_OCGT | C18: 15.48 | D18: 14.706 | E18: 12.771 | F18: 12.0615 | G18: 10.836 | H18: 10.15875 | I18: 9.4815 | J18: 8.80425
A19: DE | B19: X_DAC_LT | C19: 21.9 | D19: 21.274286 | E19: 15.104571 | F19: 9.2708571 | G19: 7.6392857 | H19: 6.0942857 | I19: 5.4188571 | J19: 4.776
A20: DE | B20: X_DAC_HT | C20: 24.45 | D20: 23.751429 | E20: 16.872429 | F20: 10.368 | G20: 8.5427143 | H20: 6.8142857 | I20: 6.0527143 | J20: 5.328
A21: DE | B21: P_Gas_CCGT | C21: 26 | D21: 26 | E21: 17 | F21: 17 | G21: 17 | H21: 17 | I21: 17 | J21: 17
A22: DE | B22: P_Gas_OCGT | C22: 12 | D22: 12 | E22: 8 | F22: 8 | G22: 8 | H22: 8 | I22: 8 | J22: 8
A23: DE | B23: P_Gas_Engines | C23: 13 | D23: 13 | E23: 9 | F23: 9 | G23: 9 | H23: 9 | I23: 9 | J23: 9
A24: DE | B24: CHP_Biomass_Solid | C24: 50.6 | D24: 48.07 | E24: 45.54 | F24: 44.275 | G24: 43.01 | H24: 43.01 | I24: 43.01 | J24: 43.01
... A29: DE | B29: CHP_Gas_CCGT_SynGas | C29: 28.6 | D29: 28.6 | E29: 18.7 | F29: 18.7 | G29: 18.7 | H29: 18.7 | I29: 18.7 | J29: 18.7
A30: DE | B30: CHP_Biomass_Solid_CCS | C30: 55 | D30: 45.1 | E30: 42.9 | F30: 41.8 | G30: 40.7 | H30: 40.7 | I30: 40.7 | J30: 40.7 | N30: JRC-TIMES+DEA
A31: DE | B31: CHP_Coal_Hardcoal_CCS | C31: 66 | D31: 66 | E31: 66 | F31: 66 | G31: 66 | H31: 66 | I31: 66 | J31: 66 | N31: JRC-TIMES+DEA
A32: DE | B32: CHP_Coal_Lignite_CCS | C32: 62.7 | D32: 62.7 | E32: 62.7 | F32: 62.7 | G32: 62.7 | H32: 62.7 | I32: 62.7 | J32: 62.7 | N32: JRC-TIMES+DEA
A33: DE | B33: CHP_Gas_CCGT_Natural_CCS | C33: 42.9 | D33: 42.9 | E33: 28.05 | F33: 28.05 | G33: 28.05 | H33: 28.05 | I33: 28.05 | J33: 28.05 | N33: JRC-TIMES+DEA
A34: DE | B34: CHP_Gas_CCGT_Biogas_CCS | C34: 42.9 | D34: 42.9 | E34: 28.05 | F34: 28.05 | G34: 28.05 | H34: 28.05 | I34: 28.05 | J34: 28.05 | N34: JRC-TIMES+DEA
A35: DE | B35: CHP_Hydrogen_FuelCell | C35: 22 | D35: 21.142857 | E35: 20.285714 | F35: 19.428571 | G35: 18.571429 | H35: 17.714286 | I35: 16.857143 | J35: 16 | N35: JRC-TIMES+DEA
A36: DE | B36: HLI_Convert_DH | C36: 1 | D36: 1 | E36: 1 | F36: 1 | G36: 1 | H36: 1 | I36: 1 | J36: 1 | N36: own assumption
A37: DE | B37: HLR_Convert_DH | C37: 1 | D37: 1 | E37: 1 | F37: 1 | G37: 1 | H37: 1 | I37: 1 | J37: 1 | N37: own assumption
A38: DE | B38: CHP_Oil | C38: 32.55 | D38: 32.55 | E38: 32.55 | F38: 32.55 | G38: 32.55 | H38: 32.55 | I38: 32.55 | J38: 32.55 | N38: annahme 3,5% capex nach
A39: DE | B39: Res_PV_Utility_Tracking | C39: 18 | D39: 16.8 | E39: 13.2 | F39: 12 | G39: 10.8 | H39: 10.8 | I39: 9.6 | J39: 8.88

Sheet Par_ResidualCapacity
A1: ResidualCapacity{r in REGION, t in TECHNOLOGY, y in YEAR}
A2: The capacity left over from periods prior to the modeling period.
A3: Unit: GW
C5: 2018 | D5: 2020 | E5: 2025 | F5: 2030 | G5: 2035 | H5: 2040 | I5: 2045 | J5: 2050
A6: AL | B6: D_PHS_Residual | C6: 1.66 | D6: 1.66 | E6: 1.66 | F6: 1.66 | G6: 1.66 | H6: 1.66 | I6: 1.66 | J6: 1.66
A7: AL | B7: P_Biomass | C7: 0 | D7: 0 | E7: 0 | F7: 0 | G7: 0 | H7: 0 | I7: 0 | J7: 0
A8: AL | B8: P_Coal_Hardcoal | C8: 0 | D8: 0 | E8: 0 | F8: 0 | G8: 0 | H8: 0 | I8: 0 | J8: 0
A9: AL | B9: P_Coal_Lignite | C9: 0 | D9: 0 | E9: 0 | F9: 0 | G9: 0 | H9: 0 | I9: 0 | J9: 0
A10: AL | B10: P_Nuclear | C10: 0 | D10: 0 | E10: 0 | F10: 0 | G10: 0 | H10: 0 | I10: 0 | J10: 0
A11: AL | B11: P_Oil | C11: 0 | D11: 0 | E11: 0 | F11: 0 | G11: 0 | H11: 0 | I11: 0 | J11: 0
A12: AL | B12: RES_PV_Utility_Avg | C12: 0 | D12: 0 | E12: 0 | F12: 0 | G12: 0 | H12: 0 | I12: 0 | J12: 0
A13: AL | B13: RES_Wind_Offshore_Transitional | C13: 0 | D13: 0 | E13: 0 | F13: 0 | G13: 0 | H13: 0 | I13: 0 | J13: 0
A14: AL | B14: RES_Wind_Onshore_Avg | C14: 0 | D14: 0 | E14: 0 | F14: 0 | G14: 0 | H14: 0 | I14: 0 | J14: 0
A15: AT | B15: CHP_Biomass_Solid | C15: 1.1694115 | D15: 1.1694115 | E15: 0.58470574 | F15: 0 | G15: 0 | H15: 0 | I15: 0 | J15: 0
A16: AT | B16: CHP_Coal_Hardcoal | C16: 0.21784897 | D16: 0.21784897 | E16: 0.10892448 | F16: 0 | G16: 0 | H16: 0 | I16: 0 | J16: 0
A17: AT | B17: CHP_Gas_CCGT_Natural | C17: 2.1007818 | D17: 1.1007818 | E17: 0.99310258 | F17: 0.88542332 | G17: 0.74884787 | H17: 0.61227241 | I17: 0.3061362 | J17: 0
... A27: AT | B27: HLI_Oil_Boiler | C27: 0.2818 | D27: 0.2537 | E27: 0.1967 | F27: 0.1181 | G27: 0.0591 | H27: 0.0237 | I27: 0.0048 | J27: 0
A28: AT | B28: HLR_Biomass | C28: 2.0737 | D28: 1.8664 | E28: 1.4465 | F28: 0.8679 | G28: 0.434 | H28: 0.1736 | I28: 0.0348
A29: AT | B29: HLR_Direct_Electric | C29: 0.5925 | D29: 0.5333 | E29: 0.4134 | F29: 0.2481 | G29: 0.1241 | H29: 0.0497 | I29: 0.01
A30: AT | B30: HLR_Gas_Boiler | C30: 21.8238 | D30: 19.6415 | E30: 15.2222 | F30: 9.1334 | G30: 4.5667 | H30: 1.8267 | I30: 0.3654
A31: AT | B31: HLR_Gas_CHP | C31: 2 | D31: 2 | E31: 2 | F31: 1 | G31: 1 | H31: 1 | I31: 1 | J31: 0.014918853
A32: AT | B32: HLR_Hardcoal | C32: 0.0194 | D32: 0.0175 | E32: 0.0136 | F32: 0.0082 | G32: 0.0041 | H32: 0.0017 | I32: 0.0004
A33: AT | B33: HLR_Oil_Boiler | C33: 1.4987 | D33: 1.3489 | E33: 1.0454 | F33: 0.6273 | G33: 0.3137 | H33: 0.1255 | I33: 0.0251
A34: AT | B34: HMI_Biomass | C34: 0.9128 | D34: 0.8216 | E34: 0.6368 | F34: 0.3821 | G34: 0.1911 | H34: 0.0765 | I34: 0.0153 | J34: 0
A35: AT | B35: HMI_Gas | C35: 17.0363 | D35: 15.3327 | E35: 11.8829 | F35: 7.1298 | G35: 3.5649 | H35: 1.426 | I35: 0.2852 | J35: 0
A36: AT | B36: HMI_HardCoal | C36: 0.1309 | D36: 0.1179 | E36: 0.0914 | F36: 0.0549 | G36: 0.0275 | H36: 0.011 | I36: 0.0022 | J36: 0
A37: AT | B37: HMI_Oil | C37: 0.1732 | D37: 0.1559 | E37: 0.1209 | F37: 0.0726 | G37: 0.0363 | H37: 0.0146 | I37: 0.003 | J37: 0
A38: AT | B38: HMI_Steam_Electric | C38: 0.0111 | D38: 0.01 | E38: 0.0078 | F38: 0.0047 | G38: 0.0024 | H38: 0.001 | I38: 0 | J38: 0
A39: AT | B39: P_Biomass | C39: 1.758 | D39: 1.654 | E39: 0.69 | F39: 0.536 | G39: 0.389 | H39: 0.373 | I39: 0.353 | J39: 0.333
A40: AT | B40: P_Coal_Hardcoal | C40: 0.8144648 | D40: 0.0664648 | E40: 0.0114648 | F40: 0.0114648 | G40: 0.0114648 | H40: 0.0114648 | I40: 0.0114648 | J40: 0.0114648
A41: AT | B41: P_Coal_Lignite | C41: 0 | D41: 0 | E41: 0 | F41: 0 | G41: 0 | H41: 0 | I41: 0 | J41: 0
A42: AT | B42: P_Gas | C42: 5.119113 | D42: 4.2212714 | E42: 4.1472795 | F42: 4.0314461 | G42: 3.5300892 | H42: 3.0329596 | I42: 1.8676808 | J42: 0.014918853
A43: AT | B43: P_Gas_CCGT | C43: 3.28991 | D43: 3.28991 | E43: 1.9580182 | F43: 0.62612644 | G43: 0.62612644 | H43: 0.62612644 | I43: 0.31306322 | J43: 0
A44: AT | B44: P_Gas_Engines | C44: 0.256 | D44: 0.256 | E44: 0.244 | F44: 0.232 | G44: 0.189 | H44: 0.146 | I44: 0.073 | J44: 0
A45: AT | B45: P_Gas_OCGT | C45: 0.491532 | D45: 0.491532 | E45: 0.45490992 | F45: 0.41828784 | G45: 0.32553844 | H45: 0.23278905 | I45: 0.11639452 | J45: 0
... A75: BE | B75: HLI_Oil_Boiler | C75: 0.1387 | D75: 0.1249 | E75: 0.0968 | F75: 0.0581 | G75: 0.0291 | H75: 0.0117 | I75: 0.0024 | J75: 0
A76: BE | B76: HLR_Biomass | C76: 0.7245 | D76: 0.6521 | E76: 0.5054 | F76: 0.3033 | G76: 0.1517 | H76: 0.0607 | I76: 0.0122
A77: BE | B77: HLR_Direct_Electric | C77: 0.793 | D77: 0.7137 | E77: 0.5532 | F77: 0.332 | G77: 0.166 | H77: 0.0664 | I77: 0.0133
A78: BE | B78: HLR_Gas_Boiler | C78: 31.2782 | D78: 28.1504 | E78: 21.8166 | F78: 13.09 | G78: 6.545 | H78: 2.618 | I78: 0.5236
A79: BE | B79: HLR_Hardcoal | C79: 0.128 | D79: 0.1152 | E79: 0.0893 | F79: 0.0536 | G79: 0.0268 | H79: 0.0108 | I79: 0.0022
A80: BE | B80: HLR_Oil_Boiler | C80: 4.8631 | D80: 4.3768 | E80: 3.3921 | F80: 2.0353 | G80: 1.0177 | H80: 0.4071 | I80: 0.0815
A81: BE | B81: HMI_Biomass | C81: 0.1314 | D81: 0.1183 | E81: 0.0917 | F81: 0.0551 | G81: 0.0276 | H81: 0.0111 | I81: 0.0023 | J81: 0
A82: BE | B82: HMI_Gas | C82: 37.6829 | D82: 33.9147 | E82: 26.2839 | F82: 15.7704 | G82: 7.8852 | H82: 3.1541 | I82: 0.6309 | J82: 0
A83: BE | B83: HMI_HardCoal | C83: 0.0752 | D83: 0.0677 | E83: 0.0525 | F83: 0.0315 | G83: 0.0158 | H83: 0.0064 | I83: 0.0013 | J83: 0
A84: BE | B84: HMI_Oil | C84: 6.263 | D84: 5.6367 | E84: 4.3685 | F84: 2.6211 | G84: 1.3106 | H84: 0.5243 | I84: 0.1049 | J84: 0
A85: BE | B85: HMI_Steam_Electric | C85: 0.0676 | D85: 0.0609 | E85: 0.0472 | F85: 0.0284 | G85: 0.0142 | H85: 0.0057 | I85: 0.0012 | J85: 0
A86: BE | B86: P_Biomass | C86: 1.178 | D86: 0.24743737 | E86: 0.24743737 | F86: 0.22670671 | G86: 0.22645568 | H86: 0.21821848 | I86: 0.18019716 | J86: 0.06375486
A87: BE | B87: P_Coal_Hardcoal | C87: 2.09 | D87: 1.5675 | E87: 1.175625 | F87: 0.88171875 | G87: 0.66128906 | H87: 0.4959668 | I87: 0 | J87: 0
A88: BE | B88: P_Coal_Lignite | C88: 0 | D88: 0 | E88: 0 | F88: 0 | G88: 0 | H88: 0 | I88: 0 | J88: 0
A89: BE | B89: P_Gas | C89: 5.439 | D89: 5.0497404 | E89: 4.98173 | F89: 4.8547189 | G89: 4.0228005 | H89: 2.4462577 | I89: 1.740593 | J89: 0.82546208
A90: BE | B90: P_Gas_CCGT | C90: 2.4423 | D90: 2.4423 | E90: 2.260334 | F90: 2.078368 | G90: 1.6175194 | H90: 1.1566707 | I90: 0.57833537 | J90: 0
A91: BE | B91: P_Gas_OCGT | C91: 2.1403 | D91: 2.1403 | E91: 1.5664514 | F91: 0.9926029 | G91: 0.49630145 | H91: 0 | I91: 0 | J91: 0
A92: BE | B92: P_Nuclear | C92: 5.06 | D92: 5.06 | E92: 3.5000691 | F92: 3.5000691 | G92: 0 | H92: 0 | I92: 0 | J92: 0
... A113: BG | B113: HLI_Oil_Boiler | C113: 0.043 | D113: 0.0387 | E113: 0.03 | F113: 0.018 | G113: 0.009 | H113: 0.0036 | I113: 0.0008 | J113: 0
A114: BG | B114: HLR_Biomass | C114: 0.9866 | D114: 0.888 | E114: 0.6882 | F114: 0.413 | G114: 0.2065 | H114: 0.0826 | I114: 0.0166
A115: BG | B115: HLR_Direct_Electric | C115: 0.4434 | D115: 0.3991 | E115: 0.3094 | F115: 0.1857 | G115: 0.0929 | H115: 0.0372 | I115: 0.0075
A116: BG | B116: HLR_Gas_Boiler | C116: 7.1873 | D116: 6.4686 | E116: 5.0132 | F116: 3.008 | G116: 1.504 | H116: 0.6016 | I116: 0.1204
A117: BG | B117: HLR_Hardcoal | C117: 0.1589 | D117: 0.1431 | E117: 0.111 | F117: 0.0666 | G117: 0.0333 | H117: 0.0134 | I117: 0.0027
A118: BG | B118: HLR_Oil_Boiler | C118: 0.0452 | D118: 0.0407 | E118: 0.0316 | F118: 0.019 | G118: 0.0095 | H118: 0.0038 | I118: 0.0008
A119: BG | B119: HMI_Biomass | C119: 0.1205 | D119: 0.1085 | E119: 0.0841 | F119: 0.0505 | G119: 0.0253 | H119: 0.0102 | I119: 0.0021 | J119: 0
A120: BG | B120: HMI_Gas | C120: 9.4671 | D120: 8.5204 | E120: 6.6034 | F120: 3.9621 | G120: 1.9811 | H120: 0.7925 | I120: 0.1585 | J120: 0
A121: BG | B121: HMI_HardCoal | C121: 0.7286 | D121: 0.6558 | E121: 0.5083 | F121: 0.305 | G121: 0.1525 | H121: 0.061 | I121: 0.0122 | J121: 0
A122: BG | B122: HMI_Oil | C122: 0.0389 | D122: 0.0351 | E122: 0.0273 | F122: 0.0164 | G122: 0.0082 | H122: 0.0033 | I122: 0.0007 | J122: 0
A123: BG | B123: HMI_Steam_Electric | C123: 0.0109 | D123: 0.0099 | E123: 0.0077 | F123: 0.0047 | G123: 0.0024 | H123: 0.001 | I123: 0 | J123: 0
A124: BG | B124: P_Biomass | C124: 0.28165 | D124: 0.051171499 | E124: 0.051171499 | F124: 0.051171499 | G124: 0.051171499 | H124: 0.051171499 | I124: 0.051171499 | J124: 0.045096752
A125: BG | B125: P_Coal_Hardcoal | C125: 0.71 | D125: 0.35333557 | E125: 0.22255861 | F125: 0.22255861 | G125: 0.079892833 | H125: 0.079892833 | I125: 0.079892833 | J125: 0.079892833
A126: BG | B126: P_Coal_Lignite | C126: 4.2 | D126: 1.6467474 | E126: 1.6467474 | F126: 1.1807867 | G126: 0.95310136 | H126: 0.70953101 | I126: 0.70953101 | J126: 0.70953101
A127: BG | B127: P_Gas | C127: 0.99 | D127: 0.51256845 | E127: 0.41758009 | F127: 0.40412515 | G127: 0.37802945 | H127: 0.37802945 | I127: 0.31009754 | J127: 0.1193119
A128: BG | B128: P_Gas_CCGT | C128: 0.102 | D128: 0.102 | E128: 0.094400389 | F128: 0.086800777 | G128: 0.067553936 | H128: 0.048307094 | I128: 0.024153547 | J128: 0
A129: BG | B129: P_Gas_OCGT | C129: 0 | D129: 0 | E129: 0 | F129: 0 | G129: 0 | H129: 0 | I129: 0 | J129: 0
A130: BG | B130: P_Nuclear | C130: 2.2 | D130: 2.2 | E130: 2.2 | F130: 2.2 | G130: 2.2 | H130: 1.1 | I130: 0 | J130: 0
... A146: CH | B146: HLI_Oil_Boiler | C146: 0.0972 | D146: 0.0875 | E146: 0.0679 | F146: 0.0408 | G146: 0.0204 | H146: 0.0082 | I146: 0.0017 | J146: 0
A147: CH | B147: HLR_Biomass | C147: 0.9688 | D147: 0.872 | E147: 0.6758 | F147: 0.4055 | G147: 0.2028 | H147: 0.0812 | I147: 0.0163
A148: CH | B148: HLR_Gas_Boiler | C148: 23.4589 | D148: 21.1131 | E148: 16.3627 | F148: 9.8177 | G148: 4.9089 | H148: 1.9636 | I148: 0.3928
A149: CH | B149: HLR_Oil_Boiler | C149: 3.6431 | D149: 3.2788 | E149: 2.5411 | F149: 1.5247 | G149: 0.7624 | H149: 0.305 | I149: 0.061
A150: CH | B150: HMI_Biomass | C150: 0.2211 | D150: 0.199 | E150: 0.1543 | F150: 0.0926 | G150: 0.0463 | H150: 0.0186 | I150: 0.0038 | J150: 0
A151: CH | B151: HMI_Gas | C151: 3.2398 | D151: 2.9159 | E151: 2.2599 | F151: 1.356 | G151: 0.678 | H151: 0.2712 | I151: 0.0543 | J151: 0
A152: CH | B152: HMI_HardCoal | C152: 0.0006 | D152: 0 | E152: 0 | F152: 0 | G152: 0 | H152: 0 | I152: 0 | J152: 0
A153: CH | B153: HMI_Oil | C153: 0.0845 | D153: 0.0761 | E153: 0.059 | F153: 0.0354 | G153: 0.0177 | H153: 0.0071 | I153: 0.0015 | J153: 0
A154: CH | B154: HMI_Steam_Electric | C154: 0.0268 | D154: 0.0242 | E154: 0.0188 | F154: 0.0113 | G154: 0.0057 | H154: 0.0023 | I154: 0.0005 | J154: 0
A155: CH | B155: P_Biomass | C155: 0.39 | D155: 0.26646023 | E155: 0.26592544 | F155: 0.25790355 | G155: 0.24633867 | H155: 0.24304524 | I155: 0.2136495 | J155: 0.08373955
A156: CH | B156: P_Coal_Hardcoal | C156: 0 | D156: 0 | E156: 0 | F156: 0 | G156: 0 | H156: 0 | I156: 0 | J156: 0
A157: CH | B157: P_Coal_Lignite | C157: 0 | D157: 0 | E157: 0 | F157: 0 | G157: 0 | H157: 0 | I157: 0 | J157: 0
A158: CH | B158: P_Gas | C158: 0.35 | D158: 0.2625 | E158: 0.196875 | F158: 0.14765625 | G158: 0.11074219 | H158: 0 | I158: 0 | J158: 0
A159: CH | B159: P_Gas_CCGT | C159: 0.132 | D159: 0.132 | E159: 0.0875 | F159: 0.043 | G159: 0.043 | H159: 0.043 | I159: 0.0215 | J159: 0
A160: CH | B160: P_Nuclear | C160: 3.278 | D160: 2.9257863 | E160: 2.2146041 | F160: 1.2303356 | G160: 0 | H160: 0 | I160: 0 | J160: 0
A161: CH | B161: P_Oil | C161: 0.66 | D161: 0.64888701 | E161: 0.64888701 | F161: 0.009968464 | G161: 0.007691716 | H161: 0 | I161: 0 | J161: 0
... A182: CZ | B182: HLI_Oil_Boiler | C182: 0.0465 | D182: 0.0419 | E182: 0.0325 | F182: 0.0195 | G182: 0.0098 | H182: 0.004 | I182: 0.0008 | J182: 0
A183: CZ | B183: HLR_Biomass | C183: 2.4485 | D183: 2.2037 | E183: 1.7079 | F183: 1.0248 | G183: 0.5124 | H183: 0.205 | I183: 0.041
A184: CZ | B184: HLR_Direct_Electric | C184: 0.6378 | D184: 0.5741 | E184: 0.445 | F184: 0.267 | G184: 0.1335 | H184: 0.0534 | I184: 0.0107
A185: CZ | B185: HLR_Gas_Boiler | C185: 23.6952 | D185: 21.3257 | E185: 16.5275 | F185: 9.9165 | G185: 4.9583 | H185: 1.9834 | I185: 0.3967
A186: CZ | B186: HLR_Hardcoal | C186: 1.0371 | D186: 0.9334 | E186: 0.7234 | F186: 0.4341 | G186: 0.2171 | H186: 0.0869 | I186: 0.0174
A187: CZ | B187: HLR_Oil_Boiler | C187: 0.0729 | D187: 0.0657 | E187: 0.051 | F187: 0.0306 | G187: 0.0153 | H187: 0.0062 | I187: 0.0013
A188: CZ | B188: HMI_Biomass | C188: 0.0701 | D188: 0.0631 | E188: 0.049 | F188: 0.0294 | G188: 0.0147 | H188: 0.0059 | I188: 0.0012 | J188: 0
A189: CZ | B189: HMI_Gas | C189: 16.462 | D189: 14.8158 | E189: 11.4823 | F189: 6.8894 | G189: 3.4447 | H189: 1.3779 | I189: 0.2756 | J189: 0
A190: CZ | B190: HMI_HardCoal | C190: 1.7621 | D190: 1.5859 | E190: 1.2291 | F190: 0.7375 | G190: 0.3688 | H190: 0.1476 | I190: 0.0296 | J190: 0
A191: CZ | B191: HMI_Oil | C191: 0.0929 | D191: 0.0837 | E191: 0.0649 | F191: 0.039 | G191: 0.0195 | H191: 0.0078 | I191: 0.0016 | J191: 0
A192: CZ | B192: HMI_Steam_Electric | C192: 0.0156 | D192: 0.0141 | E192: 0.011 | F192: 0.0066 | G192: 0.0033 | H192: 0.0014 | I192: 0.0003 | J192: 0
A193: CZ | B193: P_Biomass | C193: 0.83 | D193: 0.46482309 | E193: 0.46482309 | F193: 0.46223539 | G193: 0.43960965 | H193: 0.43740679 | I193: 0.37664903 | J193: 0.24536661
A194: CZ | B194: P_Coal_Hardcoal | C194: 1.27 | D194: 0.93602731 | E194: 0.7107886 | F194: 0.4855499 | G194: 0.44711854 | H194: 0.44711854 | I194: 0.44464936 | J194: 0.018019097
...

Sheet Par_AvailabilityFactor
A1: AvailabilityFactor{r in REGION, t in TECHNOLOGY, y in YEAR}
A2: Maximum time a technology may run for the whole year. Often used to simulate planned outages. GENeSYS-MOD will choose when to run or not run.
A3: Unit: Fraction
A5: Region | B5: Technology | C5: 2018 | D5: 2020 | E5: 2025 | F5: 2030 | G5: 2035 | H5: 2040 | I5: 2045 | J5: 2050
A6: DE | B6: A_Rooftop_Commercial | C6: 1 | D6: 1 | E6: 1 | F6: 1 | G6: 1 | H6: 1 | I6: 1 | J6: 1
A7: DE | B7: A_Rooftop_Residential | C7: 1 | D7: 1 | E7: 1 | F7: 1 | G7: 1 | H7: 1 | I7: 1 | J7: 1
A8: DE | B8: D_Battery_Li-Ion | C8: 1 | D8: 1 | E8: 1 | F8: 1 | G8: 1 | H8: 1 | I8: 1 | J8: 1
A9: DE | B9: D_Battery_Redox | C9: 1 | D9: 1 | E9: 1 | F9: 1 | G9: 1 | H9: 1 | I9: 1 | J9: 1
A10: DE | B10: D_Gas_H2 | C10: 1 | D10: 1 | E10: 1 | F10: 1 | G10: 1 | H10: 1 | I10: 1 | J10: 1
A11: DE | B11: D_Gas_Methane | C11: 1 | D11: 1 | E11: 1 | F11: 1 | G11: 1 | H11: 1 | I11: 1 | J11: 1
A12: DE | B12: D_Heat_HLI | C12: 1 | D12: 1 | E12: 1 | F12: 1 | G12: 1 | H12: 1 | I12: 1 | J12: 1
A13: DE | B13: D_Heat_HLR | C13: 1 | D13: 1 | E13: 1 | F13: 1 | G13: 1 | H13: 1 | I13: 1 | J13: 1
A14: DE | B14: D_PHS | C14: 1 | D14: 1 | E14: 1 | F14: 1 | G14: 1 | H14: 1 | I14: 1 | J14: 1
A15: DE | B15: D_PHS_Residual | C15: 1 | D15: 1 | E15: 1 | F15: 1 | G15: 1 | H15: 1 | I15: 1 | J15: 1
A16: DE | B16: D_CAES | C16: 1 | D16: 1 | E16: 1 | F16: 1 | G16: 1 | H16: 1 | I16: 1 | J16: 1
... A156: PL | B156: RES_Hydro_Large | C156: 0.6 | D156: 0.33 | E156: 0.33 | F156: 0.33 | G156: 0.33 | H156: 0.33 | I156: 0.33 | J156: 0.33
A157: DE | B157: P_Gas_CCGT | C157: 0.87 | D157: 0.87 | E157: 0.87 | F157: 0.87 | G157: 0.87 | H157: 0.87 | I157: 0.87 | J157: 0.87 | N157: ETRI 2014
A158: DE | B158: P_Gas_OCGT | C158: 0.87 | D158: 0.87 | E158: 0.87 | F158: 0.87 | G158: 0.87 | H158: 0.87 | I158: 0.87 | J158: 0.87
A159: DE | B159: P_Gas_Engines | C159: 0.87 | D159: 0.87 | E159: 0.87 | F159: 0.87 | G159: 0.87 | H159: 0.87 | I159: 0.87 | J159: 0.87
A160: DE | B160: CHP_Biomass_Solid | C160: 0.9 | D160: 0.9 | E160: 0.9 | F160: 0.9 | G160: 0.9 | H160: 0.9 | I160: 0.9 | J160: 0.9 | N160: JRC-TIMES
A161: DE | B161: CHP_Coal_Hardcoal | C161: 0.9 | D161: 0.9 | E161: 0.9 | F161: 0.9 | G161: 0.9 | H161: 0.9 | I161: 0.9 | J161: 0.9 | N161: JRC-TIMES
A162: DE | B162: CHP_Coal_Lignite | C162: 0.9 | D162: 0.9 | E162: 0.9 | F162: 0.9 | G162: 0.9 | H162: 0.9 | I162: 0.9 | J162: 0.9 | N162: JRC-TIMES
A163: DE | B163: CHP_Gas_CCGT_Natural | C163: 0.9 | D163: 0.9 | E163: 0.9 | F163: 0.9 | G163: 0.9 | H163: 0.9 | I163: 0.9 | J163: 0.9 | N163: JRC-TIMES
A164: DE | B164: CHP_Gas_CCGT_Biogas | C164: 0.9 | D164: 0.9 | E164: 0.9 | F164: 0.9 | G164: 0.9 | H164: 0.9 | I164: 0.9 | J164: 0.9 | N164: JRC-TIMES
A165: DE | B165: CHP_Gas_CCGT_SynGas | C165: 0.9 | D165: 0.9 | E165: 0.9 | F165: 0.9 | G165: 0.9 | H165: 0.9 | I165: 0.9 | J165: 0.9 | N165: JRC-TIMES
A166: DE | B166: CHP_Biomass_Solid_CCS | C166: 0.9 | D166: 0.9 | E166: 0.9 | F166: 0.9 | G166: 0.9 | H166: 0.9 | I166: 0.9 | J166: 0.9 | N166: JRC-TIMES
A167: DE | B167: CHP_Coal_Hardcoal_CCS | C167: 0.9 | D167: 0.9 | E167: 0.9 | F167: 0.9 | G167: 0.9 | H167: 0.9 | I167: 0.9 | J167: 0.9 | N167: JRC-TIMES
A168: DE | B168: CHP_Coal_Lignite_CCS | C168: 0.9 | D168: 0.9 | E168: 0.9 | F168: 0.9 | G168: 0.9 | H168: 0.9 | I168: 0.9 | J168: 0.9 | N168: JRC-TIMES
A169: DE | B169: CHP_Gas_CCGT_Natural_CCS | C169: 0.9 | D169: 0.9 | E169: 0.9 | F169: 0.9 | G169: 0.9 | H169: 0.9 | I169: 0.9 | J169: 0.9 | N169: JRC-TIMES
A170: DE | B170: CHP_Gas_CCGT_Biogas_CCS | C170: 0.9 | D170: 0.9 | E170: 0.9 | F170: 0.9 | G170: 0.9 | H170: 0.9 | I170: 0.9 | J170: 0.9 | N170: JRC-TIMES
A171: DE | B171: CHP_Hydrogen_FuelCell | C171: 0 | D171: 0 | E171: 0 | F171: 0.98 | G171: 0.98 | H171: 0.98 | I171: 0.98 | J171: 0.98
A172: DE | B172: HLI_Convert_DH | C172: 1 | D172: 1 | E172: 1 | F172: 1 | G172: 1 | H172: 1 | I172: 1 | J172: 1
A173: DE | B173: HLR_Convert_DH | C173: 1 | D173: 1 | E173: 1 | F173: 1 | G173: 1 | H173: 1 | I173: 1 | J173: 1
A174: DE | B174: CHP_Oil | C174: 0.9 | D174: 0.9 | E174: 0.9 | F174: 0.9 | G174: 0.9 | H174: 0.9 | I174: 0.9 | J174: 0.9 | N174: same as other CHPs
A175: DE | B175: Res_PV_Utility_Tracking | C175: 0.98 | D175: 0.98 | E175: 0.98 | F175: 0.98 | G175: 0.98 | H175: 0.98 | I175: 0.98 | J175: 0.98
A176: AT | B176: RES_Hydro_Large | C176: 0.28400304 | D176: 0.28400304 | E176: 0.28400304 | F176: 0.28400304 | G176: 0.28400304 | H176: 0.28400304 | I176: 0.28400304 | J176: 0.28400304
A177: BE | B177: RES_Hydro_Large | C177: 0.096724517 | D177: 0.096724517 | E177: 0.096724517 | F177: 0.096724517 | G177: 0.096724517 | H177: 0.096724517 | I177: 0.096724517 | J177: 0.096724517
A178: BG | B178: RES_Hydro_Large | C178: 0.13402415 | D178: 0.13402415 | E178: 0.13402415 | F178: 0.13402415 | G178: 0.13402415 | H178: 0.13402415 | I178: 0.13402415 | J178: 0.13402415
A179: CH | B179: RES_Hydro_Large | C179: 0.29348601 | D179: 0.29348601 | E179: 0.29348601 | F179: 0.29348601 | G179: 0.29348601 | H179: 0.29348601 | I179: 0.29348601 | J179: 0.29348601
A180: CZ | B180: RES_Hydro_Large | C180: 0.12749469 | D180: 0.12749469 | E180: 0.12749469 | F180: 0.12749469 | G180: 0.12749469 | H180: 0.12749469 | I180: 0.12749469 | J180: 0.12749469
A181: DE | B181: RES_Hydro_Large | C181: 0.4172823 | D181: 0.4172823 | E181: 0.4172823 | F181: 0.4172823 | G181: 0.4172823 | H181: 0.4172823 | I181: 0.4172823 | J181: 0.4172823
A182: DK | B182: RES_Hydro_Large | C182: 0 | D182: 0 | E182: 0 | F182: 0 | G182: 0 | H182: 0 | I182: 0 | J182: 0
A183: EE | B183: RES_Hydro_Large | C183: 0 | D183: 0 | E183: 0 | F183: 0 | G183: 0 | H183: 0 | I183: 0 | J183: 0
A184: ES | B184: RES_Hydro_Large | C184: 0.51265552 | D184: 0.45265552 | E184: 0.41265552 | F184: 0.41265552 | G184: 0.41265552 | H184: 0.41265552 | I184: 0.41265552 | J184: 0.41265552
A185: FI | B185: RES_Hydro_Large | C185: 0 | D185: 0 | E185: 0 | F185: 0 | G185: 0 | H185: 0 | I185: 0 | J185: 0
A186: FR | B186: RES_Hydro_Large | C186: 0.47514537 | D186: 0.47514537 | E186: 0.47514537 | F186: 0.47514537 | G186: 0.47514537 | H186: 0.47514537 | I186: 0.47514537 | J186: 0.47514537
... A206: PT | B206: RES_Hydro_Small | C206: 0.88 | D206: 0.88 | E206: 0.88 | F206: 0.88 | G206: 0.88 | H206: 0.88 | I206: 0.88 | J206: 0.88

Sheet Par_CapacityFactor
A1: CapacityFactor{r in REGION, t in TECHNOLOGY, l in TIMESLICE, y in YEAR}
A2: Indicates the maximum time technology may run in a given time slice.
A3: Unit: Fraction
A5: Region | B5: Technology | C5: Timeslice | D5: 2018 | E5: 2020 | F5: 2025 | G5: 2030 | H5: 2035 | I5: 2040 | J5: 2045 | K5: 2050
N998: same as Fuel_Cell
N999: same as Fuel_Cell
N1000: same as Fuel_Cell
N1001: same as Fuel_Cell
N1002: same as Fuel_Cell
N1003: same as Fuel_Cell
N1004: same as Fuel_Cell
N1005: same as Fuel_Cell
N1006: same as Fuel_Cell
N1007: same as Fuel_Cell
N1008: same as Fuel_Cell
N1009: same as Fuel_Cell
... N1045: same as Fuel_Cell
O7286: avg
O7302: avg
O7318: avg
O7337: avg
O7382: opt = süden
O7383: inf norden
O7398: norden = opt
O7399: süden = inf
O19126: avg
O19145: avg

Sheet Par_OperationalLife
A1: OperationalLife{r in REGION, t in TECHNOLOGY}
A2: Operational lifespan of a process in years.
A3: Unit: Years
A5: DE | B5: A_Rooftop_Commercial | C5: 101
A6: DE | B6: A_Rooftop_Residential | C6: 101
A7: DE | B7: D_Battery_Li-Ion | C7: 11
A8: DE | B8: D_Battery_Redox | C8: 20
A9: DE | B9: D_Gas_H2 | C9: 40
A10: DE | B10: D_Gas_Methane | C10: 40
A11: DE | B11: D_Heat_HLI | C11: 30
A12: DE | B12: D_Heat_HLR | C12: 30
A13: DE | B13: D_PHS | C13: 40
A14: DE | B14: D_PHS_Residual | C14: 40
A15: DE | B15: D_CAES | C15: 30
A16: DE | B16: FRT_Rail_Conv | C16: 26
... A152: DE | B152: P_Gas_Engines | C152: 31
A153: DE | B153: CHP_Biomass_Solid | C153: 31 | E153: JRC-TIMES | F153: *+1 year
A154: DE | B154: CHP_Coal_Hardcoal | C154: 31 | E154: JRC-TIMES | F154: *+1 year
A155: DE | B155: CHP_Coal_Lignite | C155: 31 | E155: JRC-TIMES | F155: *+1 year
A156: DE | B156: CHP_Gas_CCGT_Natural | C156: 26 | E156: JRC-TIMES | F156: *+1 year
A157: DE | B157: CHP_Gas_CCGT_Biogas | C157: 26 | E157: JRC-TIMES | F157: *+1 year
A158: DE | B158: CHP_Gas_CCGT_SynGas | C158: 26 | E158: JRC-TIMES | F158: *+1 year
A159: DE | B159: CHP_Biomass_Solid_CCS | C159: 31 | E159: JRC-TIMES | F159: *+1 year
A160: DE | B160: CHP_Coal_Hardcoal_CCS | C160: 31 | E160: JRC-TIMES | F160: *+1 year
A161: DE | B161: CHP_Coal_Lignite_CCS | C161: 31 | E161: JRC-TIMES | F161: *+1 year
A162: DE | B162: CHP_Gas_CCGT_Natural_CCS | C162: 26 | E162: JRC-TIMES | F162: *+1 year
A163: DE | B163: CHP_Gas_CCGT_Biogas_CCS | C163: 26 | E163: JRC-TIMES | F163: *+1 year
A164: DE | B164: CHP_Hydrogen_FuelCell | C164: 31 | E164: old data
A165: DE | B165: HLI_Convert_DH | C165: 100
A166: DE | B166: HLR_Convert_DH | C166: 100
A167: DE | B167: CHP_Oil | C167: 31 | E167: same as other chps
A168: DE | B168: Res_PV_Utility_Tracking | C168: 25

Sheet Par_TotalAnnualMinActivity
A1: TotalAnnualMinActivity{r in REGION, t in TECHNOLOGY, y in YEAR}
A2: Minimum total activity each year.
A3: Unit: PJ
A5: Region | B5: Technology | C5: 2018 | D5: 2020 | E5: 2025 | F5: 2030 | G5: 2035 | H5: 2040 | I5: 2045 | J5: 2050

Sheet Par_TotalAnnualMaxActivity
A1: TotalAnnualMaxActivity{r in REGION, t in TECHNOLOGY, y in YEAR}
A2: Maximum total activity each year.
A3: Unit: PJ
A5: Region | B5: Technology | C5: 2018 | D5: 2020 | E5: 2025 | F5: 2030 | G5: 2035 | H5: 2040 | I5: 2045 | J5: 2050
A6: AL | B6: RES_Biomass
A7: AT | B7: RES_Biomass | C7: 152.79727 | D7: 169.39793 | E7: 161.17087 | F7: 152.9438 | G7: 147.18486 | H7: 141.42592 | I7: 137.39466 | J7: 133.3634
A8: BA | B8: RES_Biomass
A9: BE | B9: RES_Biomass | C9: 93.198168 | D9: 96.71508 | E9: 96.484806 | F9: 96.254532 | G9: 96.09334 | H9: 95.932148 | I9: 95.819314 | J9: 95.70648
A10: BG | B10: RES_Biomass | C10: 102.32539 | D10: 109.94537 | E10: 112.68772 | F10: 115.43008 | G10: 117.34972 | H10: 119.26937 | I10: 120.61313 | J10: 121.95688
A11: CH | B11: RES_Biomass | C11: 152.79727 | D11: 169.39793 | E11: 161.17087 | F11: 152.9438 | G11: 147.18486 | H11: 141.42592 | I11: 137.39466 | J11: 133.3634
A12: CZ | B12: RES_Biomass | C12: 144.3818 | D12: 151.56216 | E12: 154.9116 | F12: 158.26104 | G12: 160.60565 | H12: 162.95026 | I12: 164.59148 | J12: 166.23271
A13: DE | B13: RES_Biomass | C13: 716.88483 | D13: 810.98316 | E13: 769.59664 | F13: 728.21012 | G13: 699.23956 | H13: 670.269 | I13: 649.9896 | J13: 629.71021
A14: DK | B14: RES_Biomass | C14: 71.845488 | D14: 87.9228 | E14: 85.51539 | F14: 83.10798 | G14: 81.422793 | H14: 79.737606 | I14: 78.557975 | J14: 77.378344
A15: ES | B15: RES_Biomass | C15: 468.23078 | D15: 508.27752 | E15: 496.03113 | F15: 483.78474 | G15: 475.21227 | H15: 466.63979 | I15: 460.63906 | J15: 454.63833
A16: FI | B16: RES_Biomass | C16: 295.44154 | D16: 364.41907 | E16: 322.27893 | F16: 280.13879 | G16: 250.64069 | H16: 221.14259 | I16: 200.49392 | J16: 179.84525
A17: FR | B17: RES_Biomass | C17: 663.44033 | D17: 828.48398 | E17: 801.7722 | F17: 775.06042 | G17: 756.36217 | H17: 737.66392 | I17: 724.57514 | J17: 711.48637
A18: GR | B18: RES_Biomass | C18: 96.149862 | D18: 93.909924 | E18: 103.89544 | F18: 113.88096 | G18: 120.87082 | H18: 127.86069 | I18: 132.75359 | J18: 137.64649
A19: HR | B19: RES_Biomass | C19: 54.6 | D19: 66.818182 | E19: 64.988636 | F19: 63.159091 | G19: 61.878409 | H19: 60.597727 | I19: 59.70125 | J19: 58.804773
A20: HU | B20: RES_Biomass | C20: 150.8504 | D20: 186.14513 | E20: 183.38184 | F20: 180.61855 | G20: 178.68425 | H20: 176.74995 | I20: 175.39594 | J20: 174.04193
... A23: LU | B23: RES_Biomass | C23: 2.114334 | D23: 2.30274 | E23: 2.114334 | F23: 1.925928 | G23: 1.7940438 | H23: 1.6621596 | I23: 1.5698407 | J23: 1.4775217
A24: ME | B24: RES_Biomass
A25: MK | B25: RES_Biomass
A26: NL | B26: RES_Biomass | C26: 63.032274 | D26: 68.0355 | E26: 64.183644 | F26: 60.331788 | G26: 57.635489 | H26: 54.93919 | I26: 53.05178 | J26: 51.164371
A27: NO | B27: RES_Biomass | C27: 377.54 | D27: 407.50747 | E27: 384.43628 | F27: 361.36509 | G27: 345.21525 | H27: 329.06542 | I27: 317.76053 | J27: 306.45565
A28: PL | B28: RES_Biomass | C28: 376.05838 | D28: 461.76217 | E28: 428.79112 | F28: 395.82007 | G28: 372.74034 | H28: 349.6606 | I28: 333.50479 | J28: 317.34897
A29: PT | B29: RES_Biomass | C29: 127.02751 | D29: 136.28034 | E29: 127.44619 | F29: 118.61204 | G29: 112.42814 | H29: 106.24424 | I29: 101.9155 | J29: 97.586772
A30: RO | B30: RES_Biomass | C30: 220.60249 | D30: 252.1291 | E30: 258.49303 | F30: 264.85697 | G30: 269.31172 | H30: 273.76648 | I30: 276.88481 | J30: 280.00314
A31: RS | B31: RES_Biomass
A32: SE | B32: RES_Biomass | C32: 334.31598 | D32: 404.77982 | E32: 357.40618 | F32: 310.03254 | G32: 276.87099 | H32: 243.70944 | I32: 220.49636 | J32: 197.28327
A33: SI | B33: RES_Biomass | C33: 20.954934 | D33: 23.153004 | E33: 24.325308 | F33: 25.497612 | G33: 26.318225 | H33: 27.138838 | I33: 27.713267 | J33: 28.287696
A34: SK | B34: RES_Biomass | C34: 68.119236 | D34: 81.810072 | E34: 82.626498 | F34: 83.442924 | G34: 84.014422 | H34: 84.58592 | I34: 84.985969 | J34: 85.386018
A35: UA | B35: RES_Biomass
A36: UK | B36: RES_Biomass | C36: 424.39498 | D36: 446.89903 | E36: 442.27262 | F36: 437.6462 | G36: 434.40771 | H36: 431.16922 | I36: 428.90228 | J36: 426.63534
A37: EE | B37: RES_Biomass | C37: 35.127252 | D37: 43.207776 | E37: 38.392956 | F37: 33.578136 | G37: 30.207762 | H37: 26.837388 | I37: 24.478126 | J37: 22.118864
A38: LT | B38: RES_Biomass | C38: 43.01937 | D38: 48.525012 | E38: 51.372036 | F38: 54.21906 | G38: 56.211977 | H38: 58.204894 | I38: 59.599935 | J38: 60.994977
A39: LV | B39: RES_Biomass | C39: 45.196506 | D39: 48.734352 | E39: 54.470268 | F39: 60.206184 | G39: 64.221325 | H39: 68.236466 | I39: 71.047065 | J39: 73.857664
A40: RU | B40: RES_Biomass
A41: BY | B41: RES_Biomass
A42: TR | B42: RES_Biomass | C42: 360.0648 | D42: 379.15767 | E42: 375.23253 | F42: 371.30739 | G42: 368.55979 | H42: 365.8122 | I42: 363.88888 | J42: 361.96556
A43: NONEU_Balkan | B43: RES_Biomass | C43: 47.725392 | D43: 50.256088 | E43: 49.735824 | F43: 49.21556 | G43: 48.851375 | H43: 48.48719 | I43: 48.232261 | J43: 47.977332
A44: AL | B44: RES_Wood | C44: 0 | D44: 0 | E44: 0 | F44: 0 | G44: 0 | H44: 0 | I44: 0 | J44: 0
A45: AT | B45: RES_Wood | C45: 4.583918 | D45: 5.0819378 | E45: 4.835126 | F45: 4.5883141 | G45: 4.4155458 | H45: 4.2427775 | I45: 4.1218397 | J45: 4.0009019
A46: BA | B46: RES_Wood | C46: 0 | D46: 0 | E46: 0 | F46: 0 | G46: 0 | H46: 0 | I46: 0 | J46: 0
A47: BE | B47: RES_Wood | C47: 2.795945 | D47: 2.9014524 | E47: 2.8945442 | F47: 2.887636 | G47: 2.8828002 | H47: 2.8779645 | I47: 2.8745794 | J47: 2.8711944
A48: BG | B48: RES_Wood | C48: 3.0697618 | D48: 3.298361 | E48: 3.3806317 | F48: 3.4629023 | G48: 3.5204917 | H48: 3.5780811 | I48: 3.6183938 | J48: 3.6587064
A49: CH | B49: RES_Wood | C49: 4.583918 | D49: 5.0819378 | E49: 4.835126 | F49: 4.5883141 | G49: 4.4155458 | H49: 4.2427775 | I49: 4.1218397 | J49: 4.0009019
A50: CZ | B50: RES_Wood | C50: 4.3314539 | D50: 4.5468648 | E50: 4.647348 | F50: 4.7478312 | G50: 4.8181694 | H50: 4.8885077 | I50: 4.9377444 | J50: 4.9869812
A51: DE | B51: RES_Wood | C51: 21.506545 | D51: 24.329495 | E51: 23.087899 | F51: 21.846304 | G51: 20.977187 | H51: 20.10807 | I51: 19.499688 | J51: 18.891306
A52: DK | B52: RES_Wood | C52: 2.1553646 | D52: 2.637684 | E52: 2.5654617 | F52: 2.4932394 | G52: 2.4426838 | H52: 2.3921282 | I52: 2.3567393 | J52: 2.3213503
A53: ES | B53: RES_Wood | C53: 14.046923 | D53: 15.248326 | E53: 14.880934 | F53: 14.513542 | G53: 14.256368 | H53: 13.999194 | I53: 13.819172 | J53: 13.63915
... A271: NONEU_Balkan | B271: RES_Biogas | C271: 0.47725392 | D271: 0.50256088 | E271: 0.49735824 | F271: 0.4921556 | G271: 0.48851375 | H271: 0.4848719 | I271: 0.48232261 | J271: 0.47977332

Sheet Par_TotalAnnualMaxCapacity
A1: TotalAnnualMaxCapacity{r in REGION, t in TECHNOLOGY, y in YEAR}
A2: Maximum total (residual and new) capacity each year.
A3: Unit: GW
A5: Region | B5: Technology | C5: 2018 | D5: 2020 | E5: 2025 | F5: 2030 | G5: 2035 | H5: 2040 | I5: 2045 | J5: 2050
A6: DE | B6: A_Air | C6: 999999 | D6: 999999 | E6: 999999 | F6: 999999 | G6: 999999 | H6: 999999 | I6: 999999 | J6: 999999
A7: DE | B7: A_CCS_Capacity | C7: 999999 | D7: 999999 | E7: 999999 | F7: 999999 | G7: 999999 | H7: 999999 | I7: 999999 | J7: 999999
A8: AL | B8: D_PHS | C8: 1.375 | D8: 1.375 | E8: 1.375 | F8: 1.375 | G8: 1.375 | H8: 1.375 | I8: 1.375 | J8: 1.375
A9: AT | B9: D_PHS | C9: 13.25 | D9: 13.25 | E9: 13.25 | F9: 13.25 | G9: 13.25 | H9: 13.25 | I9: 13.25 | J9: 13.25
A10: BA | B10: D_PHS | C10: 0 | D10: 0 | E10: 0 | F10: 0 | G10: 0 | H10: 0 | I10: 0 | J10: 0
A11: BE | B11: D_PHS | C11: 0.625 | D11: 0.625 | E11: 0.625 | F11: 0.625 | G11: 0.625 | H11: 0.625 | I11: 0.625 | J11: 0.625
A12: BG | B12: D_PHS | C12: 0 | D12: 0 | E12: 0 | F12: 0 | G12: 0 | H12: 0 | I12: 0 | J12: 0
A13: CH | B13: D_PHS | C13: 5.25 | D13: 5.25 | E13: 5.25 | F13: 5.25 | G13: 5.25 | H13: 5.25 | I13: 5.25 | J13: 5.25
A14: CZ | B14: D_PHS | C14: 0.625 | D14: 0.625 | E14: 0.625 | F14: 0.625 | G14: 0.625 | H14: 0.625 | I14: 0.625 | J14: 0.625
A15: DE | B15: D_PHS | C15: 0.125 | D15: 0.125 | E15: 0.125 | F15: 0.125 | G15: 0.125 | H15: 0.125 | I15: 0.125 | J15: 0.125
A16: DK | B16: D_PHS | C16: 0 | D16: 0 | E16: 0 | F16: 0 | G16: 0 | H16: 0 | I16: 0 | J16: 0
... A361: BY | B361: RES_CSP | C361: 0 | D361: 0 | E361: 0 | F361: 0 | G361: 0 | H361: 0 | I361: 0 | J361: 0
A362: AL | B362: A_Rooftop_Commercial | C362: 13.211992 | D362: 13.211992 | E362: 13.211992 | F362: 13.211992 | G362: 13.211992 | H362: 13.211992 | I362: 13.211992 | J362: 13.211992 | M362: Europe_AT | N362: A_Rooftop_Commercial | O362: 65.820046 | P362: 65.820046 | Q362: 65.820046 | R362: 65.820046 | S362: 65.820046 | T362: 65.820046 | U362: 65.820046 | V362: 65.820046
A363: AT | B363: A_Rooftop_Commercial | C363: 49.624854 | D363: 49.624854 | E363: 49.624854 | F363: 49.624854 | G363: 49.624854 | H363: 49.624854 | I363: 49.624854 | J363: 49.624854 | M363: Europe_Balt | N363: A_Rooftop_Commercial | O363: 76.085237 | P363: 76.085237 | Q363: 76.085237 | R363: 76.085237 | S363: 76.085237 | T363: 76.085237 | U363: 76.085237 | V363: 76.085237
A364: BA | B364: A_Rooftop_Commercial | C364: 21.280094 | D364: 21.280094 | E364: 21.280094 | F364: 21.280094 | G364: 21.280094 | H364: 21.280094 | I364: 21.280094 | J364: 21.280094 | M364: Europe_BeLux | N364: A_Rooftop_Commercial | O364: 20.932851 | P364: 20.932851 | Q364: 20.932851 | R364: 20.932851 | S364: 20.932851 | T364: 20.932851 | U364: 20.932851 | V364: 20.932851
A365: BE | B365: A_Rooftop_Commercial | C365: 36.3689 | D365: 36.3689 | E365: 36.3689 | F365: 36.3689 | G365: 36.3689 | H365: 36.3689 | I365: 36.3689 | J365: 36.3689 | M365: Europe_CH | N365: A_Rooftop_Commercial | O365: 67.547331 | P365: 67.547331 | Q365: 67.547331 | R365: 67.547331 | S365: 67.547331 | T365: 67.547331 | U365: 67.547331 | V365: 67.547331
A366: BG | B366: A_Rooftop_Commercial | C366: 67.299459 | D366: 67.299459 | E366: 67.299459 | F366: 67.299459 | G366: 67.299459 | H366: 67.299459 | I366: 67.299459 | J366: 67.299459 | M366: Europe_CZ | N366: A_Rooftop_Commercial | O366: 59.925358 | P366: 59.925358 | Q366: 59.925358 | R366: 59.925358 | S366: 59.925358 | T366: 59.925358 | U366: 59.925358 | V366: 59.925358
A367: CH | B367: A_Rooftop_Commercial | C367: 31.7803 | D367: 31.7803 | E367: 31.7803 | F367: 31.7803 | G367: 31.7803 | H367: 31.7803 | I367: 31.7803 | J367: 31.7803 | M367: Europe_DE | N367: A_Rooftop_Commercial | O367: 500.14764 | P367: 500.14764 | Q367: 500.14764 | R367: 500.14764 | S367: 500.14764 | T367: 500.14764 | U367: 500.14764 | V367: 500.14764
A368: CZ | B368: A_Rooftop_Commercial | C368: 65.090134 | D368: 65.090134 | E368: 65.090134 | F368: 65.090134 | G368: 65.090134 | H368: 65.090134 | I368: 65.090134 | J368: 65.090134 | M368: Europe_DK | N368: A_Rooftop_Commercial | O368: 40.256056 | P368: 40.256056 | Q368: 40.256056 | R368: 40.256056 | S368: 40.256056 | T368: 40.256056 | U368: 40.256056 | V368: 40.256056
A369: DE | B369: A_Rooftop_Commercial | C369: 340.57605 | D369: 340.57605 | E369: 340.57605 | F369: 340.57605 | G369: 340.57605 | H369: 340.57605 | I369: 340.57605 | J369: 340.57605 | M369: Europe_FR | N369: A_Rooftop_Commercial | O369: 487.66263 | P369: 487.66263 | Q369: 487.66263 | R369: 487.66263 | S369: 487.66263 | T369: 487.66263 | U369: 487.66263 | V369: 487.66263
A370: DK | B370: A_Rooftop_Commercial | C370: 38.238329 | D370: 38.238329 | E370: 38.238329 | F370: 38.238329 | G370: 38.238329 | H370: 38.238329 | I370: 38.238329 | J370: 38.238329 | M370: Europe_GB | N370: A_Rooftop_Commercial | O370: 389.04572 | P370: 389.04572 | Q370: 389.04572 | R370: 389.04572 | S370: 389.04572 | T370: 389.04572 | U370: 389.04572 | V370: 389.04572
A371: ES | B371: A_Rooftop_Commercial | C371: 376.60506 | D371: 376.60506 | E371: 376.60506 | F371: 376.60506 | G371: 376.60506 | H371: 376.60506 | I371: 376.60506 | J371: 376.60506 | M371: Europe_Iberia | N371: A_Rooftop_Commercial | O371: 327.1547 | P371: 327.1547 | Q371: 327.1547 | R371: 327.1547 | S371: 327.1547 | T371: 327.1547 | U371: 327.1547 | V371: 327.1547
A372: FI | B372: A_Rooftop_Commercial | C372: 34.49947 | D372: 34.49947 | E372: 34.49947 | F372: 34.49947 | G372: 34.49947 | H372: 34.49947 | I372: 34.49947 | J372: 34.49947 | M372: Europe_IT | N372: A_Rooftop_Commercial | O372: 258.6854 | P372: 258.6854 | Q372: 258.6854 | R372: 258.6854 | S372: 258.6854 | T372: 258.6854 | U372: 258.6854 | V372: 258.6854
A373: FR | B373: A_Rooftop_Commercial | C373: 427.92939 | D373: 427.92939 | E373: 427.92939 | F373: 427.92939 | G373: 427.92939 | H373: 427.92939 | I373: 427.92939 | J373: 427.92939 | M373: Europe_NL | N373: A_Rooftop_Commercial | O373: 45.826851 | P373: 45.826851 | Q373: 45.826851 | R373: 45.826851 | S373: 45.826851 | T373: 45.826851 | U373: 45.826851 | V373: 45.826851
... A376: HU | B376: A_Rooftop_Commercial | C376: 75.287022 | D376: 75.287022 | E376: 75.287022 | F376: 75.287022 | G376: 75.287022 | H376: 75.287022 | I376: 75.287022 | J376: 75.287022 | M376: Europe_SouthEast | N376: A_Rooftop_Commercial | O376: 213.72792 | P376: 213.72792 | Q376: 213.72792 | R376: 213.72792 | S376: 213.72792 | T376: 213.72792 | U376: 213.72792 | V376: 213.72792
A377: IE | B377: A_Rooftop_Commercial | C377: 55.912935 | D377: 55.912935 | E377: 55.912935 | F377: 55.912935 | G377: 55.912935 | H377: 55.912935 | I377: 55.912935 | J377: 55.912935 | O377: =SUM(O362:O376) -> 3163.2445 | P377: =SUM(P362:P376) -> 3163.2445 | Q377: =SUM(Q362:Q376) -> 3163.2445 | R377: =SUM(R362:R376) -> 3163.2445 | S377: =SUM(S362:S376) -> 3163.2445 | T377: =SUM(T362:T376) -> 3163.2445 | U377: =SUM(U362:U376) -> 3163.2445 | V377: =SUM(V362:V376) -> 3163.2445
A378: IT | B378: A_Rooftop_Commercial | C378: 271.74706 | D378: 271.74706 | E378: 271.74706 | F378: 271.74706 | G378: 271.74706 | H378: 271.74706 | I378: 271.74706 | J378: 271.74706
A379: LU | B379: A_Rooftop_Commercial | C379: 2.3792738 | D379: 2.3792738 | E379: 2.3792738 | F379: 2.3792738 | G379: 2.3792738 | H379: 2.3792738 | I379: 2.3792738 | J379: 2.3792738 | M379: Europe_AT | N379: A_Rooftop_Residential | O379: 73.286615 | P379: 73.286615 | Q379: 73.286615 | R379: 73.286615 | S379: 73.286615 | T379: 73.286615 | U379: 73.286615 | V379: 73.286615
A380: ME | B380: A_Rooftop_Commercial | C380: 9.211429 | D380: 9.211429 | E380: 9.211429 | F380: 9.211429 | G380: 9.211429 | H380: 9.211429 | I380: 9.211429 | J380: 9.211429 | M380: Europe_Balt | N380: A_Rooftop_Residential | O380: 37.756469 | P380: 37.756469 | Q380: 37.756469 | R380: 37.756469 | S380: 37.756469 | T380: 37.756469 | U380: 37.756469 | V380: 37.756469
A381: MK | B381: A_Rooftop_Commercial | C381: 19.455594 | D381: 19.455594 | E381: 19.455594 | F381: 19.455594 | G381: 19.455594 | H381: 19.455594 | I381: 19.455594 | J381: 19.455594 | M381: Europe_BeLux | N381: A_Rooftop_Residential | O381: 19.999865 | P381: 19.999865 | Q381: 19.999865 | R381: 19.999865 | S381: 19.999865 | T381: 19.999865 | U381: 19.999865 | V381: 19.999865
A382: NL | B382: A_Rooftop_Commercial | C382: 54.043505 | D382: 54.043505 | E382: 54.043505 | F382: 54.043505 | G382: 54.043505 | H382: 54.043505 | I382: 54.043505 | J382: 54.043505 | M382: Europe_CH | N382: A_Rooftop_Residential | O382: 74.991118 | P382: 74.991118 | Q382: 74.991118 | R382: 74.991118 | S382: 74.991118 | T382: 74.991118 | U382: 74.991118 | V382: 74.991118
A383: NO | B383: A_Rooftop_Commercial | C383: 20.393776 | D383: 20.393776 | E383: 20.393776 | F383: 20.393776 | G383: 20.393776 | H383: 20.393776 | I383: 20.393776 | J383: 20.393776 | M383: Europe_CZ | N383: A_Rooftop_Residential | O383: 54.891598 | P383: 54.891598 | Q383: 54.891598 | R383: 54.891598 | S383: 54.891598 | T383: 54.891598 | U383: 54.891598 | V383: 54.891598
A384: PL | B384: A_Rooftop_Commercial | C384: 228.41029 | D384: 228.41029 | E384: 228.41029 | F384: 228.41029 | G384: 228.41029 | H384: 228.41029 | I384: 228.41029 | J384: 228.41029 | M384: Europe_DE | N384: A_Rooftop_Residential | O384: 416.83053 | P384: 416.83053 | Q384: 416.83053 | R384: 416.83053 | S384: 416.83053 | T384: 416.83053 | U384: 416.83053 | V384: 416.83053
A385: PT | B385: A_Rooftop_Commercial | C385: 59.651794 | D385: 59.651794 | E385: 59.651794 | F385: 59.651794 | G385: 59.651794 | H385: 59.651794 | I385: 59.651794 | J385: 59.651794 | M385: Europe_DK | N385: A_Rooftop_Residential | O385: 20.877473 | P385: 20.877473 | Q385: 20.877473 | R385: 20.877473 | S385: 20.877473 | T385: 20.877473 | U385: 20.877473 | V385: 20.877473
A386: RO | B386: A_Rooftop_Commercial | C386: 188.98232 | D386: 188.98232 | E386: 188.98232 | F386: 188.98232 | G386: 188.98232 | H386: 188.98232 | I386: 188.98232 | J386: 188.98232 | M386: Europe_FR | N386: A_Rooftop_Residential | O386: 520.14152 | P386: 520.14152 | Q386: 520.14152 | R386: 520.14152 | S386: 520.14152 | T386: 520.14152 | U386: 520.14152 | V386: 520.14152
A387: RS | B387: A_Rooftop_Commercial | C387: 79.087476 | D387: 79.087476 | E387: 79.087476 | F387: 79.087476 | G387: 79.087476 | H387: 79.087476 | I387: 79.087476 | J387: 79.087476 | M387: Europe_GB | N387: A_Rooftop_Residential | O387: 211.5888 | P387: 211.5888 | Q387: 211.5888 | R387: 211.5888 | S387: 211.5888 | T387: 211.5888 | U387: 211.5888 | V387: 211.5888
A388: SE | B388: A_Rooftop_Commercial | C388: 50.984439 | D388: 50.984439 | E388: 50.984439 | F388: 50.984439 | G388: 50.984439 | H388: 50.984439 | I388: 50.984439 | J388: 50.984439 | M388: Europe_Iberia | N388: A_Rooftop_Residential | O388: 670.04415 | P388: 670.04415 | Q388: 670.04415 | R388: 670.04415 | S388: 670.04415 | T388: 670.04415 | U388: 670.04415 | V388: 670.04415
A389: SI | B389: A_Rooftop_Commercial | C389: 9.177199 | D389: 9.177199 | E389: 9.177199 | F389: 9.177199 | G389: 9.177199 | H389: 9.177199 | I389: 9.177199 | J389: 9.177199 | M389: Europe_IT | N389: A_Rooftop_Residential | O389: 702.85879 | P389: 702.85879 | Q389: 702.85879 | R389: 702.85879 | S389: 702.85879 | T389: 702.85879 | U389: 702.85879 | V389: 702.85879
A390: SK | B390: A_Rooftop_Commercial | C390: 31.100508 | D390: 31.100508 | E390: 31.100508 | F390: 31.100508 | G390: 31.100508 | H390: 31.100508 | I390: 31.100508 | J390: 31.100508 | M390: Europe_NL | N390: A_Rooftop_Residential | O390: 23.408222 | P390: 23.408222 | Q390: 23.408222 | R390: 23.408222 | S390: 23.408222 | T390: 23.408222 | U390: 23.408222 | V390: 23.408222
... A393: EE | B393: A_Rooftop_Commercial | C393: 12.406213 | D393: 12.406213 | E393: 12.406213 | F393: 12.406213 | G393: 12.406213 | H393: 12.406213 | I393: 12.406213 | J393: 12.406213 | M393: Europe_SouthEast | N393: A_Rooftop_Residential | O393: 287.87535 | P393: 287.87535 | Q393: 287.87535 | R393: 287.87535 | S393: 287.87535 | T393: 287.87535 | U393: 287.87535 | V393: 287.87535
A394: LT | B394: A_Rooftop_Commercial | C394: 35.179263 | D394: 35.179263 | E394: 35.179263 | F394: 35.179263 | G394: 35.179263 | H394: 35.179263 | I394: 35.179263 | J394: 35.179263 | O394: =SUM(O379:O393) -> 3407.8773 | P394: =SUM(P379:P393) -> 3407.8773 | Q394: =SUM(Q379:Q393) -> 3407.8773 | R394: =SUM(R379:R393) -> 3407.8773 | S394: =SUM(S379:S393) -> 3407.8773 | T394: =SUM(T379:T393) -> 3407.8773 | U394: =SUM(U379:U393) -> 3407.8773 | V394: =SUM(V379:V393) -> 3407.8773
A395: LV | B395: A_Rooftop_Commercial | C395: 23.112946 | D395: 23.112946 | E395: 23.112946 | F395: 23.112946 | G395: 23.112946 | H395: 23.112946 | I395: 23.112946 | J395: 23.112946
A396: RU | B396: A_Rooftop_Commercial | C396: 0 | D396: 0 | E396: 0 | F396: 0 | G396: 0 | H396: 0 | I396: 0 | J396: 0
A397: BY | B397: A_Rooftop_Commercial | C397: 0 | D397: 0 | E397: 0 | F397: 0 | G397: 0 | H397: 0 | I397: 0 | J397: 0
A398: AL | B398: A_Rooftop_Residential | C398: 14.233755 | D398: 14.233755 | E398: 14.233755 | F398: 14.233755 | G398: 14.233755 | H398: 14.233755 | I398: 14.233755 | J398: 14.233755
A399: AT | B399: A_Rooftop_Residential | C399: 53.462643 | D399: 53.462643 | E399: 53.462643 | F399: 53.462643 | G399: 53.462643 | H399: 53.462643 | I399: 53.462643 | J399: 53.462643
A400: BA | B400: A_Rooftop_Residential | C400: 22.925812 | D400: 22.925812 | E400: 22.925812 | F400: 22.925812 | G400: 22.925812 | H400: 22.925812 | I400: 22.925812 | J400: 22.925812
A401: BE | B401: A_Rooftop_Residential | C401: 39.181526 | D401: 39.181526 | E401: 39.181526 | F401: 39.181526 | G401: 39.181526 | H401: 39.181526 | I401: 39.181526 | J401: 39.181526
A402: BG | B402: A_Rooftop_Residential | C402: 72.504133 | D402: 72.504133 | E402: 72.504133 | F402: 72.504133 | G402: 72.504133 | H402: 72.504133 | I402: 72.504133 | J402: 72.504133
A403: CH | B403: A_Rooftop_Residential | C403: 34.238063 | D403: 34.238063 | E403: 34.238063 | F403: 34.238063 | G403: 34.238063 | H403: 34.238063 | I403: 34.238063 | J403: 34.238063
A404: CZ | B404: A_Rooftop_Residential | C404: 70.123947 | D404: 70.123947 | E404: 70.123947 | F404: 70.123947 | G404: 70.123947 | H404: 70.123947 | I404: 70.123947 | J404: 70.123947
A405: DE | B405: A_Rooftop_Residential | C405: 366.91485 | D405: 366.91485 | E405: 366.91485 | F405: 366.91485 | G405: 366.91485 | H405: 366.91485 | I405: 366.91485 | J405: 366.91485
A406: DK | B406: A_Rooftop_Residential | C406: 41.19553 | D406: 41.19553 | E406: 41.19553 | F406: 41.19553 | G406: 41.19553 | H406: 41.19553 | I406: 41.19553 | J406: 41.19553
... A432: RU | B432: A_Rooftop_Residential | C432: 0 | D432: 0 | E432: 0 | F432: 0 | G432: 0 | H432: 0 | I432: 0 | J432: 0
A433: BY | B433: A_Rooftop_Residential | C433: 0
A434: AL | B434: RES_PV_Rooftop_Commercial | C434: 999999 | D434: 999999 | E434: 999999 | F434: 999999 | G434: 999999 | H434: 999999 | I434: 999999 | J434: 999999
A435: AT | B435: RES_PV_Rooftop_Commercial | C435: 999999 | D435: 999999 | E435: 999999 | F435: 999999 | G435: 999999 | H435: 999999 | I435: 999999 | J435: 999999
A436: BA | B436: RES_PV_Rooftop_Commercial | C436: 999999 | D436: 999999 | E436: 999999 | F436: 999999 | G436: 999999 | H436: 999999 | I436: 999999 | J436: 999999
A437: BE | B437: RES_PV_Rooftop_Commercial | C437: 999999 | D437: 999999 | E437: 999999 | F437: 999999 | G437: 999999 | H437: 999999 | I437: 999999 | J437: 999999
A438: BG | B438: RES_PV_Rooftop_Commercial | C438: 999999 | D438: 999999 | E438: 999999 | F438: 999999 | G438: 999999 | H438: 999999 | I438: 999999 | J438: 999999
A439: CH | B439: RES_PV_Rooftop_Commercial | C439: 999999 | D439: 999999 | E439: 999999 | F439: 999999 | G439: 999999 | H439: 999999 | I439: 999999 | J439: 999999
A440: CZ | B440: RES_PV_Rooftop_Commercial | C440: 999999 | D440: 999999 | E440: 999999 | F440: 999999 | G440: 999999 | H440: 999999 | I440: 999999 | J440: 999999
A441: DE | B441: RES_PV_Rooftop_Commercial | C441: 999999 | D441: 999999 | E441: 999999 | F441: 999999 | G441: 999999 | H441: 999999 | I441: 999999 | J441: 999999
A442: DK | B442: RES_PV_Rooftop_Commercial | C442: 999999 | D442: 999999 | E442: 999999 | F442: 999999 | G442: 999999 | H442: 999999 | I442: 999999 | J442: 999999
A443: ES | B443: RES_PV_Rooftop_Commercial | C443: 999999 | D443: 999999 | E443: 999999 | F443: 999999 | G443: 999999 | H443: 999999 | I443: 999999 | J443: 999999
A444: FI | B444: RES_PV_Rooftop_Commercial | C444: 999999 | D444: 999999 | E444: 999999 | F444: 999999 | G444: 999999 | H444: 999999 | I444: 999999 | J444: 999999
A445: FR | B445: RES_PV_Rooftop_Commercial | C445: 999999 | D445: 999999 | E445: 999999 | F445: 999999 | G445: 999999 | H445: 999999 | I445: 999999 | J445: 999999
... A647: TR | B647: D_PHS | C647: 0 | D647: 0 | E647: 0 | F647: 0 | G647: 0 | H647: 0 | I647: 0 | J647: 0
A648: TR | B648: RES_Wind_Onshore_Avg | C648: 101.14 | D648: 101.14 | E648: 101.14 | F648: 101.14 | G648: 101.14 | H648: 101.14 | I648: 101.14 | J648: 101.14 | K648: https://sci-hub.se/10.1016/j.solener.2017.09.030
A649: TR | B649: RES_Wind_Onshore_Inf | C649: 101.14 | D649: 101.14 | E649: 101.14 | F649: 101.14 | G649: 101.14 | H649: 101.14 | I649: 101.14 | J649: 101.14 | K649: https://sci-hub.se/10.1016/j.solener.2017.09.030
A650: TR | B650: RES_Wind_Onshore_Opt | C650: 101.14 | D650: 101.14 | E650: 101.14 | F650: 101.14 | G650: 101.14 | H650: 101.14 | I650: 101.14 | J650: 101.14 | K650: https://sci-hub.se/10.1016/j.solener.2017.09.030
A651: TR | B651: RES_Wind_Offshore_Transitional | C651: 13 | D651: 13 | E651: 13 | F651: 13 | G651: 13 | H651: 13 | I651: 13 | J651: 13 | K651: https://sci-hub.se/10.1016/j.solener.2017.09.030
A652: TR | B652: RES_Wind_Offshore_Shallow | C652: 13 | D652: 13 | E652: 13 | F652: 13 | G652: 13 | H652: 13 | I652: 13 | J652: 13 | K652: https://sci-hub.se/10.1016/j.solener.2017.09.030
A653: TR | B653: RES_Wind_Offshore_Deep | C653: 13 | D653: 13 | E653: 13 | F653: 13 | G653: 13 | H653: 13 | I653: 13 | J653: 13 | K653: https://sci-hub.se/10.1016/j.solener.2017.09.030
A654: TR | B654: RES_PV_Utility_Avg | C654: 191.035 | D654: 191.035 | E654: 191.035 | F654: 191.035 | G654: 191.035 | H654: 191.035 | I654: 191.035 | J654: 191.035 | K654: https://sci-hub.se/10.1016/j.solener.2017.09.030
A655: TR | B655: RES_PV_Utility_Inf | C655: 191.035 | D655: 191.035 | E655: 191.035 | F655: 191.035 | G655: 191.035 | H655: 191.035 | I655: 191.035 | J655: 191.035 | K655: https://sci-hub.se/10.1016/j.solener.2017.09.030
A656: TR | B656: RES_PV_Utility_Opt | C656: 191.035 | D656: 191.035 | E656: 191.035 | F656: 191.035 | G656: 191.035 | H656: 191.035 | I656: 191.035 | J656: 191.035 | K656: https://sci-hub.se/10.1016/j.solener.2017.09.030
A657: TR | B657: RES_CSP | C657: 9168.12 | D657: 9168.12 | E657: 9168.12 | F657: 9168.12 | G657: 9168.12 | H657: 9168.12 | I657: 9168.12 | J657: 9168.12 | K657: https://sci-hub.se/10.1016/j.solener.2017.09.030
A658: TR | B658: A_Rooftop_Commercial | C658: 70.639303 | D658: 70.639303 | E658: 70.639303 | F658: 70.639303 | G658: 70.639303 | H658: 70.639303 | I658: 70.639303 | J658: 70.639303 | K658: https://sci-hub.se/10.1016/j.solener.2017.09.030
A659: TR | B659: A_Rooftop_Residential | C659: 100.18881 | D659: 100.18881 | E659: 100.18881 | F659: 100.18881 | G659: 100.18881 | H659: 100.18881 | I659: 100.18881 | J659: 100.18881 | K659: https://sci-hub.se/10.1016/j.solener.2017.09.030
... A667: TR | B667: RES_Hydro_Small | C667: 15.08 | D667: 15.08 | E667: 15.08 | F667: 15.08 | G667: 15.08 | H667: 15.08 | I667: 15.08 | J667: 15.08 | K667: https://sci-hub.se/10.1016/j.solener.2017.09.030
A668: AT | B668: RES_PV_Utility_Inf | C668: 13.041779 | D668: 13.041779 | E668: 13.041779 | F668: 13.041779 | G668: 13.041779 | H668: 13.041779 | I668: 13.041779 | J668: 13.041779
A669: BE | B669: RES_PV_Utility_Inf | C669: 12.642348 | D669: 12.642348 | E669: 12.642348 | F669: 12.642348 | G669: 12.642348 | H669: 12.642348 | I669: 12.642348 | J669: 12.642348
A670: BG | B670: RES_PV_Utility_Inf | C670: 7.3091247 | D670: 7.3091247 | E670: 7.3091247 | F670: 7.3091247 | G670: 7.3091247 | H670: 7.3091247 | I670: 7.3091247 | J670: 7.3091247
A671: CZ | B671: RES_PV_Utility_Inf | C671: 16.458284 | D671: 16.458284 | E671: 16.458284 | F671: 16.458284 | G671: 16.458284 | H671: 16.458284 | I671: 16.458284 | J671: 16.458284
